Workbook

Sheet 表格说明
A1: 中国银保监会银行业金融机构监管数据标准化规范 数据结构一览表说明
A2: 1. 标准化数据结构以表形式组织。一个或多个表归属于一个分类，每个表包含多个数据项。
A3: 2. 数据项已按表进行分类组合，通过使用最左侧导航按钮，可以展开或隐藏各表数据项，便于查看。
A4: 3. 数据结构备注中PK为监管部门作为唯一性约束的参考条件，含有多个PK的，表示联合主键的参考，并不作为主外键唯一性约束的要求，银行机构可根据数据实际入库情况作出调整。
A5: 4. “数据元说明”定义数据项的类型及长度的表示形式。
A6: 5. 数据项中备注“关联数据项：[表名].[数据项名]”表示该数据项取值的参考数据项。例如“关联数据项:机构信息表.内部机构号”表示该数据项应和“机构信息表”中的“内部机构号”数据项取值一致。
A7: 6. Cn 表示n个字节的固定长度，相应的字符长度由字符编码集确定。UTF-8的中文字符占3个字节。
A8: 7. C..n 表示最多为n个字节的可变长度。UTF-8的中文字符占3个字节。
A9: 8. I 表示整数可计算形式。
A10: 9. I..n 表示最多为n位的整数可计算形式。
A11: 10. Dw.d 表示十进制小数可计算形式，w表示包含小数点前后字符位在内的整个字段最多字符位数，d表示小数点后的最多字符位数。
A12: 11. F 表示任意长度浮点数。
... A14: 数据治理体系公众号推荐

Sheet 表结构总览
A1: 主题 | B1: 主题编号 | C1: 数据表代码 | D1: 数据表名 | E1: 数据表编号 | F1: 报送模式 | G1: 报送要求 | H1: 修改说明
A2: 公共信息 | B2: 001
C3: JGXXB | D3: 机构信息表 | E3: 101 | F3: 全量表，报送截至采集日有效的数据，以及上一采集日至采集日期间结清、失效、终结等所有视为终态的数据。 | G3: 本表报送银行机构或业务中心信息，业务中心包含管理机构、营业机构、内设机构、虚拟机构。对于营业机构、内设机构、虚拟机构，银行机构代码、金融许可证号等字段可以取上级机构或者本级实体机构对应的信息（优先取本级实体机构）。境外机构也需要报送，根据实际情况无法填报的字段可以为空。子公司不必报送（理财子公司应报送）。内设机构标准：承担业务归属的机构。机构永久关停、撤销等情况的，在报送最后状态的次月可不再报送。 | H3: 修改
C4: YGB | D4: 员工表 | E4: 102 | F4: 全量表，报送截至采集日有效的数据，以及上一采集日至采集日期间结清、失效、终结等所有视为终态的数据。 | G4: 在职类员工需每月报送。员工状态转为离职的，在报送该员工最后状态的次月可不再报送。子公司员工不用报送（理财子公司应报送）。 | H4: 修改
C5: GYB | D5: 柜员表 | E5: 103 | F5: 全量表，报送截至采集日有效的数据，以及上一采集日至采集日期间结清、失效、终结等所有视为终态的数据。 | G5: 包含实体柜员和虚拟柜员。为虚拟柜员时，工号、银行机构代码等字段依业务实际填列（若无则置空），如报送虚拟柜员，则通过“柜员类型”字段进行区分；柜员状态转为注销、无效等时，可在报送该条数据最终状态的次月不再报送。 | H5: 修改
C6: GWXXB | D6: 岗位信息表 | E6: 104 | F6: 全量表，报送截至采集日有效的数据，以及上一采集日至采集日期间结清、失效、终结等所有视为终态的数据。 | G6: 银行机构内设立的所有岗位的相关信息，至少应包括核心和人力资源系统中的所有岗位信息。撤销的岗位于次月不再报送。 | H6: 修改
C7: JGGXB | D7: 机构关系表 | E7: 105 | F7: 全量表，报送截至采集日有效的数据，以及上一采集日至采集日期间结清、失效、终结等所有视为终态的数据。 | G7: 报送范围应包括所有进行账务处理的机构，至少应包括总行、分行、支行等实体机构和省级汇总、地市级汇总、法人汇总、分行汇总。会计全科目表中的机构在机构关系表中都需要报送，每次全量报送。 | H7: 修改
C8: GDJGLFXXB | D8: 股东及关联方信息表 | E8: 106 | F8: 全量表，报送截至采集日有效的数据，以及上一采集日至采集日期间结清、失效、终结等所有视为终态的数据。 | G8: 填报银行股东及银行关联方相关信息。股东：对于已上市银行，需填报持有或控制1%以上股份或表决权，及虽不足1%但对商业银行经营管理有重大影响的股东。未上市银行机构应报送所有的对公、个人股东信息。包括金融产品。 关联方：参照《银行保险机构关联交易管理办法》（中国银行保险监督管理委员会令〔2022〕1号）第二章规定。 | H8: 修改
A9: 客户信息 | B9: 002
C10: GRJCXXB | D10: 个人基础信息表 | E10: 201 | F10: 全量表，报送截至采集日有效的数据，以及上一采集日至采集日期间结清、失效、终结等所有视为终态的数据。 | G10: 报送范围包括本行客户及本行客户的担保、配偶、亲属关系所涉及到的个人信息。包括核心系统、客户关系系统、信用卡系统等各类信息系统采集的个人客户信息。 | H10: 修改
C11: GRKHGXB | D11: 个人客户关系表 | E11: 202 | F11: 全量表，报送截至采集日有效的数据，以及上一采集日至采集日期间结清、失效、终结等所有视为终态的数据。 | G11: 个人客户的所有关联关系，包括个人对个人、个人对对公的相关关联关系。本人为本人担保的关系不报送。 | H11: 修改
C12: DGKHXXB | D12: 对公客户信息表 | E12: 203 | F12: 全量表，报送截至采集日有效的数据，以及上一采集日至采集日期间结清、失效、终结等所有视为终态的数据。 | G12: 银行机构所有对公客户的基本信息。集团类的虚拟客户的客户信息要上报。银行对企业分公司等非法人机构授信的，视同单一法人客户报送。以机构名义登记客户资料的个体工商户、私营业主应纳入本表填报范围。对于同业客户、政府机关、境外客户，若无法获取相关信息无法填报的数据项，允许为空。对于不再列为银行客户的数据不报送。 | H12: 修改
C13: DGKHCWXXB | D13: 对公客户财务信息表 | E13: 204 | F13: 增量表，报送上一采集日至采集日期间新增的数据。 | G13: 报送本月源系统中新收集的对公客户财务信息。对于非授信客户、负债类客户、离岸对公客户、机关事业单位、未达到税务部门建账标准的个体工商户等无需报送。 | H13: 新增
C14: JTKHB | D14: 集团客户表 | E14: 205 | F14: 全量表，报送截至采集日有效的数据，以及上一采集日至采集日期间结清、失效、终结等所有视为终态的数据。 | G14: 报送在本行纳入集团授信的客户信息，包括供应链客户信息。以集团成员为最小粒度报送。同业集团客户信息无需报送。 | H14: 新增
C15: GLGXB | D15: 关联关系表 | E15: 206 | F15: 全量表，报送截至采集日有效的数据，以及上一采集日至采集日期间结清、失效、终结等所有视为终态的数据。 | G15: 报送机构收集的对公客户以及机构互联网贷款合作方的关联关系。应包括母公司，子公司，与该企业受同一母公司控制的其他企业，与该企业实施共同控制的投资方，对该企业施加重大影响的投资方，该企业的合营企业，该企业的联营企业，该企业的主要投资者个人及与其关系密切的家庭成员，该企业或其母公司的关键管理人员及与其关系密切的家庭成员，该企业主要投资者个人、关键管理人员或与其关系密切的家庭成员控制、共同控制或施加重大影响的其他企业，供应链上下游，担保关系等。应采取能采尽采的原则，包括但不限于授信尽职调查、外部数据源查询等途径获知的关联关系。同一关联方兼任或具有多重关联关系的，分多条进行报送。 | H15: 修改
A16: 卡片信息 | B16: 003
C17: JJKXXB | D17: 借记卡信息表 | E17: 301 | F17: 全量表，报送截至采集日有效的数据，以及上一采集日至采集日期间结清、失效、终结等所有视为终态的数据。 | G17: 个人和对公客户在银行机构开办的借记卡信息，指只能存取款而无法透支的卡片信息。当卡片状态为“注销”时，可在报送最后状态的次月不再报送。 | H17: 修改
C18: CZXXB | D18: 存折信息表 | E18: 302 | F18: 全量表，报送截至采集日有效的数据，以及上一采集日至采集日期间结清、失效、终结等所有视为终态的数据。 | G18: 个人和对公客户在银行机构开办的存折信息，包括存折和存单。当存折状态为“注销”时，可在报送最后状态的次月不再报送。 | H18: 修改
C19: SDSHXXB | D19: 收单商户信息表 | E19: 303 | F19: 全量表，报送截至采集日有效的数据，以及上一采集日至采集日期间结清、失效、终结等所有视为终态的数据。 | G19: 报送本行因线下线上收单业务而拓展的线下POS终端、线上终端以及二维码商户的信息。同一商户存在多个POS终端的，按多条报送。商户状态为“失效”或“注销”等状态的，在报送最后状态的次月可不再报送。 | H19: 新增
A20: 会计记账信息 | B20: 004
C21: ZZKJQKMB | D21: 总账会计全科目表 | E21: 401 | F21: 全量表，报送截至采集日有效的数据，以及上一采集日至采集日期间结清、失效、终结等所有视为终态的数据。 | G21: 本表报送银行机构会计记账使用的有余额的或余额变动的会计科目。只报境内银行（不报子公司），包括总行、一级分行、二级分行、一级支行（最多报4级）。如果发生新老科目变更，在当期数据中报送最新科目即可。每月最后一天数据应同时报送按月和按日为周期的会计数据，每年最后一天数据应同时报送按日、按月、季、半年、年为周期的会计数据，以此类推。只报送人民币和本外币合计。 | H21: 修改
C22: NBKMDZB | D22: 内部科目对照表 | E22: 402 | F22: 全量表，报送截至采集日有效的数据，以及上一采集日至采集日期间结清、失效、终结等所有视为终态的数据。 | G22: 本表报送总账会计全科目的上下级对应关系，以会计科目为最小粒度报送。内部科目对照表由法人机构统一确定，分支机构按同一内容报送。报送科目必须与当期《总账会计全科目表》中的科目一致。此表首次采集为全量采集，后续采集如有变化，需全量报送。 | H22: 修改
C23: GRCKFHZ | D23: 个人存款分户账 | E23: 403 | F23: 全量表，报送截至采集日有效的数据，以及上一采集日至采集日期间结清、失效、终结等所有视为终态的数据。 | G23: 填报个人存款账户信息，个人存款账户和对公存款账户按照《人民币银行结算账户管理办法》（中国人民银行令2003年第5号）划分。信用卡业务不在本表中填报。个体工商户、私营业主以个人名义开立的存款账户计入本表，以营业执照等证件开立的对公账户不计入本表。以存款账号为最小粒度报送，如账户注销或终结，在报送该账户最终状态后的次月可不再报送。 | H23: 修改
C24: GRCKFHZMX | D24: 个人存款分户账明细记录 | E24: 404 | F24: 增量表，报送上一采集日至采集日期间新增的数据。 | G24: 除计息、扣利息税外，所有影响个人存款账户余额变动的交易信息，包括结息交易，不包括查询交易。 | H24: 修改
C25: DGCKFHZ | D25: 对公存款分户账 | E25: 405 | F25: 全量表，报送截至采集日有效的数据，以及上一采集日至采集日期间结清、失效、终结等所有视为终态的数据。 | G25: 填报银行机构吸收的除个人以外的机构（包括企业、财政部门、社保基金、部队、住房公积金、社会团体、同业机构等）开立的所有存款账户信息。个人存款账户和对公存款账户按照《人民币银行结算账户管理办法》（中国人民银行令2003年第5号）划分。个体工商户、私营业主以营业执照等证件开立的对公账户计入本表，以个人名义开立的账户不计入本表。以存款账号为最小颗粒报送，如账户注销或终结，在报送该账户最终状态后的次月可不再报送。 | H25: 修改
C26: DGCKFHZMX | D26: 对公存款分户账明细记录 | E26: 406 | F26: 增量表，报送上一采集日至采集日期间新增的数据。 | G26: 除计息、扣利息税外，所有影响对公存款账户余额变动的交易信息，包括结息交易，不包括查询交易。 | H26: 修改
C27: NBFHZ | D27: 内部分户账 | E27: 407 | F27: 全量表，报送截至采集日有效的数据，以及上一采集日至采集日期间结清、失效、终结等所有视为终态的数据。 | G27: 根据会计核算科目，除单列账之外的科目原则上都归入内部账采集；单列账报送至信用卡、对公/个人等分户账中；资本账户需要报送。以内部分户账号为最小颗粒报送，如账户注销或终结，在报送该账户最终状态后的次月可不再报送。交易与核算分离的机构，应根据总账科目中划分出对应内部分户账性质的科目，自定义内部分户账号进行报送。 | H27: 修改
C28: NBFHZMX | D28: 内部分户账明细记录 | E28: 408 | F28: 增量表，报送上一采集日至采集日期间新增的数据。 | G28: 根据会计核算科目，除单列账之外的科目原则上都归入内部账采集；单列账报送至信用卡、对公/个人等分户账中；资本账户需要报送。 | H28: 修改
C29: GRXDFHZ | D29: 个人信贷分户账 | E29: 409 | F29: 全量表，报送截至采集日有效的数据，以及上一采集日至采集日期间结清、失效、终结等所有视为终态的数据。 | G29: 填报以个人名义在银行机构所开立的信贷账户信息。不报送信用卡业务。表外业务只报送委托贷款（非现金管理项下），其他不报送。个体工商户、私营业主以个人名义开立的信贷分户账计入本表，以营业执照等证件开立的对公信贷分户账不计入本表。以信贷借据号为最小粒度报送，借据结清、核销或转让的，可在报送最后状态的次月不再报送。账户状态为“销户”时，也可于次月不再报送。 | H29: 修改
C30: GRXDFHZMX | D30: 个人信贷分户账明细记录 | E30: 410 | F30: 增量表，报送上一采集日至采集日期间新增的数据。 | G30: 所有影响个人信贷账户余额或利息变动的交易信息，包括还本、还息，不包括查询交易。贷款核销或者转让（包括资产证券化）也应该在本表体现：明细科目填报本金科目，交易金额为核销或转让前本金余额，余额填报为0，交易对手填写借款人自身信息，摘要中标明核销或者转让交易。 | H30: 修改
C31: DGXDFHZ | D31: 对公信贷分户账 | E31: 411 | F31: 全量表，报送截至采集日有效的数据，以及上一采集日至采集日期间结清、失效、终结等所有视为终态的数据。 | G31: 除个人以外的各类机构（包括企业、机关团体、社保基金、部队、住房公积金）为开展各项信贷业务，在银行机构所开立的信贷账户信息。个体工商户、私营业主以营业执照等证件开立的对公信贷分户账计入本表，以个人名义开立的信贷分户账不计入本表。贷款核销和转让（包括资产证券化）相关内容应在本表填报；尤其核算方式变化（即科目变化），需要报送变化量。表外业务只报送委托贷款（非现金管理项下），其他不报送。对于票据贴现和买断式转贴现，可以填报为信贷分户账号=信贷借据号=票据号码；对于其他若没有对应信贷分户账号的业务，可以填报为信贷分户账号=信贷借据号=业务编号。以信贷借据号为最小粒度报送，借据结清、核销或转让的，可在报送最后状态的次月不再报送。账户状态为“销户”时，也可于次月不再报送。 | H31: 修改
C32: DGXDFHZMX | D32: 对公信贷分户账明细记录 | E32: 412 | F32: 增量表，报送上一采集日至采集日期间新增的数据。 | G32: 所有影响对公信贷账户余额或利息变动的交易信息，包括还本、还息，不包括查询交易。贷款核销或者转让（包括资产证券化）也应该在本表体现：明细科目填报本金科目，交易金额为核销或转让前本金余额，余额填报为0，交易对手填写借款人自身信息，摘要中标明核销或者转让交易。 | H32: 修改
A33: 各项贷款 | B33: 005
C34: XDHTB | D34: 信贷合同表 | E34: 501 | F34: 全量表，报送截至采集日有效的数据，以及上一采集日至采集日期间结清、失效、终结等所有视为终态的数据。 | G34: 报送范围应至少包括1104报表中：各项贷款+非现金管理项下委托贷款-信用卡。如，个人贷款、对公贷款、票据贴现、买断式转贴现、贸易融资业务、融资租赁业务、委托贷款（非现金管理项下）对应的业务合同，以及各项垫款对应的原业务合同。表外业务只报送委托贷款（非现金管理项下），其他不报送。信用卡业务不报送。对于票据贴现和买断式转贴现，可以填报为信贷合同号=信贷借据号=票据号码；对于其他若没有对应合同号的业务，可以填报为信贷合同号=信贷借据号=业务编号。已撤销、失效、终结的合同在报送合同最后状态的次月可不再报送。 | H34: 修改 | J34: 报送范围应至少包括1104中：各项贷款+非现金管理项下的委托贷款-信用卡。如，个人贷款、对公贷款、票据贴现、买断式转贴现、贸易融资业务、融资租赁业务、委托贷款（非现金管理项下）对应的业务合同，以及各项垫款对应的原业务合同。委托贷款中现金管理项下委托贷款不报送，其他表外业务不报送。信用卡业务不报送。对于票据贴现和买断式转贴现，可以填报为信贷合同号=信贷借据号=票据号码；对于其他若没有对应合同号的业务，可以填报为信贷合同号=信贷借据号=业务编号。已撤销、失效、终结的合同在报送合同最后状态的次月可不再报送。
C35: HLWDKHTFJB | D35: 互联网贷款合同附加表 | E35: 502 | F35: 全量表，报送截至采集日有效的数据，以及上一采集日至采集日期间结清、失效、终结等所有视为终态的数据。 | G35: 本表报送所有互联网贷款合同的附加信息。互联网贷款的认定参照《商业银行互联网贷款管理暂行办法》。互联网贷款的发放明细应该报送至相对应的信贷业务借据表、信贷合同表、信贷分户账以及信贷分户账明细记录中。已撤销、失效、终结的合同在报送合同最后状态的次月可不再报送。 | H35: 新增
C36: GRXDYWJJB | D36: 个人信贷业务借据表 | E36: 503 | F36: 全量表，报送截至采集日有效的数据，以及上一采集日至采集日期间结清、失效、终结等所有视为终态的数据。 | G36: 所有以个人名义在信贷业务中签订的借据信息。个体工商户、私营业主以个人名义办理的贷款的计入本表，以机构名义办理的贷款不计入本表。表外业务只报送委托贷款（非现金管理项下），其他不报送。信用卡业务不报送。对于票据贴现和买断式转贴现，可以填报为信贷合同号=信贷借据号=票据号码；对于其他若没有对应借据号的业务，可以填报为信贷合同号=信贷借据号=业务编号。借据状态为结清、核销、转让的可在报送最后状态的次月不再报送。 | H36: 修改
C37: DGXDYWJJB | D37: 对公信贷业务借据表 | E37: 504 | F37: 全量表，报送截至采集日有效的数据，以及上一采集日至采集日期间结清、失效、终结等所有视为终态的数据。 | G37: 所有以机构名义在信贷业务中签订的借据信息。个体工商户、私营业主以机构名义办理的贷款计入本表，以个人名义办理的贷款不计入本表。表外业务只报送委托贷款（非现金管理项下），其他不报送。信用卡业务不报送。对于票据贴现和买断式转贴现，可以填报为信贷合同号=信贷借据号=票据号码；对于其他若没有对应借据号的业务，可以填报为信贷合同号=信贷借据号=业务编号。转贴、二级市场福费廷业务的借款人按照交易对手（同业）填报，贴现和信用证下融资的借款人按照贴现申请人、信用证融资人填报。借据状态为结清、核销、转让的可在报送最后状态的次月不再报送。 | H37: 修改
C38: STZFXXB | D38: 受托支付信息表 | E38: 505 | F38: 增量表，报送上一采集日至采集日期间新增的数据。 | G38: 《个人信贷业务借据表》和《对公信贷业务借据表》中放款方式为“受托支付”或“混合支付”的，在该表中报送受托支付对象信息。 | H38: 新增
C39: XMDKXXB | D39: 项目贷款信息表 | E39: 506 | F39: 全量表，报送截至采集日有效的数据，以及上一采集日至采集日期间结清、失效、终结等所有视为终态的数据。 | G39: 符合以下特征的贷款的相关信息：（一）贷款用途通常是用于建造一个或一组大型生产装置、基础设施、房地产项目或其他项目，包括对在建或已建项目的再融资；（二）借款人通常是为建设、经营该项目或为该项目融资而专门组建的企事业法人，包括主要从事该项目建设、经营或融资的既有企事业法人；（三）还款资金来源主要依赖该项目产生的销售收入、补贴收入或其他收入，一般不具备其他还款来源。以信贷借据号为最小颗粒报送，同一合同下多笔借据的按多条报送。已结清、核销的数据在次月不再报送。 | H39: 修改
C40: YTDKXXB | D40: 银团贷款信息表 | E40: 507 | F40: 全量表，报送截至采集日有效的数据，以及上一采集日至采集日期间结清、失效、终结等所有视为终态的数据。 | G40: 银（社）团贷款信息。以信贷借据号为最小颗粒报送，同一合同下多笔借据的按多条报送。已结清、核销的数据在次月不再报送。 | H40: 修改
C41: PJTXB | D41: 票据贴现表 | E41: 508 | F41: 全量表，报送截至采集日有效的数据，以及上一采集日至采集日期间结清、失效、终结等所有视为终态的数据。 | G41: 填报机构对客户办理的商业票据贴现，不包括对金融机构办理的买断式转贴现业务。票据状态为“卖断”、“解付”或“核销”的数据，在报送票据最后状态的次月可不再报送。 | H41: 新增
C42: PJZTXB | D42: 票据转贴现表 | E42: 509 | F42: 全量表，报送截至采集日有效的数据，以及上一采集日至采集日期间结清、失效、终结等所有视为终态的数据。 | G42: 报送本行发生的转贴现买断、转贴现卖断、质押式回购正回购、质押式回购逆回购、买断式回购正回购、买断式回购逆回购、再贴现等业务的明细信息。票据状态为“卖断”、“解付”或“核销”的数据，在报送票据最后状态的次月可不再报送。 | H42: 新增
C43: MYRZYWB | D43: 贸易融资业务表 | E43: 510 | F43: 全量表，报送截至采集日有效的数据，以及上一采集日至采集日期间结清、失效、终结等所有视为终态的数据。 | G43: 填报机构对非金融机构提供的贸易项下的融资或信用便利的余额,包括打包贷款、押汇、保理、议付信用证、买方信贷、卖方信贷、福费廷等业务。本行开出的保函及信用证在保函及信用证表中报送，不在本表中填报。贷款状态为结清、核销、转让的，于次月不再报送。 | H43: 修改
C44: RZZLYWB | D44: 融资租赁业务表 | E44: 511 | F44: 全量表，报送截至采集日有效的数据，以及上一采集日至采集日期间结清、失效、终结等所有视为终态的数据。 | G44: 填报机构与租赁公司合作，购买承租人指定租赁物件，与承租人签订租赁合同，待合同期满后租赁物资产所有权转移给承租人的一类业务。报送范围：参照1104报表G01_III[1.5融资租赁]填报口径。贷款状态为结清、核销、转让的，可在报送最终状态的次月不再报送。 | H44: 新增
C45: DKDJB | D45: 垫款登记表 | E45: 512 | F45: 全量表，报送截至采集日有效的数据，以及上一采集日至采集日期间结清、失效、终结等所有视为终态的数据。 | G45: 填报信用证、承兑汇票、保函、贵金属租赁等业务产生的各项垫款信息，相关业务定义参照1104报表《各项垫款情况表》。垫款状态为“结清”、“转让”、“核销”的，在报送最后状态的次月可不再报送。 | H45: 新增
C46: HLWDKHZXYB | D46: 互联网贷款合作协议表 | E46: 513 | F46: 全量表，报送截至采集日有效的数据，以及上一采集日至采集日期间结清、失效、终结等所有视为终态的数据。 | G46: 本表报送机构与合作方签订的互联网贷款合作协议信息。互联网贷款的认定参照《商业银行互联网贷款管理暂行办法》。已终止的合作协议于报送协议最后状态的次月不再报送。
A47: 表内外担保信息 | B47: 006
C48: BNWYWDBHTB | D48: 表内外业务担保合同表 | E48: 601 | F48: 全量表，报送截至采集日有效的数据，以及上一采集日至采集日期间结清、失效、终结等所有视为终态的数据。 | G48: 各项表内外业务（包括但不限于贷款、同业投资、表外业务等）中签订的各类担保合同信息。被担保业务若无合同号，则“被担保合同号”填写该笔业务唯一识别标识，如“自营资金业务余额表.金融工具编号”。以保证金形式的担保无需在本表填报，但以存单质押形式的担保需要填报。本表反映被担保合同和担保合同之间的关系，为多对多关系表，一个担保合同担保多个业务合同的，需按多笔填报，多个担保合同担保一个合同的，也需按多笔填报。失效的担保合同于次月不再报送。 | H48: 修改
C49: BNWYWDBR | D49: 表内外业务担保人 | E49: 602 | F49: 全量表，报送截至采集日有效的数据，以及上一采集日至采集日期间结清、失效、终结等所有视为终态的数据。 | G49: 担保合同中约定的担保人信息。同一份担保合同有多个担保人的，每个担保人填写一条记录。失效担保合同的担保人于次月不再报送。 | H49: 修改
C50: BNWYWDZYW | D50: 表内外业务抵质押物 | E50: 603 | F50: 全量表，报送截至采集日有效的数据，以及上一采集日至采集日期间结清、失效、终结等所有视为终态的数据。 | G50: 担保合同中约定的各类质押、抵押物信息。对于同一担保合同有不同的抵质押物的，需以不同的质或抵押物编号分多条记录报送。以保证金形式的押品无需在本表填报，但以存单质押形式的押品需要填报。失效担保合同的押品信息于次月不再报送。 | H50: 修改
A51: 信贷管理信息 | B51: 007
C52: SXXXB | D52: 授信信息表 | E52: 701 | F52: 全量表，报送截至采集日有效的数据，以及上一采集日至采集日期间结清、失效、终结等所有视为终态的数据。 | G52: 对客户授信的信息，但不包含客户使用授信的明细。包括对公和个人、同业客户授信，但不包括集团授信。个人授信额度包括个人贷款、信用卡额度授信（包含准贷记卡透支额度）。对公和同业授信包括已经或预期可能由本行承担信用风险的各类产品额度，包含但不限于流动资金贷款、固定资产贷款、项目融资、贸易融资、透支、保理、票据、保函、信用证、债券投资、特定目的载体投资、买入返售、同业拆借、同业存款等产品额度。 1.按授信协议为最细颗粒填报，有授信的客户都需要报送，如低风险额度授信都需要填报授信信息。 2.表内、表外、代管理的信贷资产均需报送，如：本行信贷资产转让后由本行代管的授信信息仍需报送。 3.增加授信的，应该按照单笔报送。如发生授信额度变更的，填写最新的协议授信额度。 4.无授信的无需报送。 5.授信协议失效的，报送协议最后状态的次月不再报送。 | H52: 修改
C53: ZCHXB | D53: 资产核销表 | E53: 702 | F53: 全量表，报送截至采集日有效的数据，以及上一采集日至采集日期间结清、失效、终结等所有视为终态的数据。 | G53: 已核销的个人贷款、对公贷款、信用卡以及其他债权和股权资产信息。 1.包含信用卡核销，借据号填报为卡号，合同号填报为信用卡账户号。其他非信贷类资产合同号、借据号填报业务编号等唯一标识，如“自营资金业务余额表.金融工具编号”。 2.以借据号或信用卡卡号为最小颗粒报送。 3.根据财政部2017年《金融企业呆账核销管理办法》规定，符合规定完全终结的信贷资产可以在报送次月后不再报送。通过各种手段处置已核销资产结清欠款或已无追索权的，也视为“完全终结”。 | H53: 修改
C54: XDZCZRB | D54: 信贷资产转让表 | E54: 703 | F54: 全量表，报送截至采集日有效的数据，以及上一采集日至采集日期间结清、失效、终结等所有视为终态的数据。 | G54: 业务范围包含直接转让债权、信贷资产证券化、信贷资产收益权转让、通过其他方式转让等，以及对应的信贷资产转入业务，相关业务定义参照1104报表《信贷资产转让情况统计表》。行内机构间的转让需报送。票据的买卖、买入返售、卖出回购不在本表填报。含已核销贷款，本金按实际填写0即可。终结的转让合同在报送最后状态后不再报送。 | H54: 修改
C55: ZCZRGXB | D55: 资产转让关系表 | E55: 704 | F55: 全量表，报送截至采集日有效的数据，以及上一采集日至采集日期间结清、失效、终结等所有视为终态的数据。 | G55: 本表报送信贷资产转让合同与被转让贷款借据的对应关系，一个转让合同对应多个借据的，按借据填报多条记录。对于信用卡资产转让，以信用卡账号填报为借据号。票据的买卖、买入返售、卖出回购不在本表填报。 | H55: 修改
C56: DKWJXTBDB | D56: 贷款五级形态变动表 | E56: 705 | F56: 增量表，报送上一采集日至采集日期间新增的数据。 | G56: 所有表内信贷的五级分类变动信息，与其他表格中五级分类字段一致。需要报送信用卡业务的五级形态变动，填报为信贷合同号=信用卡账号，信贷借据号=信用卡卡号。无需报送新发放业务（五级分类从无到有）的五级形态变动。 | H56: 修改
A57: 信用卡业务 | B57: 008
C58: XYKXXB | D58: 信用卡信息表 | E58: 801 | F58: 全量表，报送截至采集日有效的数据，以及上一采集日至采集日期间结清、失效、终结等所有视为终态的数据。 | G58: 填报信用卡信息，以卡号为最小粒度报送。状态为“销户”的信用卡在报送最后状态的次月不再报送。状态为“销户”的账户以及账户下所属的所有信用卡在报送最后状态的次月不再报送。 | H58: 修改
C59: XYKJYMXB | D59: 信用卡交易明细表 | E59: 802 | F59: 增量表，报送上一采集日至采集日期间新增的数据。 | G59: 影响信用卡余额变动的交易明细，不包括查询交易，以信用账号、卡号中取较小粒度报送。已核销卡的交易明细不再报送。 | H59: 修改
C60: XYKSXQKB | D60: 信用卡授信情况表 | E60: 803 | F60: 全量表，报送截至采集日有效的数据，以及上一采集日至采集日期间结清、失效、终结等所有视为终态的数据。 | G60: 报送信用卡持卡人当月授信情况。客户额度按同一账户下的总额度报送，不以单张信用卡额度报送。对主副卡客户（一账户多个客户）的情况，本表只报送主卡人的授信信息。同一客户多个账户的，按多条分别报送。同一账户多个币种共享额度的，按记账币种统一折算填报。状态为“销户”的账户在报送最后状态的次月可不再报送。 | H60: 修改
C61: XYKFQYWB | D61: 信用卡分期业务表 | E61: 804 | F61: 增量表，报送上一采集日至采集日期间新增的数据。 | G61: 填报每月新增的持卡人分期业务情况。 | H61: 修改
A62: 表外授信业务 | B62: 009
C63: PJCPXXB | D63: 票据出票信息表 | E63: 901 | F63: 全量表，报送截至采集日有效的数据，以及上一采集日至采集日期间结清、失效、终结等所有视为终态的数据。 | G63: 报送由出票人签发并向填报机构申请，经填报机构承兑的汇票。票据状态为卖断（转贴现卖断），解付（票据到期且出票人已付款）的数据，在报送票据最后状态的次月可不再报送。 | H63: 修改
C64: BHYXYZB | D64: 保函与信用证表 | E64: 902 | F64: 全量表，报送截至采集日有效的数据，以及上一采集日至采集日期间结清、失效、终结等所有视为终态的数据。 | G64: 报送范围为跟单信用证、保函、信用风险仍在银行的销售与购买协议、其他担保类业务、承诺、其他承诺，相关业务定义可参照1104报表。合同到期且已结清的数据，在报送合同最后状态的次月不再填报。 | H64: 新增
C65: JYBJXXB | D65: 交易背景信息表 | E65: 903 | F65: 增量表，报送上一采集日至采集日期间新增的数据。 | G65: 填报承兑汇票、保函、信用证、保理融资等业务为审查交易背景真实性收集的发票、仓单、提单等信息，以能采尽采的原则，每月报送新收集的单据信息。报送范围：本行开出的票据（同《票据出票信息表》），本行开立的保函和信用证（同《保函与信用证表》），保理融资业务（同《贸易融资业务表》），其中非基于企业间贸易的保函可以不报送，业务尚未收集发票的暂时不报送。非本行开立的票据、保函、信用证的单据信息如未收集发票信息的可以不报送。同一票据或合同下对应的多个单据，以单据编号为最小粒度逐条报送。 | H65: 新增
C66: WTDKXXB | D66: 委托贷款信息表 | E66: 904 | F66: 全量表，报送截至采集日有效的数据，以及上一采集日至采集日期间结清、失效、终结等所有视为终态的数据。 | G66: 报送范围为个人及对公委托贷款业务，包括现金管理项下委托贷款、非现金管理项下委托贷款和公积金委托贷款。对于现金管理项下委托贷款，每发生一笔放款仅报送一次，以后不再报送，贷款状态以“其他-现金管理项下”报送。结清或者终结的委托贷款，在报送合同最后状态的次月不再填报。 | H66: 修改
C67: DLDXJYXXB | D67: 代理代销交易信息表 | E67: 905 | F67: 增量表，报送上一采集日至采集日期间新增的数据。 | G67: 报送范围包括债券承销、代理代销信托计划、代理资产管理计划、代理代销保险产品、代理代销基金、代理贵金属交易以及其他代理代销业务，相关业务定义可参照1104报表。代理销售他行发行的理财产品也需要报送，包括填报机构理财子公司发行的理财产品。涉及分红、付息等交易无需报送。涉及赎回、卖出的交易需要报送。 | H67: 新增
A68: 资金交易信息 | B68: 010
C69: HLXXB | D69: 汇率信息表 | E69: 1001 | F69: 增量表，报送上一采集日至采集日期间新增的数据。 | G69: 国家外汇管理局公布汇率的主要币种，填报各主要外币与人民币的折算汇率。其他货币对人民币的折算汇率，以当天美元兑人民币的基准汇率与同一天国际外汇市场其他货币兑美元汇率套算确定。机构可只填报常见的外币信息，但至少应包含其它表中填报使用过的所有外币。 | H69: 修改
C70: JRGJXXB | D70: 金融工具信息表 | E70: 1002 | F70: 全量表，报送截至采集日有效的数据，以及上一采集日至采集日期间结清、失效、终结等所有视为终态的数据。 | G70: 记录《自营资金交易信息表》和《自营资金业务余额表》中所有业务对应的标的物。债券、非标准化债权类资产等以产品为单位的标的物，以单一产品为金融工具；同业拆放、存放同业等以对某机构为单位的业务，以对某机构为单一金融工具，如：金融工具名称为“存放XX银行”。已结清（余额为0）/赎回/终结的业务在报送最后状态的次月不再报送。同业往来大类下的同业存单，债券和同业投资大类下的所有业务需填报基础资产相关信息，基础资产如对应多个，按多条报送。票据业务不在本表报送。 | H70: 修改
C71: ZYZJJYXXB | D71: 自营资金交易信息表 | E71: 1003 | F71: 增量表，报送上一采集日至采集日期间新增的数据。 | G71: 填报在阶段开始日到结束日之间，银行发生的自营资金交易，业务范围参考《自营报送范围》，其中债券与同业投资部分填报口径与1104报表G31一致。同一金融工具当月发生当月结清的数据也需要报送，买入与卖出操作按不同笔次分别填报。票据业务（包含贴现和转贴现）不在本表填报。结算性账户交易不报送。同业存放业务在对公存款分户账及分户账明细报表中报送，不在本表报送。 | H71: 修改
C72: ZYZJYWYEB | D72: 自营资金业务余额表 | E72: 1004 | F72: 全量表，报送截至采集日有效的数据，以及上一采集日至采集日期间结清、失效、终结等所有视为终态的数据。 | G72: 填报截至报送日期有余额的自营资金业务及所持有的头寸信息，业务范围参考《自营报送范围》，其中债券与同业投资部分余额填报口径与1104报表G31一致。票据业务（包含贴现和转贴现）不在本表填报。已结清（余额为0）/赎回/核销/终结的业务在报送最后状态的次月不再报送。同一金融工具当月发生当月结清的数据也需要一条，并于次月不再报送。 | H72: 修改
C73: JQJYSPJYXXB | D73: 即期及衍生品交易信息表 | E73: 1005 | F73: 增量表，报送上一采集日至采集日期间新增的数据。 | G73: 填报范围：报告期内发生的自营、代客即期资金交易，以及衍生品交易信息，按发生额填报。其中即期资金交易包括结售汇、贵金属实物（积存金）交易、商品类交易等。交易不涉及的数据项不填报。 填报方式：非掉期（互换）交易中若报送机构既可以为买方也可以为卖方，则按报送机构为卖方填报。掉期（互换）交易（或具有类似特征的交易）将两端（LEG1、LEG2）拆分为2条记录报送，交易编号保持一致，即用2条记录表示1笔交易。如：掉期交易按近端、远端拆分为2条记录报送，互换交易拆分为收入、支付端2条记录报送。衍生品交易存续期内按估值周期填报交易估值信息，填报估值金额、估值币种及估值日期，其他字段不变。如同一笔交易由多条记录表示，多条记录的估值信息字段（估值金额、估值币种、估值日期）保持一致。可参照《即期及衍生品交易信息表填报示例》填报。 | H73: 新增
A74: 理财业务 | B74: 011
C75: LCCPXXB | D75: 理财产品信息表 | E75: 1101 | F75: 全量表，报送截至采集日有效的数据，以及上一采集日至采集日期间结清、失效、终结等所有视为终态的数据。 | G75: 该表体现截至统计时点所有在全国银行业理财信息登记系统中取得产品登记编码并成功发行的理财产品相关信息。 | H75: 修改
C76: LCCPZTB | D76: 理财产品状态表 | E76: 1102 | F76: 全量表，报送截至采集日有效的数据，以及上一采集日至采集日期间结清、失效、终结等所有视为终态的数据。 | G76: 全量表，报送截至采集日有效的数据以及与上一采集日期间失效的数据。该表体现统计期末存续的理财产品状态及运营情况等信息。包含银行及理财公司数据。 | H76: 修改
C77: LCCPDCCCXXB | D77: 理财产品底层持仓信息表 | E77: 1103 | F77: 全量表，报送截至采集日有效的数据，以及上一采集日至采集日期间结清、失效、终结等所有视为终态的数据。 | G77: 该表体现统计期末理财产品持有所有类别资产的相关信息。 | H77: 修改
C78: FBZCMXXXB | D78: 非标资产明细信息表 | E78: 1104 | F78: 全量表，报送截至采集日有效的数据，以及上一采集日至采集日期间结清、失效、终结等所有视为终态的数据。 | G78: 该表体现统计期末理财产品持有的非标准化债权类资产（目前包含信托贷款、委托贷款、信贷资产转让、收/受益权、委托债权、应收账款、带回购条款的股权性融资、债券融资类产品）明细信息。 | H78: 修改
C79: QTFBZCMXXXB | D79: 其他非标资产明细信息表 | E79: 1105 | F79: 全量表，报送截至采集日有效的数据，以及上一采集日至采集日期间结清、失效、终结等所有视为终态的数据。 | G79: 该表体现统计期末理财产品持有的其他非标准化债权类资产（包括但不限于保理、融资租赁、股票质押融资等）明细信息。 | H79: 修改
C80: LCCPZCJYXXB | D80: 理财产品资产交易信息表 | E80: 1106 | F80: 增量表，报送上一采集日至采集日期间新增的数据。 | G80: 该表体现统计期内理财产品发生的逐笔投资交易信息。 | H80: 修改
C81: LCCPXSMXB | D81: 理财产品销售明细表 | E81: 1107 | F81: 增量表，报送上一采集日至采集日期间新增的数据。 | G81: 代销他行理财产品由银行机构在代理代销信息表中报送。 | H81: 修改
C82: KHLCCPCYXXB | D82: 客户理财产品持有信息表 | E82: 1108 | F82: 全量表，报送截至采集日有效的数据，以及上一采集日至采集日期间结清、失效、终结等所有视为终态的数据。 | G82: 全量表，报送截至采集日有效的数据。本机构客户开立的理财分户账信息，报送本机构理财产品账户信息，代销其他机构理财在其他机构数据源下报送。买入不同理财产品的，每个产品作为一条记录。本表为状态表，每月逐客户（客户证件类别+客户证件号码）、逐产品报送截至月底的持仓信息。 仅包含产品起始日在2018年10月1日之后的理财产品（由母行划转至理财公司的产品，仅包含母行原产品的起始日在2018年10月1日之后的产品） 包含银行及理财公司数据。 | H82: 新增

Sheet 数据元说明
A2: 数据元说明
A4: 分类 | B4: 数据元编码 | C4: 数据元名称 | D4: 数据元英文 | E4: 数据元说明 | F4: 格式
A6: 公共信息 | B6: 001
B7: 001001 | C7: 名称 | D7: Name | E7: 名称应与公章所使用的名称完全一致。银行机构以银保监会金融机构许可证登记名称为准。无独立金融机构许可证的机构，可在本名称中体现出机构特征。第三方支付平台填报第三方支付平台名称。 客户名称按照客户的不同类型按如下标准填报。 （1）集团客户，填报银行对该集团授信采用的集团客户名称。视同集团客户填报的供应链融资填报核心企业客户名称。 （2）单一法人客户，经有关部门批准正式使用的全称，与公章所使用的名称完全一致。视同单一法人客户填报的分公司，填报分公司全称，与分公司公章所使用的名称完全一致。客户是境内涉密机构的，客户名称填报为“*********”。 （3）同业客户，经有关部门批准正式使用的客户全称，与客户公章所使用的名称完全一致。 （4）自然人，与有效证件上的姓名一致。 （5）境外客户，客户名称填报英文名称。 | F7: C..450
B8: 001002 | C8: 是否标志 | D8: Yes or No | E8: 是，否。 | F8: C3
B9: 001003 | C9: 比例 | D9: Ratio | E9: 百分比为单位，即1/100，保留两位小数。如4.5%则填报为4.50。 | F9: D20.2
B10: 001004 | C10: 比例（精） | D10: Accurate rate | E10: 百分比为单位，即1/100，保留六位小数。4.123456%则填报为4.123456。 | F10: D20.6
B11: 001005 | C11: 日期 | D11: Date | E11: YYYYMMDD，默认值99991231。 | F11: C8
B12: 001006 | C12: 年月 | D12: Year & Month | E12: YYYYMM，默认值999912。 | F12: C6
B13: 001007 | C13: 时间 | D13: Time | E13: 24小时制时间，精确到秒。hhmmss，默认值000000。 | F13: C6
B14: 001008 | C14: 地址 | D14: Address | E14: 中文描述。个人填报个人住址。机构填报有关部门批准的有效证件上登记的地址。参照《企业法人营业执照》中的注册地填报，要写明省（区、市）、地（区、市、州、盟）、县（区、市、旗）。境内涉密机构不填报。客户为境外企业的，填报客户在境外的注册地址（英文）。 | F14: C..600
B15: 001009 | C15: 电话 | D15: Tel. | E15: 手机号码或者区号-固定电话号码。 | F15: C..30
B16: 001010 | C16: 银行机构代码 | D16: Bank code | E16: 12位人行支付行号或SWIFT行号。 | F16: C..30
B17: 001011 | C17: 金融许可证号 | D17: Financial license number | E17: 金融许可证机构编码编制规则（试行） 一、机构编码结构 机构编码由大写英文字母和数字组成，共15位。分六个部分，分别是机构类型代码、机构代码、组织类别代码、发证机关代码、地址代码、顺序代码，从左至右顺序排列，如下表所示。 二、机构编码含义 （一）第［一］位是机构类型代码，用大写英文字母表示。 A-政策性银行 B-商业银行 C-农村合作银行 D-城市信用社 E-农村信用社 F-资金互助社 J-金融资产管理公司 K-信托公司 L-财务公司 M-金融租赁公司 N-汽车金融公司 P-货币经纪公司 Q-贷款公司 Z-其他类金融机构 新增机构类型时，根据需要确定机构类型代码。 （二）第［二］位至第［五］位是机构代码，用数字表示。 1.每个法人机构指定唯一的代码，由计算机系统按照规则自动生成。除农村信用社、资金互助社、贷款公司（E、F、Q类机构）外，全国统一编码。E、F、Q类机构在省（自治区、直辖市）范围内统一编码。 2.新设立的机构依照所属机构类型顺序排列。 机构代码编码示例如下： A-政策性银行 0001-国家开发银行 …… B-商业银行 0001-中国工商银行股份有限公司 …… C-农村合作银行 0001-天津大港农村合作银行 …… D-城市信用社 0001-邯郸市城市信用社股份有限公司 …… E-农村信用社天津市 0001-天津市宝坻区农村信用合作联社 …… 新疆维吾尔自治区 0001-新疆维吾尔自治区农村信用社联合社 …… F-资金互助社 吉林省 0001-吉林省梨树县闰家村百信农村资金互助社 …… 青海省 0001-青海省乐都县雨润镇兴乐农村资金互助社 …… J-金融资产管理公司 0001-中国华融资产管理公司 …… K-信托投资公司 0001-中诚信托投资有限责任公司 …… L-财务公司 0001-中海石油财务有限责任公司 …… M-金融租赁公司 0001-中国外贸金融租赁公司 …… N-汽车金融公司 0001-大众汽车金融（中国）有限公司 …… P-货币经纪公司 0001-上海国利货币经纪有限公司 …… Q-贷款公司四川省 0001-四川省仪陇县惠民贷款有限责任公司 …… 新疆维吾尔自治区 0001- …… Z-其他类金融机构 0001-中央国债登记结算有限责任公司 …… （三）第〔六〕位是组织类别代码，用大写英文字母表示。 机构类型不同，组织类别代码的含义不同。定义如下： 1.A-政策性银行 H-总行 G-总行营业部 H-级分行 K-一级分行营业部 M-二级分行 S-支行 X-其他分支机构 2.B-商业银行 H-总行 G-总行营业部、专营机构 B-一级分行 K-一级分行营业部 L-二级分行 M-直属支行 N-二级分行营业部 S-支行 U-分理处、办事处、营业所 V-储蓄所 X-其他分支机构 3.C-农村合作银行 H-总行 S-支行 U-分理处 V-储蓄所 X-其他分支机构 4.D-城市信用社 H-法人 S-分社、营业部 X-其他分支机构 5.E-农村信用社 H-省（自治区、直辖市）联合社 B-地（市）联合社、联社 S-县（市）联合社、联社、合作社（县级） T-信用合作社 U-信用社、分社 V-储蓄所 X-其他分支机构 6.F-资金互助社 H-法人 7.J-金融资产管理公司 H-总公司 B-办事处 X-其他分支机构 8.K-信托公司 H-法人 9.N-汽车金融公司 H-法人 10.L-财务公司 H-总公司 B-分公司 X-其他分支机构 11.M-金融租赁公司 H-总公司 B-分公司 X-其他分支机构 12.P-货币经纪公司 H-总公司 B-分公司 X-其他分支机构 13.Q-贷款公司 H-总公司 B-分公司 X-其他分支机构 14.Z-其他类金融机构 Z类机构组织类别代码编码方法参照以上规则。 新增机构类型时，参照以上规则，根据实际情况定义其组织类别代码。 （四）第〔七〕位是发证机关代码，用数字表示。 1-银保监会 2-银监局 3-银监分局 （五）第〔八〕位至第〔十一〕是地址代码，用数字表示。按照《中华人民共和国行政区划代码》 （GB/T2260），取市（地区、自治州、盟）、直辖市行政区划代码前四位，作为地址代码。 地址代码示例如下：1100表示北京市，1200表示天津市，1301表示石家庄市，…… （六）第〔十二〕位至第〔十五〕位是顺序代码，用数字表示。机构类型代码、机构代码、组织类别代码、发证机关代码和地址代码相同的机构按照制发金融许可证的顺序编码。 三、机构编码的编制规则 编制机构编码时，按照从左至右的顺序依次确定机构类型代码、机构代码、组织类别代码、发证机关代码、地址代码、顺序代码，由计算机自动生成。 为了保证机构编码的唯一性，以利于电子计算机较长时间地存储数据，因行政许可变更需换发金融许可证，涉及机构编码变更的，原机构编码不再使用.金融机构终止的，机构编码不再使用。注销开业许可收回金融许可证的，机构编码不再使用。 | F17: C..30
B18: 001012 | C18: 内部机构号 | D18: Inner organization number | E18: 银行内部机构号。应具有标识机构的唯一性。 | F18: C..30
... B40: 001034 | C40: 员工状态 | D40: State of staff | E40: 在岗，离岗，离职，其他-银行自定义。无法以枚举类型填报的，以“其他-XX”填报，其中“XX”为银行自定义类型。 | F40: C..30
B41: 001035 | C41: 柜员状态 | D41: State of Teller | E41: 在岗，离岗，其他-银行自定义。无法以枚举类型填报的，以“其他-XX”填报，其中“XX”为银行自定义类型。
B42: 001036 | C42: IP地址 | D42: IP address | E42: 点分十进制格式表示的IPV4地址，或者IPV6地址。 | F42: C..40
B43: 001037 | C43: MAC地址 | D43: MAC address | E43: 网络设备唯一的网络标识： 1.可以是MAC地址，以12个16进制数表示（6个字节），每个字节以英文半角冒号（:）隔开。 2.若交易渠道为网银、手机银行，Android7.0以上系统可填报设备IMEI码；IOS7以上系统科填报UUID码，唯一对应设备即可。 | F43: C..60
B44: 001038 | C44: 备注 | D44: Remark | E44: 银行自定义。 | F44: C..600
A45: 客户信息 | B45: 002
B46: 002001 | C46: 客户统一编号 | D46: Customer number | E46: 银行自定义的唯一识别客户的标识。供应链融资的填写供应链融资编码。 | F46: C..60
B47: 002002 | C47: 证件类别 | D47: Document type | E47: 同业客户：银行机构代码，金融许可证号，SWIFT编码，其他-XX。 对公客户：统一社会信用代码，组织机构代码，营业执照（工商注册号），公司注册证书，全球法人识别码，其他-XX。 个人客户：居民身份证，军官证，文职干部证，警官证，士兵证，户口簿，临时身份证，其他有效通行旅行证件，护照，学生证，无证件，其他-XX。 无法以枚举类型填报的，以“其他-XX”报送，其中“XX”为银行自定义类型。 对公客户优先填报统一社会信用代码，没有统一社会信用代码的对公客户填报组织机构代码。组织机构代码、统一社会信用代码均没有的可以填报客户提供的批文文号、开户主证件、上级机构统一社会信用代码等，以“其他-XX”填报。 | F47: C..60
B48: 002003 | C48: 证件号码 | D48: Document number | E48: 与证件类别对应的证件号码。涉及个人身份证件时需按照本规范给定规则进行脱敏处理。 | F48: C..70
B49: 002004 | C49: 国籍 | D49: Nationality | E49: 参照《GB/T 2659-2000 世界各国和地区名称》，填报中文名称。 | F49: C..60
B50: 002005 | C50: 民族 | D50: Ethnicity | E50: 国家认可的在公安户籍管理部门正式登记注册的客户所属民族的名称。 | F50: C..30
B51: 002006 | C51: 性别 | D51: Gender | E51: 男，女。 | F51: C3
B52: 002007 | C52: 学历 | D52: Education degree | E52: 《学历代码》（GB/T 4658）规定的学历。 | F52: C..30
B53: 002008 | C53: 职业 | D53: Career | E53: 中文描述或中文字典，银行自定义。 | F53: C..90
B54: 002009 | C54: 单位性质 | D54: Unit property | E54: 国有企业、民营企业、政府机关、事业单位、社会团体、境外机构、其他-银行自定义。无法以枚举类型填报的，以“其他-XX”填报，其中“XX”为银行自定义类型。 | F54: C..60
B55: 002010 | C55: 社会关系 | D55: Social relationship | E55: 配偶，父母，子女，亲属关系，朋友，同事，合作伙伴，离异原配偶，其他-银行自定义。无法以枚举类型填报的，以“其他-XX”填报，其中“XX”为银行自定义类型。 | F55: C..60
B56: 002011 | C56: 法人代表 | D56: Legal person | E56: 该对公客户法人代表。依照法律或者法人组织章程规定，代表法人行使职权的负责人姓名。 | F56: C..150
B57: 002012 | C57: 营业执照号 | D57: Business license number | E57: 已登记统一社会信用代码的，填18位统一社会信用代码；未登记统一社会信用代码的，填报营业执照注册号。 | F57: C..60
... B73: 002028 | C73: 财务报表编号 | D73: Financial statement number | E73: 唯一标识财务报表的编号，银行自定义。 | F73: C..30
A74: 账户 | B74: 003
B75: 003001 | C75: 账号 | D75: Account number | E75: 系统内最细一级的账号，无唯一性约束，不需要和序号、子序号等做拼接。 | F75: C..60
B76: 003002 | C76: 会计科目编号 | D76: Subject number of general ledger accounting | E76: 机构实际使用的总账会计科目编码。 | F76: C..60
B77: 003003 | C77: 会计科目名称 | D77: Subject name of general ledger accounting | E77: 机构实际使用的总账会计科目编码对应的名称。 | F77: C..300
B78: 003004 | C78: 会计科目级次 | D78: Subject grade of general ledger accounting | E78: 总账会计科目编号在科目结构中所对应的级次。 | F78: I
B79: 003005 | C79: 会计科目大类 | D79: Account category | E79: 资产、负债、所有者权益、损益、资产负债共同类、表外、其他。 | F79: C..30
B80: 003006 | C80: 会计科目子类 | D80: Account sub category | E80: 资产类业务子类：1现金，2贵金属，3存放中央银行款项，4存放同业款项，5应收利息，6贷款，7贸易融资，8贴现及买断式转贴现，9其他贷款，10拆放同业，11其他应收款，12投资，13买入返售资产，14长期待摊费用，15固定资产原价，16减：累计折旧，17固定资产净值，18固定资产清理，19在建工程，20无形资产，21抵债资产，22递延所得税资产，23其他资产，24各项资产减值损失准备。 负债类业务子类：25单位存款，26储蓄存款，27向中央银行借款，28同业存放款项，29同业拆入，30卖出回购款项，31汇出汇款，32应解汇款，33存入保证金，34应付利息，35应交税费，36应付职工薪酬，37应付福利费，38应付股利，39其他应付款，40预提费用，41递延收益，42预计负债，43转贷款资金，44应付债券，45其他负债，46递延所得税负债。 所有者权益类业务子类：47实收资本，48资本公积，49盈余公积，50一般风险准备，51信托赔偿准备，52未分配利润，53其他综合收益，54其他权益工具。 损益类业务子类：55利息收入，56利息支出，57手续费及佣金收入，58手续费及佣金支出，59投资损益，60公允价值变动损益，61汇兑损益，62资产处置损益，63其他业务收入，64营业支出，65营业外收入，66营业外支出，67资产减值损失，68所得税，69少数股东损益。 表外业务类别：70承兑汇票，71跟单信用证，72保函，73信用风险仍在银行的销售与购买协议，74其他担保类业务，75可随时无条件撤销的贷款承诺，76不可无条件撤销的贷款承诺，77未使用的信用卡授信额度，78其他承诺，79发行非保本理财产品，80委托贷款，81委托投资，82代理代销业务，83资产托管，84其他金融资产服务业务，85金融衍生品类。 | F80: C..300
B81: 003007 | C81: 借贷标志 | D81: D.C. flag | E81: 借，贷，借贷并列。 | F81: C..12
B82: 003008 | C82: 金额 | D82: Amount | E82: 与币种相对应金额。 | F82: D20.2
B83: 003009 | C83: 余额 | D83: Balance | E83: 与币种相对应金额。(以正数填列。如信贷分户账，某客户初次获得贷款1万元，此时余额为10000；如活期存款明细，某客户初次开户存入10000元，此时余额为10000） | F83: D20.2
B84: 003010 | C84: 币种 | D84: Currency | E84: 遵循《GB/T 12406 表示货币和资金的代码》的字母代码，如CNY。上述文件所列币种无法涵盖的，允许银行自定义填报。多个币种合计折算为人民币（本外币合计）的，填报为BWB。 | F84: C3
B85: 003011 | C85: 账户名称 | D85: Account name | E85: 不同类型的账户名称按照相应规定命名，如人民币银行结算账户名称须符合《人民币银行结算账户管理办法》（中国人民银行令2003年第5号）第二十四条规定。银行内部账户名称由银行自定义。如户名为自然人名称，则为隐私，银行机构变形，变形规则见《采集技术接口说明》。客户是境内涉密机构的，账户名称填报为“*********”。其他情况，则为非隐私，不做变形。 | F85: C..450
B86: 003012 | C86: 个人存款账户类型 | D86: Type of individual deposit account | E86: 个人活期存款，个人定期存款，定活两便存款，个人通知存款，个人协议存款，个人协定存款，个人保证金存款，个人结构性存款（不含保本理财），个人其他存款。 | F86: C..60
... B99: 003025 | C99: 外部账号 | D99: Outer account number | E99: 客户交易时所使用的实际账号（银行提供给客户的账号，而非系统记账账号）。如，个人账号报送卡号、折号、单号或客户账号；对公活期账号报送活期存款账号对应的客户账号；对公定期账号报送与该业务绑定交易的客户账号；第三方平台账号报送第三方平台实际支付的账号。 | F99: C..60
A100: 交易流水信息 | B100: 004
B101: 004001 | C101: 交易序列号 | D101: Trading time stamp | E101: 唯一标识该笔交易的编号，银行自定义。可以是业务编号，也可以是交易系统中使用的时间戳，需能够体现交易次序，如：时间戳(纳秒)：1530027865231834600。 | F101: C..100
B102: 004002 | C102: 交易类型 | D102: Trading type | E102: 转账，取现，存现，消费，代发，代扣，代缴，结息，批量交易，贷款发放，贷款还本，贷款还息，银证业务，投资理财，其他-银行自定义类型。无法以枚举类型填报的，以“其他-XX”报送，其中“XX”为银行自定义类型。 | F102: C..60
B103: 004003 | C103: 交易渠道 | D103: Trading channel | E103: 柜面，ATM，VTM，POS，网银，手机银行，银联交易，第三方支付-银行自定义，其他-银行自定义。交易类型为第三方支付的，以“第三方支付-XX”填报，其中“XX”为第三方支付平台名称。如无法以枚举类型填报，则以“其他-XX”填报，其中“XX”为银行自定义类型。 | F103: C..60
B104: 004004 | C104: 现转标志 | D104: Cash or transfer | E104: 现，转。 | F104: C3
B105: 004005 | C105: 摘要 | D105: Memo | E105: 银行自定义交易内容的简要描述。 | F105: C..600
B106: 004006 | C106: 附言 | D106: Postscript | E106: 客户在交易凭证上的真实备注、附言。 | F106: C..600
B107: 004007 | C107: 冲补抹标志 | D107: Regular， strike， mend | E107: 正常，冲补抹。 | F107: C..9
B108: 004008 | C108: 卡片交易类型 | D108: Card trading type | E108: 现金交易，还款交易，消费交易，转账交易，其他-银行自定义。以枚举类型填报，如无法以枚举类型填报，则以“其他-XX”填报，其中“XX”为银行自定义类型。 | F108: C..60
B109: 004009 | C109: 担保说明 | D109: Guarantee illustration | E109: 中文字典或中文描述，银行自定义。 | F109: C..600
A110: 授信交易信息 | B110: 005
B111: 005001 | C111: 产品名称 | D111: Product name | E111: 银行内部产品中文名称，银行自定义。 | F111: C..300
B112: 005002 | C112: 合同名称 | D112: Contract name | E112: 信贷合同的中文名称，银行自定义。 | F112: C..300
B113: 005003 | C113: 信贷业务种类 | D113: Loan business type | E113: 流动资金贷款，法人账户透支，项目贷款，项目贷款（银团），一般固定资产贷款，住房按揭贷款，商用房贷款，汽车贷款，助学贷款，消费贷款，个人经营性贷款，票据贴现，买断式转贴现，贸易融资业务，融资租赁业务，垫款，委托贷款，其他-银行自定义类型。以枚举类型填报，如无法以枚举类型填报，则以“其他-XX”填报，其中“XX”为银行自定义类型。 | F113: C..150
B114: 005004 | C114: 利率浮动 | D114: Rate float | E114: 基准点为单位。浮动比例与上浮比例均折算点数填报。如上浮1%是填100.00，下浮1%是填-100.00，精确到小数点后2位。如果利率类型是固定利率，则利率浮动填写0.00。如利率类型是浮动利率，则与利率基准结合进行计算。 | F114: D20.6
B115: 005005 | C115: 放款方式 | D115: Distribute way | E115: 自主支付，受托支付，混合支付，其他-银行自定义。以枚举类型填报，如无法以枚举类型填报，则以“其他-XX”填报，其中“XX”为银行自定义方式。 | F115: C..30
B116: 005006 | C116: 贷款用途 | D116: Loan purpose | E116: 贷款使用的具体内容。 | F116: C..1500
B117: 005007 | C117: 贷款投向行业 | D117: Invest industry | E117: 与1104报表G01_VII《贷款分行业情况表》口径一致，使用以下枚举值填报（序号+名称）：2.1农、林、牧、渔业；2.2采矿业；2.3制造业；2.4电力、热力、燃气及水的生产和供应业；2.5建筑业；2.6批发和零售业；2.7交通运输、仓储和邮政业；2.8住宿和餐饮业；2.9信息传输、软件和信息技术服务业；2.10金融业；2.11房地产业；2.12租赁和商务服务业；2.13科学研究和技术服务业；2.14水利、环境和公共设施管理业；2.15居民服务、修理和其他服务业；2.16教育；2.17卫生和社会工作；2.18文化、体育和娱乐业；2.19公共管理、社会保障和社会组织；2.20国际组织；2.21.1个人贷款-信用卡；2.21.2个人贷款-汽车；2.21.3个人贷款-住房按揭贷款；2.21.4个人贷款-其他；2.22买断式转贴现；2.23买断其他票据类资产；3.对境外贷款。 | F117: C..100
B118: 005008 | C118: 项目名称 | D118: Project name | E118: 项目贷款对应的项目名称。 | F118: C..300
B119: 005009 | C119: 项目类型 | D119: Project type | E119: 基础设施建设项目，房地产项目，技术改造项目，科技开发项目，并购贷款，其他-银行自定义类型。如无法以枚举类型填报，则以“其他-XX”填报，其中“XX”为银行自定义类型。 | F119: C..60
B120: 005010 | C120: 批文文号 | D120: Approval number | E120: 银行自定义。 | F120: C..60
B121: 005011 | C121: 立项批文 | D121: Project approval | E121: 批文名称，可银行自定义。 | F121: C..60
B122: 005012 | C122: 许可证编号 | D122: Permition number | E122: 银行自定义。 | F122: C..60
... B159: 005049 | C159: 贸易内容 | D159: Trade content | E159: 贸易交易内容、货品或服务的简述信息，银行自定义，应填写中文。 | F159: C..1500
A160: 卡片信息 | B160: 006
B161: 006001 | C161: 卡号 | D161: Card number | E161: 卡号，可以是借记卡号，贷记卡号等。 | F161: C..60
B162: 006002 | C162: 借记卡产品名称 | D162: Debit card name | E162: 借记卡产品名称，中文字典或中文描述，银行自定义。 | F162: C..150
B163: 006003 | C163: 卡片状态 | D163: Card state | E163: 未激活，正常，注销，冻结，睡眠，挂失，其他-银行自定义。以枚举类型填报，如果无法以枚举类型填报的，以“其他-XX”填报，其中XX为银行自定义的卡片状态。 | F163: C..30
B164: 006004 | C164: 存折类型 | D164: Passbook type | E164: 普通存折，存单，一本通，大额定期存单，其他-银行自定义。无法以枚举类型填报的，以“其他-XX”填报，其中XX为银行自定义的类型。 | F164: C..30
B165: 006005 | C165: 存折状态 | D165: Passbook state | E165: 未激活，正常，注销，冻结，睡眠，挂失，其他-银行自定义。无法以枚举类型填报的，以“其他-XX”填报，其中XX为银行自定义状态。 | F165: C..30
B166: 006006 | C166: 卡片名称 | D166: Card name | E166: 信用卡片种类名称。 | F166: C..60
B167: 006007 | C167: 卡片种类 | D167: Card type | E167: 个人卡，单位卡。 | F167: C9
B168: 006008 | C168: 卡片级别 | D168: Card level | E168: 中文字典或中文描述，银行自定义。 | F168: C..60
B169: 006009 | C169: 发卡渠道 | D169: Card issuing | E169: 银行网点、银行卡中心直销、银行官方网站（含网银渠道）、手机终端（银行APP）、合作发卡、第三方机构引流、其他-银行自定义。无法以枚举类型填报的，以“其他-XX”填报，其中XX为银行自定义类型。 | F169: C..60
B170: 006010 | C170: 商户编号 | D170: Merchant ID | E170: 唯一识别商户的编码。可以是商业银行自有商户编号，也可以是第三方支付机构收单交易显示的商户编号。 | F170: C..200
B171: 006011 | C171: 商户名称 | D171: Merchant Name | E171: 商户注册登记的名称。 | F171: C..450
B172: 006012 | C172: 商户MCC码 | D172: MCC Code | E172: 商户类别码。由四位数字代码组成。 | F172: C4
... B178: 006018 | C178: 清算账号类型 | D178: Banding account type | E178: 本行卡，本行对公结算账户，他行卡，他行对公结算账户，第三方平台账户-银行自定义，其他-银行自定义。无法以枚举类型填报的，以“其他-XX”填报，其中XX为银行自定义类型。清算账号为第三方平台账户的，需填报至具体平台名称。 | F178: C..60
A179: 信贷管理信息 | B179: 007
B180: 007001 | C180: 授信协议号 | D180: Credit agreement number | E180: 填报银行授予客户授信额度的授信号码（或授信合同号码），该号码唯一标识该笔授信。若银行对该客户有多笔授信，应逐笔填列。 | F180: C..60
B181: 007002 | C181: 授信主体种类 | D181: Credit type | E181: 单一法人授信，供应链融资，个人客户授信，同业客户授信，其他-银行自定义。无法以枚举类型填报的，以“其他-XX”填报，其中XX为银行自定义种类。 | F181: C..60
B182: 007003 | C182: 授信种类 | D182: Credit granting type | E182: 综合额度授信，低风险额度授信，信用卡额度授信，临时额度授信，专项额度授信，其他-银行自定义。无法以枚举类型填报的，以“其他-XX”填报，其中XX为银行自定义种类。 | F182: C..60
B183: 007004 | C183: 信用卡授信类型 | D183: Credit card granting type | E183: 新发卡授信、固定额度上调,专项分期额度上调,其他-银行自定义。无法以枚举类型填报的，以“其他-XX”填报，其中XX为银行自定义类型。 | F183: C..60
B184: 007005 | C184: 信用卡异常标识 | D184: Credit card exception type | E184: 盗刷,套现,用于投资,流向房地产,用于生产经营,其他-银行自定义。无法以枚举类型填报的，以“其他-XX”填报，其中XX为银行自定义类型。 | F184: C..60
B185: 007006 | C185: 催收方式 | D185: Collection method | E185: 电话催收，信函催收，外访催收，司法催收，其他-银行自定义。无法以枚举类型填报的，以“其他-XX”填报，其中XX为银行自定义类型。 | F185: C..60
B186: 007007 | C186: 信用卡限制措施 | D186: Restrictive measures | E186: 警告,降额,止付,提前还款，其他-银行自定义。无法以枚举类型填报的，以“其他-XX”填报，其中XX为银行自定义类型。 | F186: C..60
B187: 007008 | C187: 有效状态 | D187: Validity status | E187: 有效，无效。 | F187: C6
B188: 007009 | C188: 审批意见 | D188: Decision | E188: 银行授信批复全文。 | F188: C..3000
B189: 007010 | C189: 信贷资产类型 | D189: Loan asset type | E189: 个人贷款，对公贷款，信用卡贷款。 | F189: C..30
B190: 007011 | C190: 核销资产类型 | D190: Write off asset type | E190: 个人贷款，对公贷款，信用卡贷款，非信贷类债权，股权。 | F190: C..30
B191: 007012 | C191: 变动方式 | D191: Variation way | E191: 人工，自动。 | F191: C..30
... B204: 007025 | C204: 互联贷款合作协议状态 | D204: Internet-based Agreement state | E204: 有效，撤销，终结，其他-银行自定义。无法以枚举类型填报的，以“其他-XX”填报，其中“XX”为银行自定义状态。 | F204: C..30
...

Sheet 数据结构
A2: 中国银保监会银行业金融机构监管数据标准化规范（2021版）
A4: 分类 | B4: 分类编号 | C4: 传输文件名称 | D4: 表名 | E4: 表编号 | F4: 数据项名称 | G4: 数据项编号 | H4: 数据项代码 | I4: 数据元 | J4: 数据元编码 | K4: 数据元说明 | L4: 格式 | M4: 备注 | N4: 变更类型 | O4: 变更规范列 | P4: 变更说明
A6: 公共信息 | B6: 001 | F6: 数据治理体系公众号推荐
C7: JGXXB | D7: 机构信息表 | E7: 101 | M7: =INDEX(表结构总览!D:G,MATCH(D7,表结构总览!D:D,0),4) -> 本表报送银行机构或业务中心信息，业务中心包含管理机构、营业机构、内设机构、虚拟机构。对于营业机构、内设机构、虚拟机构，银行机构代码、金融许可证号等字段可以取上级机构或者本级实体机构对应的信息（优先取本级实体机构）。境外机构也需要报送，根据实际情况无法填报的字段可以为空。子公司不必报送（理财子公司应报送）。内设机构标准：承担业务归属的机构。机构永久关停、撤销等情况的，在报送最后状态的次月可不再报送。 | N7: 修改 | O7: 备注
C8: JGXXB | D8: 机构信息表 | E8: 101 | F8: 银行机构代码 | G8: 10101 | H8: YHJGDM | I8: 银行机构代码 | J8: =INDEX(数据元说明!A:F,MATCH(I8,数据元说明!C:C,0),2) -> 001010 | K8: =INDEX(数据元说明!A:F,MATCH(I8,数据元说明!C:C,0),5) -> 12位人行支付行号或SWIFT行号。 | L8: =INDEX(数据元说明!A:F,MATCH(I8,数据元说明!C:C,0),6) -> C..30 | M8: 需填报人行大小额支付系统中登记的“人行支付行号”；允许多个内部机构号对应同一个“人行支付行号”；该字段不可为空，内设机构、虚拟机构等无“人行支付行号”的，填报本级或上一级机构的“人行支付行号”，优先填本级。
C9: JGXXB | D9: 机构信息表 | E9: 101 | F9: 内部机构号 | G9: 10102 | H9: NBJGH | I9: 内部机构号 | J9: =INDEX(数据元说明!A:F,MATCH(I9,数据元说明!C:C,0),2) -> 001012 | K9: =INDEX(数据元说明!A:F,MATCH(I9,数据元说明!C:C,0),5) -> 银行内部机构号。应具有标识机构的唯一性。 | L9: =INDEX(数据元说明!A:F,MATCH(I9,数据元说明!C:C,0),6) -> C..30 | M9: PK
C10: JGXXB | D10: 机构信息表 | E10: 101 | F10: 金融许可证号 | G10: 10103 | H10: JRXKZH | I10: 金融许可证号 | J10: =INDEX(数据元说明!A:F,MATCH(I10,数据元说明!C:C,0),2) -> 001011 | K10: =INDEX(数据元说明!A:F,MATCH(I10,数据元说明!C:C,0),5) -> 金融许可证机构编码编制规则（试行） 一、机构编码结构 机构编码由大写英文字母和数字组成，共15位。分六个部分，分别是机构类型代码、机构代码、组织类别代码、发证机关代码、地址代码、顺序代码，从左至右顺序排列，如下表所示。 二、机构编码含义 （一）第［一］位是机构类型代码，用大写英文字母表示。 A-政策性银行 B-商业银行 C-农村合作银行 D-城市信用社 E-农村信用社 F-资金互助社 J-金融资产管理公司 K-信托公司 L-财务公司 M-金融租赁公司 N-汽车金融公司 P-货币经纪公司 Q-贷款公司 Z-其他类金融机构 新增机构类型时，根据需要确定机构类型代码。 （二）第［二］位至第［五］位是机构代码，用数字表示。 1.每个法人机构指定唯一的代码，由计算机系统按照规则自动生成。除农村信用社、资金互助社、贷款公司（E、F、Q类机构）外，全国统一编码。E、F、Q类机构在省（自治区、直辖市）范围内统一编码。 2.新设立的机构依照所属机构类型顺序排列。 机构代码编码示例如下： A-政策性银行 0001-国家开发银行 …… B-商业银行 0001-中国工商银行股份有限公司 …… C-农村合作银行 0001-天津大港农村合作银行 …… D-城市信用社 0001-邯郸市城市信用社股份有限公司 …… E-农村信用社天津市 0001-天津市宝坻区农村信用合作联社 …… 新疆维吾尔自治区 0001-新疆维吾尔自治区农村信用社联合社 …… F-资金互助社 吉林省 0001-吉林省梨树县闰家村百信农村资金互助社 …… 青海省 0001-青海省乐都县雨润镇兴乐农村资金互助社 …… J-金融资产管理公司 0001-中国华融资产管理公司 …… K-信托投资公司 0001-中诚信托投资有限责任公司 …… L-财务公司 0001-中海石油财务有限责任公司 …… M-金融租赁公司 0001-中国外贸金融租赁公司 …… N-汽车金融公司 0001-大众汽车金融（中国）有限公司 …… P-货币经纪公司 0001-上海国利货币经纪有限公司 …… Q-贷款公司四川省 0001-四川省仪陇县惠民贷款有限责任公司 …… 新疆维吾尔自治区 0001- …… Z-其他类金融机构 0001-中央国债登记结算有限责任公司 …… （三）第〔六〕位是组织类别代码，用大写英文字母表示。 机构类型不同，组织类别代码的含义不同。定义如下： 1.A-政策性银行 H-总行 G-总行营业部 H-级分行 K-一级分行营业部 M-二级分行 S-支行 X-其他分支机构 2.B-商业银行 H-总行 G-总行营业部、专营机构 B-一级分行 K-一级分行营业部 L-二级分行 M-直属支行 N-二级分行营业部 S-支行 U-分理处、办事处、营业所 V-储蓄所 X-其他分支机构 3.C-农村合作银行 H-总行 S-支行 U-分理处 V-储蓄所 X-其他分支机构 4.D-城市信用社 H-法人 S-分社、营业部 X-其他分支机构 5.E-农村信用社 H-省（自治区、直辖市）联合社 B-地（市）联合社、联社 S-县（市）联合社、联社、合作社（县级） T-信用合作社 U-信用社、分社 V-储蓄所 X-其他分支机构 6.F-资金互助社 H-法人 7.J-金融资产管理公司 H-总公司 B-办事处 X-其他分支机构 8.K-信托公司 H-法人 9.N-汽车金融公司 H-法人 10.L-财务公司 H-总公司 B-分公司 X-其他分支机构 11.M-金融租赁公司 H-总公司 B-分公司 X-其他分支机构 12.P-货币经纪公司 H-总公司 B-分公司 X-其他分支机构 13.Q-贷款公司 H-总公司 B-分公司 X-其他分支机构 14.Z-其他类金融机构 Z类机构组织类别代码编码方法参照以上规则。 新增机构类型时，参照以上规则，根据实际情况定义其组织类别代码。 （四）第〔七〕位是发证机关代码，用数字表示。 1-银保监会 2-银监局 3-银监分局 （五）第〔八〕位至第〔十一〕是地址代码，用数字表示。按照《中华人民共和国行政区划代码》 （GB/T2260），取市（地区、自治州、盟）、直辖市行政区划代码前四位，作为地址代码。 地址代码示例如下：1100表示北京市，1200表示天津市，1301表示石家庄市，…… （六）第〔十二〕位至第〔十五〕位是顺序代码，用数字表示。机构类型代码、机构代码、组织类别代码、发证机关代码和地址代码相同的机构按照制发金融许可证的顺序编码。 三、机构编码的编制规则 编制机构编码时，按照从左至右的顺序依次确定机构类型代码、机构代码、组织类别代码、发证机关代码、地址代码、顺序代码，由计算机自动生成。 为了保证机构编码的唯一性，以利于电子计算机较长时间地存储数据，因行政许可变更需换发金融许可证，涉及机构编码变更的，原机构编码不再使用.金融机构终止的，机构编码不再使用。注销开业许可收回金融许可证的，机构编码不再使用。 | L10: =INDEX(数据元说明!A:F,MATCH(I10,数据元说明!C:C,0),6) -> C..30 | M10: 内设机构、虚拟机构及营业部如有金融许可证的填写金融许可证号，没有金融许可证的取上一级管理机构的金融许可证号。 | N10: 修改 | O10: 备注
C11: JGXXB | D11: 机构信息表 | E11: 101 | F11: 营业执照号 | G11: 10104 | H11: YYZZH | I11: 营业执照号 | J11: =INDEX(数据元说明!A:F,MATCH(I11,数据元说明!C:C,0),2) -> 002012 | K11: =INDEX(数据元说明!A:F,MATCH(I11,数据元说明!C:C,0),5) -> 已登记统一社会信用代码的，填18位统一社会信用代码；未登记统一社会信用代码的，填报营业执照注册号。 | L11: =INDEX(数据元说明!A:F,MATCH(I11,数据元说明!C:C,0),6) -> C..60 | M11: 内设机构、虚拟机构及营业部如有营业执照的填写营业执照号，没有营业执照的取上一级管理机构的营业执照号。 | N11: 修改 | O11: 备注
C12: JGXXB | D12: 机构信息表 | E12: 101 | F12: 银行机构名称 | G12: 10105 | H12: YHJGMC | I12: 名称 | J12: =INDEX(数据元说明!A:F,MATCH(I12,数据元说明!C:C,0),2) -> 001001 | K12: =INDEX(数据元说明!A:F,MATCH(I12,数据元说明!C:C,0),5) -> 名称应与公章所使用的名称完全一致。银行机构以银保监会金融机构许可证登记名称为准。无独立金融机构许可证的机构，可在本名称中体现出机构特征。第三方支付平台填报第三方支付平台名称。 客户名称按照客户的不同类型按如下标准填报。 （1）集团客户，填报银行对该集团授信采用的集团客户名称。视同集团客户填报的供应链融资填报核心企业客户名称。 （2）单一法人客户，经有关部门批准正式使用的全称，与公章所使用的名称完全一致。视同单一法人客户填报的分公司，填报分公司全称，与分公司公章所使用的名称完全一致。客户是境内涉密机构的，客户名称填报为“*********”。 （3）同业客户，经有关部门批准正式使用的客户全称，与客户公章所使用的名称完全一致。 （4）自然人，与有效证件上的姓名一致。 （5）境外客户，客户名称填报英文名称。 | L12: =INDEX(数据元说明!A:F,MATCH(I12,数据元说明!C:C,0),6) -> C..450 | M12: 需填写全称，有金融许可证号的需与金融许可证上的机构名称保持一致。例如：应填报“XX银行股份有限公司XX省分行”，不应填报为“XX省分行”。无独立金融机构许可证的机构，可在本名称中体现出机构特征。 | N12: 修改 | O12: 格式
C13: JGXXB | D13: 机构信息表 | E13: 101 | F13: 机构类别 | G13: 10106 | H13: JGLB | I13: 机构类别 | J13: =INDEX(数据元说明!A:F,MATCH(I13,数据元说明!C:C,0),2) -> 001013 | K13: =INDEX(数据元说明!A:F,MATCH(I13,数据元说明!C:C,0),5) -> 管理机构，营业机构，虚拟机构，内设机构。 | L13: =INDEX(数据元说明!A:F,MATCH(I13,数据元说明!C:C,0),6) -> C..30 | M13: 仅允许填报为：管理机构，营业机构，虚拟机构，内设机构。 各行根据实际情况进行映射： 管理机构：总行、一级分行、专营机构； 营业机构：除总行、一级分行、专营机构以外的有金融许可证的实体机构。专营机构分支机构作为营业机构。营业部也作为营业机构，若无金融许可证号则填报上一级管理机构的金融许可证号； 虚拟机构：具有单独标识、分账核算体系、独立出表的非实体机构，如自由贸易专用账务核算体系（FTU-Free Trade Accounting Unit）； 内设机构：如清算中心等内设部门。 | N13: 修改 | O13: 数据元说明、备注
C14: JGXXB | D14: 机构信息表 | E14: 101 | F14: 行政区划代码 | G14: 10107 | H14: XZQHDM | I14: 地区代码 | J14: =INDEX(数据元说明!A:F,MATCH(I14,数据元说明!C:C,0),2) -> 001028 | K14: =INDEX(数据元说明!A:F,MATCH(I14,数据元说明!C:C,0),5) -> 境内地区参照《GB/T 2260 中华人民共和国行政区划代码》填写国内行政区划代码，填写至二级分类，如110100。境外地区参照《GB/T 2659 世界各国和地区名称代码》定义的三字符代码，如USA。 | L14: =INDEX(数据元说明!A:F,MATCH(I14,数据元说明!C:C,0),6) -> C..6 | M14: 营业机构、管理机构必须填报实际的“行政区划代码”（要求到区县一级，6位代码），内设机构、虚拟机构，营业部取本级或上一级管理机构的行政区划代码，优先取本级。 | N14: 新增
C15: JGXXB | D15: 机构信息表 | E15: 101 | F15: 营业状态 | G15: 10108 | H15: YYZT | I15: 营业状态 | J15: =INDEX(数据元说明!A:F,MATCH(I15,数据元说明!C:C,0),2) -> 001014 | K15: =INDEX(数据元说明!A:F,MATCH(I15,数据元说明!C:C,0),5) -> 营业，停业。 | L15: =INDEX(数据元说明!A:F,MATCH(I15,数据元说明!C:C,0),6) -> C6 | M15: 营业：正常、拟撤销等状态的机构 停业：歇业、筹建中等状态的机构
C16: JGXXB | D16: 机构信息表 | E16: 101 | F16: 成立日期 | G16: 10109 | H16: CLRQ | I16: 日期 | J16: =INDEX(数据元说明!A:F,MATCH(I16,数据元说明!C:C,0),2) -> 001005 | K16: =INDEX(数据元说明!A:F,MATCH(I16,数据元说明!C:C,0),5) -> YYYYMMDD，默认值99991231。 | L16: =INDEX(数据元说明!A:F,MATCH(I16,数据元说明!C:C,0),6) -> C8 | M16: 填报银保监会及其派出机构批复成立的日期 | N16: 修改 | O16: 数据项名称、数据项代码、备注
C17: JGXXB | D17: 机构信息表 | E17: 101 | F17: 机构地址 | G17: 10110 | H17: JGDZ | I17: 地址 | J17: =INDEX(数据元说明!A:F,MATCH(I17,数据元说明!C:C,0),2) -> 001008 | K17: =INDEX(数据元说明!A:F,MATCH(I17,数据元说明!C:C,0),5) -> 中文描述。个人填报个人住址。机构填报有关部门批准的有效证件上登记的地址。参照《企业法人营业执照》中的注册地填报，要写明省（区、市）、地（区、市、州、盟）、县（区、市、旗）。境内涉密机构不填报。客户为境外企业的，填报客户在境外的注册地址（英文）。 | L17: =INDEX(数据元说明!A:F,MATCH(I17,数据元说明!C:C,0),6) -> C..600 | M17: 虚拟机构可为空
C18: JGXXB | D18: 机构信息表 | E18: 101 | F18: 机构联系电话 | G18: 10111 | H18: JGLXDH | I18: 电话 | J18: =INDEX(数据元说明!A:F,MATCH(I18,数据元说明!C:C,0),2) -> 001009 | K18: =INDEX(数据元说明!A:F,MATCH(I18,数据元说明!C:C,0),5) -> 手机号码或者区号-固定电话号码。 | L18: =INDEX(数据元说明!A:F,MATCH(I18,数据元说明!C:C,0),6) -> C..30 | M18: 机构办公联系电话，区号-座机电话，虚拟机构、自助银行及自助设备机构、机构本部和仅承担内部核算职能的机构可为空。非隐私，不做变形。 | N18: 新增
C19: JGXXB | D19: 机构信息表 | E19: 101 | F19: 负责人姓名 | G19: 10112 | H19: FZRXM | I19: 姓名 | J19: =INDEX(数据元说明!A:F,MATCH(I19,数据元说明!C:C,0),2) -> 001016 | K19: =INDEX(数据元说明!A:F,MATCH(I19,数据元说明!C:C,0),5) -> 姓名。 | L19: =INDEX(数据元说明!A:F,MATCH(I19,数据元说明!C:C,0),6) -> C..150 | M19: 非隐私，不做变形。虚拟机构、自助银行及自助设备机构、机构本部和仅承担内部核算职能的机构可为空。
C20: JGXXB | D20: 机构信息表 | E20: 101 | F20: 负责人职务 | G20: 10113 | H20: FZRZW | I20: 职务 | J20: =INDEX(数据元说明!A:F,MATCH(I20,数据元说明!C:C,0),2) -> 001018 | K20: =INDEX(数据元说明!A:F,MATCH(I20,数据元说明!C:C,0),5) -> 中文字典或中文描述，银行自定义。 | L20: =INDEX(数据元说明!A:F,MATCH(I20,数据元说明!C:C,0),6) -> C..150 | M20: 虚拟机构、自助银行及自助设备机构、机构本部和仅承担内部核算职能的机构可为空。
C21: JGXXB | D21: 机构信息表 | E21: 101 | F21: 负责人联系电话 | G21: 10114 | H21: FZRLXDH | I21: 电话 | J21: =INDEX(数据元说明!A:F,MATCH(I21,数据元说明!C:C,0),2) -> 001009 | K21: =INDEX(数据元说明!A:F,MATCH(I21,数据元说明!C:C,0),5) -> 手机号码或者区号-固定电话号码。 | L21: =INDEX(数据元说明!A:F,MATCH(I21,数据元说明!C:C,0),6) -> C..30 | M21: 负责人联系电话，区号-座机电话/手机，虚拟机构、自助银行及自助设备机构、机构本部和仅承担内部核算职能的机构可为空。非隐私，不做变形 | N21: 修改 | O21: 备注
C22: JGXXB | D22: 机构信息表 | E22: 101 | F22: 备注 | G22: 10115 | H22: BBZ | I22: 备注 | J22: =INDEX(数据元说明!A:F,MATCH(I22,数据元说明!C:C,0),2) -> 001038 | K22: =INDEX(数据元说明!A:F,MATCH(I22,数据元说明!C:C,0),5) -> 银行自定义。 | L22: =INDEX(数据元说明!A:F,MATCH(I22,数据元说明!C:C,0),6) -> C..600 | M22: 描述其他字段未能详尽说明的情况，或标注对本条报送记录的特殊说明（如视需要可用于说明各种不满足检核规则的例外情况：客户信息表中可标注“境外客户”“客户已工商注销”“客户名下账户均已管控”，信贷分户账中可标注“线上化业务”“自助类贷款”等）。不同备注事项用英文半角分号隔开。 | N22: 新增
C23: JGXXB | D23: 机构信息表 | E23: 101 | F23: 采集日期 | G23: 10116 | H23: CJRQ | I23: 日期 | J23: =INDEX(数据元说明!A:F,MATCH(I23,数据元说明!C:C,0),2) -> 001005 | K23: =INDEX(数据元说明!A:F,MATCH(I23,数据元说明!C:C,0),5) -> YYYYMMDD，默认值99991231。 | L23: =INDEX(数据元说明!A:F,MATCH(I23,数据元说明!C:C,0),6) -> C8 | M23: PK。采集日期指该期（批次）数据报送的期末日期，例如：按日采集的表，采集日期应为每日；按月采集的表，采集日期应为月末最后一天；以此类推。有特殊报送要求的，应以报送要求的截至日期为采集日期。
C24: YGB | D24: 员工表 | E24: 102 | M24: =INDEX(表结构总览!D:G,MATCH(D24,表结构总览!D:D,0),4) -> 在职类员工需每月报送。员工状态转为离职的，在报送该员工最后状态的次月可不再报送。子公司员工不用报送（理财子公司应报送）。 | N24: 修改 | O24: 备注
C25: YGB | D25: 员工表 | E25: 102 | F25: 金融许可证号 | G25: 10201 | H25: JRXKZH | I25: 金融许可证号 | J25: =INDEX(数据元说明!A:F,MATCH(I25,数据元说明!C:C,0),2) -> 001011 | K25: =INDEX(数据元说明!A:F,MATCH(I25,数据元说明!C:C,0),5) -> 金融许可证机构编码编制规则（试行） 一、机构编码结构 机构编码由大写英文字母和数字组成，共15位。分六个部分，分别是机构类型代码、机构代码、组织类别代码、发证机关代码、地址代码、顺序代码，从左至右顺序排列，如下表所示。 二、机构编码含义 （一）第［一］位是机构类型代码，用大写英文字母表示。 A-政策性银行 B-商业银行 C-农村合作银行 D-城市信用社 E-农村信用社 F-资金互助社 J-金融资产管理公司 K-信托公司 L-财务公司 M-金融租赁公司 N-汽车金融公司 P-货币经纪公司 Q-贷款公司 Z-其他类金融机构 新增机构类型时，根据需要确定机构类型代码。 （二）第［二］位至第［五］位是机构代码，用数字表示。 1.每个法人机构指定唯一的代码，由计算机系统按照规则自动生成。除农村信用社、资金互助社、贷款公司（E、F、Q类机构）外，全国统一编码。E、F、Q类机构在省（自治区、直辖市）范围内统一编码。 2.新设立的机构依照所属机构类型顺序排列。 机构代码编码示例如下： A-政策性银行 0001-国家开发银行 …… B-商业银行 0001-中国工商银行股份有限公司 …… C-农村合作银行 0001-天津大港农村合作银行 …… D-城市信用社 0001-邯郸市城市信用社股份有限公司 …… E-农村信用社天津市 0001-天津市宝坻区农村信用合作联社 …… 新疆维吾尔自治区 0001-新疆维吾尔自治区农村信用社联合社 …… F-资金互助社 吉林省 0001-吉林省梨树县闰家村百信农村资金互助社 …… 青海省 0001-青海省乐都县雨润镇兴乐农村资金互助社 …… J-金融资产管理公司 0001-中国华融资产管理公司 …… K-信托投资公司 0001-中诚信托投资有限责任公司 …… L-财务公司 0001-中海石油财务有限责任公司 …… M-金融租赁公司 0001-中国外贸金融租赁公司 …… N-汽车金融公司 0001-大众汽车金融（中国）有限公司 …… P-货币经纪公司 0001-上海国利货币经纪有限公司 …… Q-贷款公司四川省 0001-四川省仪陇县惠民贷款有限责任公司 …… 新疆维吾尔自治区 0001- …… Z-其他类金融机构 0001-中央国债登记结算有限责任公司 …… （三）第〔六〕位是组织类别代码，用大写英文字母表示。 机构类型不同，组织类别代码的含义不同。定义如下： 1.A-政策性银行 H-总行 G-总行营业部 H-级分行 K-一级分行营业部 M-二级分行 S-支行 X-其他分支机构 2.B-商业银行 H-总行 G-总行营业部、专营机构 B-一级分行 K-一级分行营业部 L-二级分行 M-直属支行 N-二级分行营业部 S-支行 U-分理处、办事处、营业所 V-储蓄所 X-其他分支机构 3.C-农村合作银行 H-总行 S-支行 U-分理处 V-储蓄所 X-其他分支机构 4.D-城市信用社 H-法人 S-分社、营业部 X-其他分支机构 5.E-农村信用社 H-省（自治区、直辖市）联合社 B-地（市）联合社、联社 S-县（市）联合社、联社、合作社（县级） T-信用合作社 U-信用社、分社 V-储蓄所 X-其他分支机构 6.F-资金互助社 H-法人 7.J-金融资产管理公司 H-总公司 B-办事处 X-其他分支机构 8.K-信托公司 H-法人 9.N-汽车金融公司 H-法人 10.L-财务公司 H-总公司 B-分公司 X-其他分支机构 11.M-金融租赁公司 H-总公司 B-分公司 X-其他分支机构 12.P-货币经纪公司 H-总公司 B-分公司 X-其他分支机构 13.Q-贷款公司 H-总公司 B-分公司 X-其他分支机构 14.Z-其他类金融机构 Z类机构组织类别代码编码方法参照以上规则。 新增机构类型时，参照以上规则，根据实际情况定义其组织类别代码。 （四）第〔七〕位是发证机关代码，用数字表示。 1-银保监会 2-银监局 3-银监分局 （五）第〔八〕位至第〔十一〕是地址代码，用数字表示。按照《中华人民共和国行政区划代码》 （GB/T2260），取市（地区、自治州、盟）、直辖市行政区划代码前四位，作为地址代码。 地址代码示例如下：1100表示北京市，1200表示天津市，1301表示石家庄市，…… （六）第〔十二〕位至第〔十五〕位是顺序代码，用数字表示。机构类型代码、机构代码、组织类别代码、发证机关代码和地址代码相同的机构按照制发金融许可证的顺序编码。 三、机构编码的编制规则 编制机构编码时，按照从左至右的顺序依次确定机构类型代码、机构代码、组织类别代码、发证机关代码、地址代码、顺序代码，由计算机自动生成。 为了保证机构编码的唯一性，以利于电子计算机较长时间地存储数据，因行政许可变更需换发金融许可证，涉及机构编码变更的，原机构编码不再使用.金融机构终止的，机构编码不再使用。注销开业许可收回金融许可证的，机构编码不再使用。 | L25: =INDEX(数据元说明!A:F,MATCH(I25,数据元说明!C:C,0),6) -> C..30 | M25: 营业机构、管理机构必须填报“金融许可证号”，内设机构、虚拟机构及营业部取本级或上一级管理机构的金融许可证号，优先取本级。 | N25: 修改 | O25: 备注
C26: YGB | D26: 员工表 | E26: 102 | F26: 内部机构号 | G26: 10202 | H26: NBJGH | I26: 内部机构号 | J26: =INDEX(数据元说明!A:F,MATCH(I26,数据元说明!C:C,0),2) -> 001012 | K26: =INDEX(数据元说明!A:F,MATCH(I26,数据元说明!C:C,0),5) -> 银行内部机构号。应具有标识机构的唯一性。 | L26: =INDEX(数据元说明!A:F,MATCH(I26,数据元说明!C:C,0),6) -> C..30 | M26: 关联数据项：机构信息表.内部机构号。员工如果采集区间发生过更换机构，按采集时点的最后填报内部机构号。 | N26: 修改 | O26: 备注
C27: YGB | D27: 员工表 | E27: 102 | F27: 银行机构名称 | G27: 10203 | H27: YHJGMC | I27: 名称 | J27: =INDEX(数据元说明!A:F,MATCH(I27,数据元说明!C:C,0),2) -> 001001 | K27: =INDEX(数据元说明!A:F,MATCH(I27,数据元说明!C:C,0),5) -> 名称应与公章所使用的名称完全一致。银行机构以银保监会金融机构许可证登记名称为准。无独立金融机构许可证的机构，可在本名称中体现出机构特征。第三方支付平台填报第三方支付平台名称。 客户名称按照客户的不同类型按如下标准填报。 （1）集团客户，填报银行对该集团授信采用的集团客户名称。视同集团客户填报的供应链融资填报核心企业客户名称。 （2）单一法人客户，经有关部门批准正式使用的全称，与公章所使用的名称完全一致。视同单一法人客户填报的分公司，填报分公司全称，与分公司公章所使用的名称完全一致。客户是境内涉密机构的，客户名称填报为“*********”。 （3）同业客户，经有关部门批准正式使用的客户全称，与客户公章所使用的名称完全一致。 （4）自然人，与有效证件上的姓名一致。 （5）境外客户，客户名称填报英文名称。 | L27: =INDEX(数据元说明!A:F,MATCH(I27,数据元说明!C:C,0),6) -> C..450 | M27: 需填写全称，有金融许可证号的需与金融许可证上的机构名称保持一致。关联数据项：机构信息表.银行机构名称 | N27: 修改 | O27: 格式
C28: YGB | D28: 员工表 | E28: 102 | F28: 工号 | G28: 10204 | H28: GH | I28: 工号 | J28: =INDEX(数据元说明!A:F,MATCH(I28,数据元说明!C:C,0),2) -> 001015 | K28: =INDEX(数据元说明!A:F,MATCH(I28,数据元说明!C:C,0),5) -> 工号，银行自定义。 | L28: =INDEX(数据元说明!A:F,MATCH(I28,数据元说明!C:C,0),6) -> C..30 | M28: PK。非员工高管可报送脱敏后的身份证号。 | N28: 修改 | O28: 备注 | P28: 调整数据项位置
C29: YGB | D29: 员工表 | E29: 102 | F29: 姓名 | G29: 10205 | H29: XM | I29: 姓名 | J29: =INDEX(数据元说明!A:F,MATCH(I29,数据元说明!C:C,0),2) -> 001016 | K29: =INDEX(数据元说明!A:F,MATCH(I29,数据元说明!C:C,0),5) -> 姓名。 | L29: =INDEX(数据元说明!A:F,MATCH(I29,数据元说明!C:C,0),6) -> C..150 | M29: 员工姓名为非隐私，不做变形。 | N29: 修改 | O29: 备注
C30: YGB | D30: 员工表 | E30: 102 | F30: 国籍 | G30: 10206 | H30: GJ | I30: 国籍 | J30: =INDEX(数据元说明!A:F,MATCH(I30,数据元说明!C:C,0),2) -> 002004 | K30: =INDEX(数据元说明!A:F,MATCH(I30,数据元说明!C:C,0),5) -> 参照《GB/T 2659-2000 世界各国和地区名称》，填报中文名称。 | L30: =INDEX(数据元说明!A:F,MATCH(I30,数据元说明!C:C,0),6) -> C..60 | M30: 国籍为中国的员工，员工信息需以中文填报。 | N30: 新增
C31: YGB | D31: 员工表 | E31: 102 | F31: 证件类别 | G31: 10207 | H31: ZJLB | I31: 证件类别 | J31: =INDEX(数据元说明!A:F,MATCH(I31,数据元说明!C:C,0),2) -> 002002 | K31: =INDEX(数据元说明!A:F,MATCH(I31,数据元说明!C:C,0),5) -> 同业客户：银行机构代码，金融许可证号，SWIFT编码，其他-XX。 对公客户：统一社会信用代码，组织机构代码，营业执照（工商注册号），公司注册证书，全球法人识别码，其他-XX。 个人客户：居民身份证，军官证，文职干部证，警官证，士兵证，户口簿，临时身份证，其他有效通行旅行证件，护照，学生证，无证件，其他-XX。 无法以枚举类型填报的，以“其他-XX”报送，其中“XX”为银行自定义类型。 对公客户优先填报统一社会信用代码，没有统一社会信用代码的对公客户填报组织机构代码。组织机构代码、统一社会信用代码均没有的可以填报客户提供的批文文号、开户主证件、上级机构统一社会信用代码等，以“其他-XX”填报。 | L31: =INDEX(数据元说明!A:F,MATCH(I31,数据元说明!C:C,0),6) -> C..60
C32: YGB | D32: 员工表 | E32: 102 | F32: 证件号码 | G32: 10208 | H32: ZJHM | I32: 证件号码 | J32: =INDEX(数据元说明!A:F,MATCH(I32,数据元说明!C:C,0),2) -> 002003 | K32: =INDEX(数据元说明!A:F,MATCH(I32,数据元说明!C:C,0),5) -> 与证件类别对应的证件号码。涉及个人身份证件时需按照本规范给定规则进行脱敏处理。 | L32: =INDEX(数据元说明!A:F,MATCH(I32,数据元说明!C:C,0),6) -> C..70 | M32: 隐私，银行机构变形。变形规则见《采集技术接口说明》。 | N32: 修改 | O32: 数据项代码 | P32: 调整数据项位置
C33: YGB | D33: 员工表 | E33: 102 | F33: 联系电话 | G33: 10209 | H33: LXDH | I33: 电话 | J33: =INDEX(数据元说明!A:F,MATCH(I33,数据元说明!C:C,0),2) -> 001009 | K33: =INDEX(数据元说明!A:F,MATCH(I33,数据元说明!C:C,0),5) -> 手机号码或者区号-固定电话号码。 | L33: =INDEX(数据元说明!A:F,MATCH(I33,数据元说明!C:C,0),6) -> C..30 | M33: 非隐私，不做变形。 | N33: 修改 | O33: 备注
C34: YGB | D34: 员工表 | E34: 102 | F34: 所属部门 | G34: 10210 | H34: SSBM | I34: 所属部门 | J34: =INDEX(数据元说明!A:F,MATCH(I34,数据元说明!C:C,0),2) -> 001017 | K34: =INDEX(数据元说明!A:F,MATCH(I34,数据元说明!C:C,0),5) -> 中文字典或中文描述，银行自定义。 | L34: =INDEX(数据元说明!A:F,MATCH(I34,数据元说明!C:C,0),6) -> C..150
C35: YGB | D35: 员工表 | E35: 102 | F35: 岗位编号 | G35: 10211 | H35: GWBH | I35: 岗位编号 | J35: =INDEX(数据元说明!A:F,MATCH(I35,数据元说明!C:C,0),2) -> 001023 | K35: =INDEX(数据元说明!A:F,MATCH(I35,数据元说明!C:C,0),5) -> 银行自定义。 | L35: =INDEX(数据元说明!A:F,MATCH(I35,数据元说明!C:C,0),6) -> C..60 | M35: 同一员工存在多个岗位时，用英文半角分号隔开。 | N35: 修改 | O35: 备注 | P35: 增加备注说明
C36: YGB | D36: 员工表 | E36: 102 | F36: 岗位名称 | G36: 10212 | H36: GWMC | I36: 岗位名称 | J36: =INDEX(数据元说明!A:F,MATCH(I36,数据元说明!C:C,0),2) -> 001025 | K36: =INDEX(数据元说明!A:F,MATCH(I36,数据元说明!C:C,0),5) -> 岗位名称，中文字典或中文描述，银行自定义。 | L36: =INDEX(数据元说明!A:F,MATCH(I36,数据元说明!C:C,0),6) -> C..150 | M36: 同一员工存在多个岗位时，用英文半角分号隔开。 | N36: 新增
C37: YGB | D37: 员工表 | E37: 102 | F37: 是否高管 | G37: 10213 | H37: SFGG | I37: 是否标志 | J37: =INDEX(数据元说明!A:F,MATCH(I37,数据元说明!C:C,0),2) -> 001002 | K37: =INDEX(数据元说明!A:F,MATCH(I37,数据元说明!C:C,0),5) -> 是，否。 | L37: =INDEX(数据元说明!A:F,MATCH(I37,数据元说明!C:C,0),6) -> C3 | M37: 任职资格经银保监会及其派出机构批复的，填写为是。 | N37: 新增
C38: YGB | D38: 员工表 | E38: 102 | F38: 批复日期 | G38: 10214 | H38: PFRQ | I38: 日期 | J38: =INDEX(数据元说明!A:F,MATCH(I38,数据元说明!C:C,0),2) -> 001005 | K38: =INDEX(数据元说明!A:F,MATCH(I38,数据元说明!C:C,0),5) -> YYYYMMDD，默认值99991231。 | L38: =INDEX(数据元说明!A:F,MATCH(I38,数据元说明!C:C,0),6) -> C8 | M38: 任职资格经银保监会及其派出机构批复的必填，其他允许为空。 | N38: 新增
C39: YGB | D39: 员工表 | E39: 102 | F39: 任职日期 | G39: 10215 | H39: RZRQ | I39: 日期 | J39: =INDEX(数据元说明!A:F,MATCH(I39,数据元说明!C:C,0),2) -> 001005 | K39: =INDEX(数据元说明!A:F,MATCH(I39,数据元说明!C:C,0),5) -> YYYYMMDD，默认值99991231。 | L39: =INDEX(数据元说明!A:F,MATCH(I39,数据元说明!C:C,0),6) -> C8 | M39: 任职资格经银保监会及其派出机构批复的必填，其他允许为空。 | N39: 新增
C40: YGB | D40: 员工表 | E40: 102 | F40: 员工类型 | G40: 10216 | H40: YGLX | I40: 员工类型 | J40: =INDEX(数据元说明!A:F,MATCH(I40,数据元说明!C:C,0),2) -> 001033 | K40: =INDEX(数据元说明!A:F,MATCH(I40,数据元说明!C:C,0),5) -> 正式员工，非员工高管，非正式员工，其他-银行自定义。无法以枚举类型填报的，以“其他-XX”填报，其中“XX”为银行自定义类型。 | L40: =INDEX(数据元说明!A:F,MATCH(I40,数据元说明!C:C,0),6) -> C..30 | M40: 正式员工是指与银行业金融机构签订劳动合同的员工。非员工高管是指不是本机构员工的董（理）事会成员、监事会成员、高级管理人员。非正式员工是指银行业金融机构聘用或与劳务派遣机构签订协议从事辅助性金融服务的其他人员。 | N40: 新增 | O40: 数据元、备注 | P40: 增加备注说明
C41: YGB | D41: 员工表 | E41: 102 | F41: 员工状态 | G41: 10217 | H41: YGZT | I41: 员工状态 | J41: =INDEX(数据元说明!A:F,MATCH(I41,数据元说明!C:C,0),2) -> 001034 | K41: =INDEX(数据元说明!A:F,MATCH(I41,数据元说明!C:C,0),5) -> 在岗，离岗，离职，其他-银行自定义。无法以枚举类型填报的，以“其他-XX”填报，其中“XX”为银行自定义类型。 | L41: =INDEX(数据元说明!A:F,MATCH(I41,数据元说明!C:C,0),6) -> C..30 | N41: 修改 | O41: 数据元、备注 | P41: 增加备注说明
C42: YGB | D42: 员工表 | E42: 102 | F42: 备注 | G42: 10218 | H42: BBZ | I42: 备注 | J42: =INDEX(数据元说明!A:F,MATCH(I42,数据元说明!C:C,0),2) -> 001038 | K42: =INDEX(数据元说明!A:F,MATCH(I42,数据元说明!C:C,0),5) -> 银行自定义。 | L42: =INDEX(数据元说明!A:F,MATCH(I42,数据元说明!C:C,0),6) -> C..600 | M42: 描述其他字段未能详尽说明的情况，或标注对本条报送记录的特殊说明（如视需要可用于说明各种不满足检核规则的例外情况：客户信息表中可标注“境外客户”“客户已工商注销”“客户名下账户均已管控”，信贷分户账中可标注“线上化业务”“自助类贷款”等）。不同备注事项用英文半角分号隔开。 | N42: 新增
C43: YGB | D43: 员工表 | E43: 102 | F43: 采集日期 | G43: 10219 | H43: CJRQ | I43: 日期 | J43: =INDEX(数据元说明!A:F,MATCH(I43,数据元说明!C:C,0),2) -> 001005 | K43: =INDEX(数据元说明!A:F,MATCH(I43,数据元说明!C:C,0),5) -> YYYYMMDD，默认值99991231。 | L43: =INDEX(数据元说明!A:F,MATCH(I43,数据元说明!C:C,0),6) -> C8 | M43: PK。采集日期指该期（批次）数据报送的期末日期，例如：按日采集的表，采集日期应为每日；按月采集的表，采集日期应为月末最后一天；以此类推。有特殊报送要求的，应以报送要求的截至日期为采集日期。
C44: GYB | D44: 柜员表 | E44: 103 | M44: =INDEX(表结构总览!D:G,MATCH(D44,表结构总览!D:D,0),4) -> 包含实体柜员和虚拟柜员。为虚拟柜员时，工号、银行机构代码等字段依业务实际填列（若无则置空），如报送虚拟柜员，则通过“柜员类型”字段进行区分；柜员状态转为注销、无效等时，可在报送该条数据最终状态的次月不再报送。 | N44: 修改 | O44: 备注 | P44: 增加备注说明
C45: GYB | D45: 柜员表 | E45: 103 | F45: 金融许可证号 | G45: 10301 | H45: JRXKZH | I45: 金融许可证号 | J45: =INDEX(数据元说明!A:F,MATCH(I45,数据元说明!C:C,0),2) -> 001011 | K45: =INDEX(数据元说明!A:F,MATCH(I45,数据元说明!C:C,0),5) -> 金融许可证机构编码编制规则（试行） 一、机构编码结构 机构编码由大写英文字母和数字组成，共15位。分六个部分，分别是机构类型代码、机构代码、组织类别代码、发证机关代码、地址代码、顺序代码，从左至右顺序排列，如下表所示。 二、机构编码含义 （一）第［一］位是机构类型代码，用大写英文字母表示。 A-政策性银行 B-商业银行 C-农村合作银行 D-城市信用社 E-农村信用社 F-资金互助社 J-金融资产管理公司 K-信托公司 L-财务公司 M-金融租赁公司 N-汽车金融公司 P-货币经纪公司 Q-贷款公司 Z-其他类金融机构 新增机构类型时，根据需要确定机构类型代码。 （二）第［二］位至第［五］位是机构代码，用数字表示。 1.每个法人机构指定唯一的代码，由计算机系统按照规则自动生成。除农村信用社、资金互助社、贷款公司（E、F、Q类机构）外，全国统一编码。E、F、Q类机构在省（自治区、直辖市）范围内统一编码。 2.新设立的机构依照所属机构类型顺序排列。 机构代码编码示例如下： A-政策性银行 0001-国家开发银行 …… B-商业银行 0001-中国工商银行股份有限公司 …… C-农村合作银行 0001-天津大港农村合作银行 …… D-城市信用社 0001-邯郸市城市信用社股份有限公司 …… E-农村信用社天津市 0001-天津市宝坻区农村信用合作联社 …… 新疆维吾尔自治区 0001-新疆维吾尔自治区农村信用社联合社 …… F-资金互助社 吉林省 0001-吉林省梨树县闰家村百信农村资金互助社 …… 青海省 0001-青海省乐都县雨润镇兴乐农村资金互助社 …… J-金融资产管理公司 0001-中国华融资产管理公司 …… K-信托投资公司 0001-中诚信托投资有限责任公司 …… L-财务公司 0001-中海石油财务有限责任公司 …… M-金融租赁公司 0001-中国外贸金融租赁公司 …… N-汽车金融公司 0001-大众汽车金融（中国）有限公司 …… P-货币经纪公司 0001-上海国利货币经纪有限公司 …… Q-贷款公司四川省 0001-四川省仪陇县惠民贷款有限责任公司 …… 新疆维吾尔自治区 0001- …… Z-其他类金融机构 0001-中央国债登记结算有限责任公司 …… （三）第〔六〕位是组织类别代码，用大写英文字母表示。 机构类型不同，组织类别代码的含义不同。定义如下： 1.A-政策性银行 H-总行 G-总行营业部 H-级分行 K-一级分行营业部 M-二级分行 S-支行 X-其他分支机构 2.B-商业银行 H-总行 G-总行营业部、专营机构 B-一级分行 K-一级分行营业部 L-二级分行 M-直属支行 N-二级分行营业部 S-支行 U-分理处、办事处、营业所 V-储蓄所 X-其他分支机构 3.C-农村合作银行 H-总行 S-支行 U-分理处 V-储蓄所 X-其他分支机构 4.D-城市信用社 H-法人 S-分社、营业部 X-其他分支机构 5.E-农村信用社 H-省（自治区、直辖市）联合社 B-地（市）联合社、联社 S-县（市）联合社、联社、合作社（县级） T-信用合作社 U-信用社、分社 V-储蓄所 X-其他分支机构 6.F-资金互助社 H-法人 7.J-金融资产管理公司 H-总公司 B-办事处 X-其他分支机构 8.K-信托公司 H-法人 9.N-汽车金融公司 H-法人 10.L-财务公司 H-总公司 B-分公司 X-其他分支机构 11.M-金融租赁公司 H-总公司 B-分公司 X-其他分支机构 12.P-货币经纪公司 H-总公司 B-分公司 X-其他分支机构 13.Q-贷款公司 H-总公司 B-分公司 X-其他分支机构 14.Z-其他类金融机构 Z类机构组织类别代码编码方法参照以上规则。 新增机构类型时，参照以上规则，根据实际情况定义其组织类别代码。 （四）第〔七〕位是发证机关代码，用数字表示。 1-银保监会 2-银监局 3-银监分局 （五）第〔八〕位至第〔十一〕是地址代码，用数字表示。按照《中华人民共和国行政区划代码》 （GB/T2260），取市（地区、自治州、盟）、直辖市行政区划代码前四位，作为地址代码。 地址代码示例如下：1100表示北京市，1200表示天津市，1301表示石家庄市，…… （六）第〔十二〕位至第〔十五〕位是顺序代码，用数字表示。机构类型代码、机构代码、组织类别代码、发证机关代码和地址代码相同的机构按照制发金融许可证的顺序编码。 三、机构编码的编制规则 编制机构编码时，按照从左至右的顺序依次确定机构类型代码、机构代码、组织类别代码、发证机关代码、地址代码、顺序代码，由计算机自动生成。 为了保证机构编码的唯一性，以利于电子计算机较长时间地存储数据，因行政许可变更需换发金融许可证，涉及机构编码变更的，原机构编码不再使用.金融机构终止的，机构编码不再使用。注销开业许可收回金融许可证的，机构编码不再使用。 | L45: =INDEX(数据元说明!A:F,MATCH(I45,数据元说明!C:C,0),6) -> C..30 | M45: 营业机构、管理机构必须填报“金融许可证号”，内设机构、虚拟机构及营业部取本级或上一级管理机构的金融许可证号，优先取本级。 | N45: 修改 | O45: 备注
C46: GYB | D46: 柜员表 | E46: 103 | F46: 内部机构号 | G46: 10302 | H46: NBJGH | I46: 内部机构号 | J46: =INDEX(数据元说明!A:F,MATCH(I46,数据元说明!C:C,0),2) -> 001012 | K46: =INDEX(数据元说明!A:F,MATCH(I46,数据元说明!C:C,0),5) -> 银行内部机构号。应具有标识机构的唯一性。 | L46: =INDEX(数据元说明!A:F,MATCH(I46,数据元说明!C:C,0),6) -> C..30 | M46: PK。关联数据项：机构信息表.内部机构号
C47: GYB | D47: 柜员表 | E47: 103 | F47: 银行机构名称 | G47: 10303 | H47: YHJGMC | I47: 名称 | J47: =INDEX(数据元说明!A:F,MATCH(I47,数据元说明!C:C,0),2) -> 001001 | K47: =INDEX(数据元说明!A:F,MATCH(I47,数据元说明!C:C,0),5) -> 名称应与公章所使用的名称完全一致。银行机构以银保监会金融机构许可证登记名称为准。无独立金融机构许可证的机构，可在本名称中体现出机构特征。第三方支付平台填报第三方支付平台名称。 客户名称按照客户的不同类型按如下标准填报。 （1）集团客户，填报银行对该集团授信采用的集团客户名称。视同集团客户填报的供应链融资填报核心企业客户名称。 （2）单一法人客户，经有关部门批准正式使用的全称，与公章所使用的名称完全一致。视同单一法人客户填报的分公司，填报分公司全称，与分公司公章所使用的名称完全一致。客户是境内涉密机构的，客户名称填报为“*********”。 （3）同业客户，经有关部门批准正式使用的客户全称，与客户公章所使用的名称完全一致。 （4）自然人，与有效证件上的姓名一致。 （5）境外客户，客户名称填报英文名称。 | L47: =INDEX(数据元说明!A:F,MATCH(I47,数据元说明!C:C,0),6) -> C..450 | M47: 需填写全称，有金融许可证号的需与金融许可证上的机构名称保持一致。关联数据项：机构信息表.银行机构名称 | N47: 修改 | O47: 格式
C48: GYB | D48: 柜员表 | E48: 103 | F48: 柜员号 | G48: 10304 | H48: GYH | I48: 柜员号 | J48: =INDEX(数据元说明!A:F,MATCH(I48,数据元说明!C:C,0),2) -> 001020 | K48: =INDEX(数据元说明!A:F,MATCH(I48,数据元说明!C:C,0),5) -> 柜员编号，银行自定义。 | L48: =INDEX(数据元说明!A:F,MATCH(I48,数据元说明!C:C,0),6) -> C..30 | M48: PK，虚拟柜员也需要填写柜员号。 | N48: 修改 | O48: 备注 | P48: 调整数据项位置
C49: GYB | D49: 柜员表 | E49: 103 | F49: 工号 | G49: 10305 | H49: GH | I49: 工号 | J49: =INDEX(数据元说明!A:F,MATCH(I49,数据元说明!C:C,0),2) -> 001015 | K49: =INDEX(数据元说明!A:F,MATCH(I49,数据元说明!C:C,0),5) -> 工号，银行自定义。 | L49: =INDEX(数据元说明!A:F,MATCH(I49,数据元说明!C:C,0),6) -> C..30 | M49: 虚拟柜员员工号允许为空。关联数据项：员工表.工号。 | N49: 修改 | P49: 调整数据项位置
C50: GYB | D50: 柜员表 | E50: 103 | F50: 柜员类型 | G50: 10306 | H50: GYLX | I50: 柜员类型 | J50: =INDEX(数据元说明!A:F,MATCH(I50,数据元说明!C:C,0),2) -> 001021 | K50: =INDEX(数据元说明!A:F,MATCH(I50,数据元说明!C:C,0),5) -> 中文字典或中文描述，银行自定义。 | L50: =INDEX(数据元说明!A:F,MATCH(I50,数据元说明!C:C,0),6) -> C..30 | M50: 银行自定义，“柜员类型”需体现具体虚拟柜员，如自助银行，网银等。
C51: GYB | D51: 柜员表 | E51: 103 | F51: 是否实体柜员 | G51: 10307 | H51: SFSTGY | I51: 是否标志 | J51: =INDEX(数据元说明!A:F,MATCH(I51,数据元说明!C:C,0),2) -> 001002 | K51: =INDEX(数据元说明!A:F,MATCH(I51,数据元说明!C:C,0),5) -> 是，否。 | L51: =INDEX(数据元说明!A:F,MATCH(I51,数据元说明!C:C,0),6) -> C3 | M51: 必填，实体柜员填是，其他填否。
C52: GYB | D52: 柜员表 | E52: 103 | F52: 岗位编号 | G52: 10308 | H52: GWBH | I52: 岗位编号 | J52: =INDEX(数据元说明!A:F,MATCH(I52,数据元说明!C:C,0),2) -> 001023 | K52: =INDEX(数据元说明!A:F,MATCH(I52,数据元说明!C:C,0),5) -> 银行自定义。 | L52: =INDEX(数据元说明!A:F,MATCH(I52,数据元说明!C:C,0),6) -> C..60 | M52: 关联数据项：岗位信息表.岗位编号
C53: GYB | D53: 柜员表 | E53: 103 | F53: 柜员权限级别 | G53: 10309 | H53: GYQXJB | I53: 柜员权限级别 | J53: =INDEX(数据元说明!A:F,MATCH(I53,数据元说明!C:C,0),2) -> 001022 | K53: =INDEX(数据元说明!A:F,MATCH(I53,数据元说明!C:C,0),5) -> 高柜，低柜，其他-银行自定义。无法以枚举类型填报的，以“其他-XX”填报，其中“XX”为银行自定义类型。 | L53: =INDEX(数据元说明!A:F,MATCH(I53,数据元说明!C:C,0),6) -> C..30
C54: GYB | D54: 柜员表 | E54: 103 | F54: 上岗日期 | G54: 10310 | H54: SGRQ | I54: 日期 | J54: =INDEX(数据元说明!A:F,MATCH(I54,数据元说明!C:C,0),2) -> 001005 | K54: =INDEX(数据元说明!A:F,MATCH(I54,数据元说明!C:C,0),5) -> YYYYMMDD，默认值99991231。 | L54: =INDEX(数据元说明!A:F,MATCH(I54,数据元说明!C:C,0),6) -> C8 | M54: 虚拟柜员可填写默认日期。
C55: GYB | D55: 柜员表 | E55: 103 | F55: 柜员状态 | G55: 10311 | H55: GYZT | I55: 柜员状态 | J55: =INDEX(数据元说明!A:F,MATCH(I55,数据元说明!C:C,0),2) -> 001035 | K55: =INDEX(数据元说明!A:F,MATCH(I55,数据元说明!C:C,0),5) -> 在岗，离岗，其他-银行自定义。无法以枚举类型填报的，以“其他-XX”填报，其中“XX”为银行自定义类型。 | L55: =INDEX(数据元说明!A:F,MATCH(I55,数据元说明!C:C,0),6) -> 0 | N55: 修改 | O55: 数据元
C56: GYB | D56: 柜员表 | E56: 103 | F56: 备注 | G56: 10312 | H56: BBZ | I56: 备注 | J56: =INDEX(数据元说明!A:F,MATCH(I56,数据元说明!C:C,0),2) -> 001038 | K56: =INDEX(数据元说明!A:F,MATCH(I56,数据元说明!C:C,0),5) -> 银行自定义。 | L56: =INDEX(数据元说明!A:F,MATCH(I56,数据元说明!C:C,0),6) -> C..600 | M56: 描述其他字段未能详尽说明的情况，或标注对本条报送记录的特殊说明（如视需要可用于说明各种不满足检核规则的例外情况：客户信息表中可标注“境外客户”“客户已工商注销”“客户名下账户均已管控”，信贷分户账中可标注“线上化业务”“自助类贷款”等）。不同备注事项用英文半角分号隔开。 | N56: 新增
C57: GYB | D57: 柜员表 | E57: 103 | F57: 采集日期 | G57: 10313 | H57: CJRQ | I57: 日期 | J57: =INDEX(数据元说明!A:F,MATCH(I57,数据元说明!C:C,0),2) -> 001005 | K57: =INDEX(数据元说明!A:F,MATCH(I57,数据元说明!C:C,0),5) -> YYYYMMDD，默认值99991231。 | L57: =INDEX(数据元说明!A:F,MATCH(I57,数据元说明!C:C,0),6) -> C8 | M57: PK。采集日期指该期（批次）数据报送的期末日期，例如：按日采集的表，采集日期应为每日；按月采集的表，采集日期应为月末最后一天；以此类推。有特殊报送要求的，应以报送要求的截至日期为采集日期。
C58: GWXXB | D58: 岗位信息表 | E58: 104 | M58: =INDEX(表结构总览!D:G,MATCH(D58,表结构总览!D:D,0),4) -> 银行机构内设立的所有岗位的相关信息，至少应包括核心和人力资源系统中的所有岗位信息。撤销的岗位于次月不再报送。 | N58: 修改
C59: GWXXB | D59: 岗位信息表 | E59: 104 | F59: 金融许可证号 | G59: 10401 | H59: JRXKZH | I59: 金融许可证号 | J59: =INDEX(数据元说明!A:F,MATCH(I59,数据元说明!C:C,0),2) -> 001011 | K59: =INDEX(数据元说明!A:F,MATCH(I59,数据元说明!C:C,0),5) -> 金融许可证机构编码编制规则（试行） 一、机构编码结构 机构编码由大写英文字母和数字组成，共15位。分六个部分，分别是机构类型代码、机构代码、组织类别代码、发证机关代码、地址代码、顺序代码，从左至右顺序排列，如下表所示。 二、机构编码含义 （一）第［一］位是机构类型代码，用大写英文字母表示。 A-政策性银行 B-商业银行 C-农村合作银行 D-城市信用社 E-农村信用社 F-资金互助社 J-金融资产管理公司 K-信托公司 L-财务公司 M-金融租赁公司 N-汽车金融公司 P-货币经纪公司 Q-贷款公司 Z-其他类金融机构 新增机构类型时，根据需要确定机构类型代码。 （二）第［二］位至第［五］位是机构代码，用数字表示。 1.每个法人机构指定唯一的代码，由计算机系统按照规则自动生成。除农村信用社、资金互助社、贷款公司（E、F、Q类机构）外，全国统一编码。E、F、Q类机构在省（自治区、直辖市）范围内统一编码。 2.新设立的机构依照所属机构类型顺序排列。 机构代码编码示例如下： A-政策性银行 0001-国家开发银行 …… B-商业银行 0001-中国工商银行股份有限公司 …… C-农村合作银行 0001-天津大港农村合作银行 …… D-城市信用社 0001-邯郸市城市信用社股份有限公司 …… E-农村信用社天津市 0001-天津市宝坻区农村信用合作联社 …… 新疆维吾尔自治区 0001-新疆维吾尔自治区农村信用社联合社 …… F-资金互助社 吉林省 0001-吉林省梨树县闰家村百信农村资金互助社 …… 青海省 0001-青海省乐都县雨润镇兴乐农村资金互助社 …… J-金融资产管理公司 0001-中国华融资产管理公司 …… K-信托投资公司 0001-中诚信托投资有限责任公司 …… L-财务公司 0001-中海石油财务有限责任公司 …… M-金融租赁公司 0001-中国外贸金融租赁公司 …… N-汽车金融公司 0001-大众汽车金融（中国）有限公司 …… P-货币经纪公司 0001-上海国利货币经纪有限公司 …… Q-贷款公司四川省 0001-四川省仪陇县惠民贷款有限责任公司 …… 新疆维吾尔自治区 0001- …… Z-其他类金融机构 0001-中央国债登记结算有限责任公司 …… （三）第〔六〕位是组织类别代码，用大写英文字母表示。 机构类型不同，组织类别代码的含义不同。定义如下： 1.A-政策性银行 H-总行 G-总行营业部 H-级分行 K-一级分行营业部 M-二级分行 S-支行 X-其他分支机构 2.B-商业银行 H-总行 G-总行营业部、专营机构 B-一级分行 K-一级分行营业部 L-二级分行 M-直属支行 N-二级分行营业部 S-支行 U-分理处、办事处、营业所 V-储蓄所 X-其他分支机构 3.C-农村合作银行 H-总行 S-支行 U-分理处 V-储蓄所 X-其他分支机构 4.D-城市信用社 H-法人 S-分社、营业部 X-其他分支机构 5.E-农村信用社 H-省（自治区、直辖市）联合社 B-地（市）联合社、联社 S-县（市）联合社、联社、合作社（县级） T-信用合作社 U-信用社、分社 V-储蓄所 X-其他分支机构 6.F-资金互助社 H-法人 7.J-金融资产管理公司 H-总公司 B-办事处 X-其他分支机构 8.K-信托公司 H-法人 9.N-汽车金融公司 H-法人 10.L-财务公司 H-总公司 B-分公司 X-其他分支机构 11.M-金融租赁公司 H-总公司 B-分公司 X-其他分支机构 12.P-货币经纪公司 H-总公司 B-分公司 X-其他分支机构 13.Q-贷款公司 H-总公司 B-分公司 X-其他分支机构 14.Z-其他类金融机构 Z类机构组织类别代码编码方法参照以上规则。 新增机构类型时，参照以上规则，根据实际情况定义其组织类别代码。 （四）第〔七〕位是发证机关代码，用数字表示。 1-银保监会 2-银监局 3-银监分局 （五）第〔八〕位至第〔十一〕是地址代码，用数字表示。按照《中华人民共和国行政区划代码》 （GB/T2260），取市（地区、自治州、盟）、直辖市行政区划代码前四位，作为地址代码。 地址代码示例如下：1100表示北京市，1200表示天津市，1301表示石家庄市，…… （六）第〔十二〕位至第〔十五〕位是顺序代码，用数字表示。机构类型代码、机构代码、组织类别代码、发证机关代码和地址代码相同的机构按照制发金融许可证的顺序编码。 三、机构编码的编制规则 编制机构编码时，按照从左至右的顺序依次确定机构类型代码、机构代码、组织类别代码、发证机关代码、地址代码、顺序代码，由计算机自动生成。 为了保证机构编码的唯一性，以利于电子计算机较长时间地存储数据，因行政许可变更需换发金融许可证，涉及机构编码变更的，原机构编码不再使用.金融机构终止的，机构编码不再使用。注销开业许可收回金融许可证的，机构编码不再使用。 | L59: =INDEX(数据元说明!A:F,MATCH(I59,数据元说明!C:C,0),6) -> C..30 | M59: 营业机构、管理机构必须填报“金融许可证号”，内设机构、虚拟机构及营业部取本级或上一级管理机构的金融许可证号，优先取本级。 | N59: 修改 | O59: 备注
C60: GWXXB | D60: 岗位信息表 | E60: 104 | F60: 内部机构号 | G60: 10402 | H60: NBJGH | I60: 内部机构号 | J60: =INDEX(数据元说明!A:F,MATCH(I60,数据元说明!C:C,0),2) -> 001012 | K60: =INDEX(数据元说明!A:F,MATCH(I60,数据元说明!C:C,0),5) -> 银行内部机构号。应具有标识机构的唯一性。 | L60: =INDEX(数据元说明!A:F,MATCH(I60,数据元说明!C:C,0),6) -> C..30 | M60: PK。关联数据项：机构信息表.内部机构号
C61: GWXXB | D61: 岗位信息表 | E61: 104 | F61: 岗位编号 | G61: 10403 | H61: GWBH | I61: 岗位编号 | J61: =INDEX(数据元说明!A:F,MATCH(I61,数据元说明!C:C,0),2) -> 001023 | K61: =INDEX(数据元说明!A:F,MATCH(I61,数据元说明!C:C,0),5) -> 银行自定义。 | L61: =INDEX(数据元说明!A:F,MATCH(I61,数据元说明!C:C,0),6) -> C..60 | M61: PK。 | N61: 修改 | P61: 调整数据项位置
C62: GWXXB | D62: 岗位信息表 | E62: 104 | F62: 岗位种类 | G62: 10404 | H62: GWZL | I62: 岗位种类 | J62: =INDEX(数据元说明!A:F,MATCH(I62,数据元说明!C:C,0),2) -> 001024 | K62: =INDEX(数据元说明!A:F,MATCH(I62,数据元说明!C:C,0),5) -> 岗位种类，中文字典或中文描述，银行自定义。 | L62: =INDEX(数据元说明!A:F,MATCH(I62,数据元说明!C:C,0),6) -> C..60 | M62: 外资银行也应翻译文中文描述。
C63: GWXXB | D63: 岗位信息表 | E63: 104 | F63: 岗位名称 | G63: 10405 | H63: GWMC | I63: 岗位名称 | J63: =INDEX(数据元说明!A:F,MATCH(I63,数据元说明!C:C,0),2) -> 001025 | K63: =INDEX(数据元说明!A:F,MATCH(I63,数据元说明!C:C,0),5) -> 岗位名称，中文字典或中文描述，银行自定义。 | L63: =INDEX(数据元说明!A:F,MATCH(I63,数据元说明!C:C,0),6) -> C..150 | M63: 外资银行也应翻译文中文描述。
C64: GWXXB | D64: 岗位信息表 | E64: 104 | F64: 岗位说明 | G64: 10406 | H64: GWSM | I64: 岗位说明 | J64: =INDEX(数据元说明!A:F,MATCH(I64,数据元说明!C:C,0),2) -> 001026 | K64: =INDEX(数据元说明!A:F,MATCH(I64,数据元说明!C:C,0),5) -> 对岗位工作的中文描述，银行自定义。 | L64: =INDEX(数据元说明!A:F,MATCH(I64,数据元说明!C:C,0),6) -> C..600 | M64: 外资银行也应翻译文中文描述。
C65: GWXXB | D65: 岗位信息表 | E65: 104 | F65: 岗位状态 | G65: 10407 | H65: GWZT | I65: 状态 | J65: =INDEX(数据元说明!A:F,MATCH(I65,数据元说明!C:C,0),2) -> 001019 | K65: =INDEX(数据元说明!A:F,MATCH(I65,数据元说明!C:C,0),5) -> 中文字典或中文描述，银行自定义。 | L65: =INDEX(数据元说明!A:F,MATCH(I65,数据元说明!C:C,0),6) -> C..60
C66: GWXXB | D66: 岗位信息表 | E66: 104 | F66: 备注 | G66: 10408 | H66: BBZ | I66: 备注 | J66: =INDEX(数据元说明!A:F,MATCH(I66,数据元说明!C:C,0),2) -> 001038 | K66: =INDEX(数据元说明!A:F,MATCH(I66,数据元说明!C:C,0),5) -> 银行自定义。 | L66: =INDEX(数据元说明!A:F,MATCH(I66,数据元说明!C:C,0),6) -> C..600 | M66: 描述其他字段未能详尽说明的情况，或标注对本条报送记录的特殊说明（如视需要可用于说明各种不满足检核规则的例外情况：客户信息表中可标注“境外客户”“客户已工商注销”“客户名下账户均已管控”，信贷分户账中可标注“线上化业务”“自助类贷款”等）。不同备注事项用英文半角分号隔开。 | N66: 新增
C67: GWXXB | D67: 岗位信息表 | E67: 104 | F67: 采集日期 | G67: 10409 | H67: CJRQ | I67: 日期 | J67: =INDEX(数据元说明!A:F,MATCH(I67,数据元说明!C:C,0),2) -> 001005 | K67: =INDEX(数据元说明!A:F,MATCH(I67,数据元说明!C:C,0),5) -> YYYYMMDD，默认值99991231。 | L67: =INDEX(数据元说明!A:F,MATCH(I67,数据元说明!C:C,0),6) -> C8 | M67: PK。采集日期指该期（批次）数据报送的期末日期，例如：按日采集的表，采集日期应为每日；按月采集的表，采集日期应为月末最后一天；以此类推。有特殊报送要求的，应以报送要求的截至日期为采集日期。
C68: JGGXB | D68: 机构关系表 | E68: 105 | M68: =INDEX(表结构总览!D:G,MATCH(D68,表结构总览!D:D,0),4) -> 报送范围应包括所有进行账务处理的机构，至少应包括总行、分行、支行等实体机构和省级汇总、地市级汇总、法人汇总、分行汇总。会计全科目表中的机构在机构关系表中都需要报送，每次全量报送。 | N68: 修改
C69: JGGXB | D69: 机构关系表 | E69: 105 | F69: 银行机构代码 | G69: 10501 | H69: YHJGDM | I69: 银行机构代码 | J69: =INDEX(数据元说明!A:F,MATCH(I69,数据元说明!C:C,0),2) -> 001010 | K69: =INDEX(数据元说明!A:F,MATCH(I69,数据元说明!C:C,0),5) -> 12位人行支付行号或SWIFT行号。 | L69: =INDEX(数据元说明!A:F,MATCH(I69,数据元说明!C:C,0),6) -> C..30 | M69: 关联数据项：机构信息表.银行机构代码 | N69: 修改 | P69: 增加备注说明
C70: JGGXB | D70: 机构关系表 | E70: 105 | F70: 金融许可证号 | G70: 10502 | H70: JRXKZH | I70: 金融许可证号 | J70: =INDEX(数据元说明!A:F,MATCH(I70,数据元说明!C:C,0),2) -> 001011 | K70: =INDEX(数据元说明!A:F,MATCH(I70,数据元说明!C:C,0),5) -> 金融许可证机构编码编制规则（试行） 一、机构编码结构 机构编码由大写英文字母和数字组成，共15位。分六个部分，分别是机构类型代码、机构代码、组织类别代码、发证机关代码、地址代码、顺序代码，从左至右顺序排列，如下表所示。 二、机构编码含义 （一）第［一］位是机构类型代码，用大写英文字母表示。 A-政策性银行 B-商业银行 C-农村合作银行 D-城市信用社 E-农村信用社 F-资金互助社 J-金融资产管理公司 K-信托公司 L-财务公司 M-金融租赁公司 N-汽车金融公司 P-货币经纪公司 Q-贷款公司 Z-其他类金融机构 新增机构类型时，根据需要确定机构类型代码。 （二）第［二］位至第［五］位是机构代码，用数字表示。 1.每个法人机构指定唯一的代码，由计算机系统按照规则自动生成。除农村信用社、资金互助社、贷款公司（E、F、Q类机构）外，全国统一编码。E、F、Q类机构在省（自治区、直辖市）范围内统一编码。 2.新设立的机构依照所属机构类型顺序排列。 机构代码编码示例如下： A-政策性银行 0001-国家开发银行 …… B-商业银行 0001-中国工商银行股份有限公司 …… C-农村合作银行 0001-天津大港农村合作银行 …… D-城市信用社 0001-邯郸市城市信用社股份有限公司 …… E-农村信用社天津市 0001-天津市宝坻区农村信用合作联社 …… 新疆维吾尔自治区 0001-新疆维吾尔自治区农村信用社联合社 …… F-资金互助社 吉林省 0001-吉林省梨树县闰家村百信农村资金互助社 …… 青海省 0001-青海省乐都县雨润镇兴乐农村资金互助社 …… J-金融资产管理公司 0001-中国华融资产管理公司 …… K-信托投资公司 0001-中诚信托投资有限责任公司 …… L-财务公司 0001-中海石油财务有限责任公司 …… M-金融租赁公司 0001-中国外贸金融租赁公司 …… N-汽车金融公司 0001-大众汽车金融（中国）有限公司 …… P-货币经纪公司 0001-上海国利货币经纪有限公司 …… Q-贷款公司四川省 0001-四川省仪陇县惠民贷款有限责任公司 …… 新疆维吾尔自治区 0001- …… Z-其他类金融机构 0001-中央国债登记结算有限责任公司 …… （三）第〔六〕位是组织类别代码，用大写英文字母表示。 机构类型不同，组织类别代码的含义不同。定义如下： 1.A-政策性银行 H-总行 G-总行营业部 H-级分行 K-一级分行营业部 M-二级分行 S-支行 X-其他分支机构 2.B-商业银行 H-总行 G-总行营业部、专营机构 B-一级分行 K-一级分行营业部 L-二级分行 M-直属支行 N-二级分行营业部 S-支行 U-分理处、办事处、营业所 V-储蓄所 X-其他分支机构 3.C-农村合作银行 H-总行 S-支行 U-分理处 V-储蓄所 X-其他分支机构 4.D-城市信用社 H-法人 S-分社、营业部 X-其他分支机构 5.E-农村信用社 H-省（自治区、直辖市）联合社 B-地（市）联合社、联社 S-县（市）联合社、联社、合作社（县级） T-信用合作社 U-信用社、分社 V-储蓄所 X-其他分支机构 6.F-资金互助社 H-法人 7.J-金融资产管理公司 H-总公司 B-办事处 X-其他分支机构 8.K-信托公司 H-法人 9.N-汽车金融公司 H-法人 10.L-财务公司 H-总公司 B-分公司 X-其他分支机构 11.M-金融租赁公司 H-总公司 B-分公司 X-其他分支机构 12.P-货币经纪公司 H-总公司 B-分公司 X-其他分支机构 13.Q-贷款公司 H-总公司 B-分公司 X-其他分支机构 14.Z-其他类金融机构 Z类机构组织类别代码编码方法参照以上规则。 新增机构类型时，参照以上规则，根据实际情况定义其组织类别代码。 （四）第〔七〕位是发证机关代码，用数字表示。 1-银保监会 2-银监局 3-银监分局 （五）第〔八〕位至第〔十一〕是地址代码，用数字表示。按照《中华人民共和国行政区划代码》 （GB/T2260），取市（地区、自治州、盟）、直辖市行政区划代码前四位，作为地址代码。 地址代码示例如下：1100表示北京市，1200表示天津市，1301表示石家庄市，…… （六）第〔十二〕位至第〔十五〕位是顺序代码，用数字表示。机构类型代码、机构代码、组织类别代码、发证机关代码和地址代码相同的机构按照制发金融许可证的顺序编码。 三、机构编码的编制规则 编制机构编码时，按照从左至右的顺序依次确定机构类型代码、机构代码、组织类别代码、发证机关代码、地址代码、顺序代码，由计算机自动生成。 为了保证机构编码的唯一性，以利于电子计算机较长时间地存储数据，因行政许可变更需换发金融许可证，涉及机构编码变更的，原机构编码不再使用.金融机构终止的，机构编码不再使用。注销开业许可收回金融许可证的，机构编码不再使用。 | L70: =INDEX(数据元说明!A:F,MATCH(I70,数据元说明!C:C,0),6) -> C..30 | M70: 营业机构、管理机构必须填报“金融许可证号”，内设机构、虚拟机构及营业部取本级或上一级管理机构的金融许可证号，优先取本级。 | N70: 修改 | O70: 备注
C71: JGGXB | D71: 机构关系表 | E71: 105 | F71: 内部机构号 | G71: 10503 | H71: NBJGH | I71: 内部机构号 | J71: =INDEX(数据元说明!A:F,MATCH(I71,数据元说明!C:C,0),2) -> 001012 | K71: =INDEX(数据元说明!A:F,MATCH(I71,数据元说明!C:C,0),5) -> 银行内部机构号。应具有标识机构的唯一性。 | L71: =INDEX(数据元说明!A:F,MATCH(I71,数据元说明!C:C,0),6) -> C..30 | M71: PK
C72: JGGXB | D72: 机构关系表 | E72: 105 | F72: 银行机构名称 | G72: 10504 | H72: YHJGMC | I72: 名称 | J72: =INDEX(数据元说明!A:F,MATCH(I72,数据元说明!C:C,0),2) -> 001001 | K72: =INDEX(数据元说明!A:F,MATCH(I72,数据元说明!C:C,0),5) -> 名称应与公章所使用的名称完全一致。银行机构以银保监会金融机构许可证登记名称为准。无独立金融机构许可证的机构，可在本名称中体现出机构特征。第三方支付平台填报第三方支付平台名称。 客户名称按照客户的不同类型按如下标准填报。 （1）集团客户，填报银行对该集团授信采用的集团客户名称。视同集团客户填报的供应链融资填报核心企业客户名称。 （2）单一法人客户，经有关部门批准正式使用的全称，与公章所使用的名称完全一致。视同单一法人客户填报的分公司，填报分公司全称，与分公司公章所使用的名称完全一致。客户是境内涉密机构的，客户名称填报为“*********”。 （3）同业客户，经有关部门批准正式使用的客户全称，与客户公章所使用的名称完全一致。 （4）自然人，与有效证件上的姓名一致。 （5）境外客户，客户名称填报英文名称。 | L72: =INDEX(数据元说明!A:F,MATCH(I72,数据元说明!C:C,0),6) -> C..450 | M72: 需填写全称，有金融许可证号的需与金融许可证上的机构名称保持一致。关联数据项：机构信息表.银行机构名称 | N72: 修改 | O72: 格式 | P72: 增加备注说明
C73: JGGXB | D73: 机构关系表 | E73: 105 | F73: 上级管理机构代码 | G73: 10505 | H73: SJGLJGDM | I73: 银行机构代码 | J73: =INDEX(数据元说明!A:F,MATCH(I73,数据元说明!C:C,0),2) -> 001010 | K73: =INDEX(数据元说明!A:F,MATCH(I73,数据元说明!C:C,0),5) -> 12位人行支付行号或SWIFT行号。 | L73: =INDEX(数据元说明!A:F,MATCH(I73,数据元说明!C:C,0),6) -> C..30 | M73: 没有上级机构的该项填写为0。 | N73: 修改 | O73: 数据元
C74: JGGXB | D74: 机构关系表 | E74: 105 | F74: 上级管理内部机构号 | G74: 10506 | H74: SJGLNBJGH | I74: 内部机构号 | J74: =INDEX(数据元说明!A:F,MATCH(I74,数据元说明!C:C,0),2) -> 001012 | K74: =INDEX(数据元说明!A:F,MATCH(I74,数据元说明!C:C,0),5) -> 银行内部机构号。应具有标识机构的唯一性。 | L74: =INDEX(数据元说明!A:F,MATCH(I74,数据元说明!C:C,0),6) -> C..30 | M74: 没有上级机构的该项填写为0。 | N74: 新增
C75: JGGXB | D75: 机构关系表 | E75: 105 | F75: 上级管理机构名称 | G75: 10507 | H75: SJGLJGMC | I75: 名称 | J75: =INDEX(数据元说明!A:F,MATCH(I75,数据元说明!C:C,0),2) -> 001001 | K75: =INDEX(数据元说明!A:F,MATCH(I75,数据元说明!C:C,0),5) -> 名称应与公章所使用的名称完全一致。银行机构以银保监会金融机构许可证登记名称为准。无独立金融机构许可证的机构，可在本名称中体现出机构特征。第三方支付平台填报第三方支付平台名称。 客户名称按照客户的不同类型按如下标准填报。 （1）集团客户，填报银行对该集团授信采用的集团客户名称。视同集团客户填报的供应链融资填报核心企业客户名称。 （2）单一法人客户，经有关部门批准正式使用的全称，与公章所使用的名称完全一致。视同单一法人客户填报的分公司，填报分公司全称，与分公司公章所使用的名称完全一致。客户是境内涉密机构的，客户名称填报为“*********”。 （3）同业客户，经有关部门批准正式使用的客户全称，与客户公章所使用的名称完全一致。 （4）自然人，与有效证件上的姓名一致。 （5）境外客户，客户名称填报英文名称。 | L75: =INDEX(数据元说明!A:F,MATCH(I75,数据元说明!C:C,0),6) -> C..450 | M75: 没有上级机构的该项填写为空，其中总行本级上级机构为总行法人名称。 | N75: 修改 | O75: 格式、备注
C76: JGGXB | D76: 机构关系表 | E76: 105 | F76: 备注 | G76: 10508 | H76: BBZ | I76: 备注 | J76: =INDEX(数据元说明!A:F,MATCH(I76,数据元说明!C:C,0),2) -> 001038 | K76: =INDEX(数据元说明!A:F,MATCH(I76,数据元说明!C:C,0),5) -> 银行自定义。 | L76: =INDEX(数据元说明!A:F,MATCH(I76,数据元说明!C:C,0),6) -> C..600 | M76: 描述其他字段未能详尽说明的情况，或标注对本条报送记录的特殊说明（如视需要可用于说明各种不满足检核规则的例外情况：客户信息表中可标注“境外客户”“客户已工商注销”“客户名下账户均已管控”，信贷分户账中可标注“线上化业务”“自助类贷款”等）。不同备注事项用英文半角分号隔开。 | N76: 新增
C77: JGGXB | D77: 机构关系表 | E77: 105 | F77: 采集日期 | G77: 10509 | H77: CJRQ | I77: 日期 | J77: =INDEX(数据元说明!A:F,MATCH(I77,数据元说明!C:C,0),2) -> 001005 | K77: =INDEX(数据元说明!A:F,MATCH(I77,数据元说明!C:C,0),5) -> YYYYMMDD，默认值99991231。 | L77: =INDEX(数据元说明!A:F,MATCH(I77,数据元说明!C:C,0),6) -> C8 | M77: PK。采集日期指该期（批次）数据报送的期末日期，例如：按日采集的表，采集日期应为每日；按月采集的表，采集日期应为月末最后一天；以此类推。有特殊报送要求的，应以报送要求的截至日期为采集日期。
C78: GDJGLFXXB | D78: 股东及关联方信息表 | E78: 106 | M78: =INDEX(表结构总览!D:G,MATCH(D78,表结构总览!D:D,0),4) -> 填报银行股东及银行关联方相关信息。股东：对于已上市银行，需填报持有或控制1%以上股份或表决权，及虽不足1%但对商业银行经营管理有重大影响的股东。未上市银行机构应报送所有的对公、个人股东信息。包括金融产品。 关联方：参照《银行保险机构关联交易管理办法》（中国银行保险监督管理委员会令〔2022〕1号）第二章规定。 | N78: 修改
C79: GDJGLFXXB | D79: 股东及关联方信息表 | E79: 106 | F79: 金融许可证号 | G79: 10601 | H79: JRXKZH | I79: 金融许可证号 | J79: =INDEX(数据元说明!A:F,MATCH(I79,数据元说明!C:C,0),2) -> 001011 | K79: =INDEX(数据元说明!A:F,MATCH(I79,数据元说明!C:C,0),5) -> 金融许可证机构编码编制规则（试行） 一、机构编码结构 机构编码由大写英文字母和数字组成，共15位。分六个部分，分别是机构类型代码、机构代码、组织类别代码、发证机关代码、地址代码、顺序代码，从左至右顺序排列，如下表所示。 二、机构编码含义 （一）第［一］位是机构类型代码，用大写英文字母表示。 A-政策性银行 B-商业银行 C-农村合作银行 D-城市信用社 E-农村信用社 F-资金互助社 J-金融资产管理公司 K-信托公司 L-财务公司 M-金融租赁公司 N-汽车金融公司 P-货币经纪公司 Q-贷款公司 Z-其他类金融机构 新增机构类型时，根据需要确定机构类型代码。 （二）第［二］位至第［五］位是机构代码，用数字表示。 1.每个法人机构指定唯一的代码，由计算机系统按照规则自动生成。除农村信用社、资金互助社、贷款公司（E、F、Q类机构）外，全国统一编码。E、F、Q类机构在省（自治区、直辖市）范围内统一编码。 2.新设立的机构依照所属机构类型顺序排列。 机构代码编码示例如下： A-政策性银行 0001-国家开发银行 …… B-商业银行 0001-中国工商银行股份有限公司 …… C-农村合作银行 0001-天津大港农村合作银行 …… D-城市信用社 0001-邯郸市城市信用社股份有限公司 …… E-农村信用社天津市 0001-天津市宝坻区农村信用合作联社 …… 新疆维吾尔自治区 0001-新疆维吾尔自治区农村信用社联合社 …… F-资金互助社 吉林省 0001-吉林省梨树县闰家村百信农村资金互助社 …… 青海省 0001-青海省乐都县雨润镇兴乐农村资金互助社 …… J-金融资产管理公司 0001-中国华融资产管理公司 …… K-信托投资公司 0001-中诚信托投资有限责任公司 …… L-财务公司 0001-中海石油财务有限责任公司 …… M-金融租赁公司 0001-中国外贸金融租赁公司 …… N-汽车金融公司 0001-大众汽车金融（中国）有限公司 …… P-货币经纪公司 0001-上海国利货币经纪有限公司 …… Q-贷款公司四川省 0001-四川省仪陇县惠民贷款有限责任公司 …… 新疆维吾尔自治区 0001- …… Z-其他类金融机构 0001-中央国债登记结算有限责任公司 …… （三）第〔六〕位是组织类别代码，用大写英文字母表示。 机构类型不同，组织类别代码的含义不同。定义如下： 1.A-政策性银行 H-总行 G-总行营业部 H-级分行 K-一级分行营业部 M-二级分行 S-支行 X-其他分支机构 2.B-商业银行 H-总行 G-总行营业部、专营机构 B-一级分行 K-一级分行营业部 L-二级分行 M-直属支行 N-二级分行营业部 S-支行 U-分理处、办事处、营业所 V-储蓄所 X-其他分支机构 3.C-农村合作银行 H-总行 S-支行 U-分理处 V-储蓄所 X-其他分支机构 4.D-城市信用社 H-法人 S-分社、营业部 X-其他分支机构 5.E-农村信用社 H-省（自治区、直辖市）联合社 B-地（市）联合社、联社 S-县（市）联合社、联社、合作社（县级） T-信用合作社 U-信用社、分社 V-储蓄所 X-其他分支机构 6.F-资金互助社 H-法人 7.J-金融资产管理公司 H-总公司 B-办事处 X-其他分支机构 8.K-信托公司 H-法人 9.N-汽车金融公司 H-法人 10.L-财务公司 H-总公司 B-分公司 X-其他分支机构 11.M-金融租赁公司 H-总公司 B-分公司 X-其他分支机构 12.P-货币经纪公司 H-总公司 B-分公司 X-其他分支机构 13.Q-贷款公司 H-总公司 B-分公司 X-其他分支机构 14.Z-其他类金融机构 Z类机构组织类别代码编码方法参照以上规则。 新增机构类型时，参照以上规则，根据实际情况定义其组织类别代码。 （四）第〔七〕位是发证机关代码，用数字表示。 1-银保监会 2-银监局 3-银监分局 （五）第〔八〕位至第〔十一〕是地址代码，用数字表示。按照《中华人民共和国行政区划代码》 （GB/T2260），取市（地区、自治州、盟）、直辖市行政区划代码前四位，作为地址代码。 地址代码示例如下：1100表示北京市，1200表示天津市，1301表示石家庄市，…… （六）第〔十二〕位至第〔十五〕位是顺序代码，用数字表示。机构类型代码、机构代码、组织类别代码、发证机关代码和地址代码相同的机构按照制发金融许可证的顺序编码。 三、机构编码的编制规则 编制机构编码时，按照从左至右的顺序依次确定机构类型代码、机构代码、组织类别代码、发证机关代码、地址代码、顺序代码，由计算机自动生成。 为了保证机构编码的唯一性，以利于电子计算机较长时间地存储数据，因行政许可变更需换发金融许可证，涉及机构编码变更的，原机构编码不再使用.金融机构终止的，机构编码不再使用。注销开业许可收回金融许可证的，机构编码不再使用。 | L79: =INDEX(数据元说明!A:F,MATCH(I79,数据元说明!C:C,0),6) -> C..30 | M79: 填报机构金融许可证号。 | N79: 修改 | O79: 备注
C80: GDJGLFXXB | D80: 股东及关联方信息表 | E80: 106 | F80: 内部机构号 | G80: 10602 | H80: NBJGH | I80: 内部机构号 | J80: =INDEX(数据元说明!A:F,MATCH(I80,数据元说明!C:C,0),2) -> 001012 | K80: =INDEX(数据元说明!A:F,MATCH(I80,数据元说明!C:C,0),5) -> 银行内部机构号。应具有标识机构的唯一性。 | L80: =INDEX(数据元说明!A:F,MATCH(I80,数据元说明!C:C,0),6) -> C..30 | M80: PK
C81: GDJGLFXXB | D81: 股东及关联方信息表 | E81: 106 | F81: 银行机构名称 | G81: 10603 | H81: YHJGMC | I81: 名称 | J81: =INDEX(数据元说明!A:F,MATCH(I81,数据元说明!C:C,0),2) -> 001001 | K81: =INDEX(数据元说明!A:F,MATCH(I81,数据元说明!C:C,0),5) -> 名称应与公章所使用的名称完全一致。银行机构以银保监会金融机构许可证登记名称为准。无独立金融机构许可证的机构，可在本名称中体现出机构特征。第三方支付平台填报第三方支付平台名称。 客户名称按照客户的不同类型按如下标准填报。 （1）集团客户，填报银行对该集团授信采用的集团客户名称。视同集团客户填报的供应链融资填报核心企业客户名称。 （2）单一法人客户，经有关部门批准正式使用的全称，与公章所使用的名称完全一致。视同单一法人客户填报的分公司，填报分公司全称，与分公司公章所使用的名称完全一致。客户是境内涉密机构的，客户名称填报为“*********”。 （3）同业客户，经有关部门批准正式使用的客户全称，与客户公章所使用的名称完全一致。 （4）自然人，与有效证件上的姓名一致。 （5）境外客户，客户名称填报英文名称。 | L81: =INDEX(数据元说明!A:F,MATCH(I81,数据元说明!C:C,0),6) -> C..450 | M81: 填报本行法人机构名称。关联数据项：机构信息表.银行机构名称 | N81: 修改 | O81: 格式 | P81: 增加备注说明
C82: GDJGLFXXB | D82: 股东及关联方信息表 | E82: 106 | F82: 客户统一编号 | G82: 10604 | H82: KHTYBH | I82: 客户统一编号 | J82: =INDEX(数据元说明!A:F,MATCH(I82,数据元说明!C:C,0),2) -> 002001 | K82: =INDEX(数据元说明!A:F,MATCH(I82,数据元说明!C:C,0),5) -> 银行自定义的唯一识别客户的标识。供应链融资的填写供应链融资编码。 | L82: =INDEX(数据元说明!A:F,MATCH(I82,数据元说明!C:C,0),6) -> C..60 | M82: 如果股东不是本银行客户，填为空值。 | N82: 修改 | P82: 调整数据项位置
C83: GDJGLFXXB | D83: 股东及关联方信息表 | E83: 106 | F83: 股东或关联方名称 | G83: 10605 | H83: GDHGLFMC | I83: 名称 | J83: =INDEX(数据元说明!A:F,MATCH(I83,数据元说明!C:C,0),2) -> 001001 | K83: =INDEX(数据元说明!A:F,MATCH(I83,数据元说明!C:C,0),5) -> 名称应与公章所使用的名称完全一致。银行机构以银保监会金融机构许可证登记名称为准。无独立金融机构许可证的机构，可在本名称中体现出机构特征。第三方支付平台填报第三方支付平台名称。 客户名称按照客户的不同类型按如下标准填报。 （1）集团客户，填报银行对该集团授信采用的集团客户名称。视同集团客户填报的供应链融资填报核心企业客户名称。 （2）单一法人客户，经有关部门批准正式使用的全称，与公章所使用的名称完全一致。视同单一法人客户填报的分公司，填报分公司全称，与分公司公章所使用的名称完全一致。客户是境内涉密机构的，客户名称填报为“*********”。 （3）同业客户，经有关部门批准正式使用的客户全称，与客户公章所使用的名称完全一致。 （4）自然人，与有效证件上的姓名一致。 （5）境外客户，客户名称填报英文名称。 | L83: =INDEX(数据元说明!A:F,MATCH(I83,数据元说明!C:C,0),6) -> C..450 | M83: 对个人股东，为股东姓名；对法人股东及关联法人，为经有关部门批准正式使用的客户全称，与客户公章所使用的名称完全一致。非股东的关联自然人名称为隐私，银行机构需做变形，变形规则见《采集技术接口说明》。 | N83: 修改 | O83: 格式
C84: GDJGLFXXB | D84: 股东及关联方信息表 | E84: 106 | F84: 股东或关联方类型 | G84: 10606 | H84: GDHGLFLX | I84: 股东或关联方类别 | J84: =INDEX(数据元说明!A:F,MATCH(I84,数据元说明!C:C,0),2) -> 002027 | K84: =INDEX(数据元说明!A:F,MATCH(I84,数据元说明!C:C,0),5) -> 自然人（中国公民），自然人（非中国公民），境内非金融机构、境内银行业金融机构、境内非银行金融机构、境外银行，金融产品，纯国有企业，国有控股企业，国有参股企业，民营企业，政府机关，事业单位，社会团体，中外合资企业、外商独资企业、境外机构，其他-银行自定义。无法以枚举类型填报的，以“其他-XX”填报，其中“XX”为银行自定义类型 | L84: =INDEX(数据元说明!A:F,MATCH(I84,数据元说明!C:C,0),6) -> C..60 | N84: 新增
C85: GDJGLFXXB | D85: 股东及关联方信息表 | E85: 106 | F85: 股东或关联方证件类别 | G85: 10607 | H85: GDHGLFZJLB | I85: 证件类别 | J85: =INDEX(数据元说明!A:F,MATCH(I85,数据元说明!C:C,0),2) -> 002002 | K85: =INDEX(数据元说明!A:F,MATCH(I85,数据元说明!C:C,0),5) -> 同业客户：银行机构代码，金融许可证号，SWIFT编码，其他-XX。 对公客户：统一社会信用代码，组织机构代码，营业执照（工商注册号），公司注册证书，全球法人识别码，其他-XX。 个人客户：居民身份证，军官证，文职干部证，警官证，士兵证，户口簿，临时身份证，其他有效通行旅行证件，护照，学生证，无证件，其他-XX。 无法以枚举类型填报的，以“其他-XX”报送，其中“XX”为银行自定义类型。 对公客户优先填报统一社会信用代码，没有统一社会信用代码的对公客户填报组织机构代码。组织机构代码、统一社会信用代码均没有的可以填报客户提供的批文文号、开户主证件、上级机构统一社会信用代码等，以“其他-XX”填报。 | L85: =INDEX(数据元说明!A:F,MATCH(I85,数据元说明!C:C,0),6) -> C..60 | M85: 不可为空。如未收集证件号码，可以填写为其他任意能识别该股东的编号,如“其他-客户编号”。 | N85: 修改 | O85: 数据元说明
C86: GDJGLFXXB | D86: 股东及关联方信息表 | E86: 106 | F86: 股东或关联方证件号码 | G86: 10608 | H86: GDHGLFZJHM | I86: 证件号码 | J86: =INDEX(数据元说明!A:F,MATCH(I86,数据元说明!C:C,0),2) -> 002003 | K86: =INDEX(数据元说明!A:F,MATCH(I86,数据元说明!C:C,0),5) -> 与证件类别对应的证件号码。涉及个人身份证件时需按照本规范给定规则进行脱敏处理。 | L86: =INDEX(数据元说明!A:F,MATCH(I86,数据元说明!C:C,0),6) -> C..70 | M86: 如包含个人身份证件号码，则为隐私，银行机构需做变形，变形规则见《采集技术接口说明》。 | N86: 修改 | O86: 格式
C87: GDJGLFXXB | D87: 股东及关联方信息表 | E87: 106 | F87: 股东或关联方所属行业 | G87: 10609 | H87: SSHY | I87: 所属行业 | J87: =INDEX(数据元说明!A:F,MATCH(I87,数据元说明!C:C,0),2) -> 002014 | K87: =INDEX(数据元说明!A:F,MATCH(I87,数据元说明!C:C,0),5) -> 行业分类按《GB/T 4754 国民经济行业分类》执行。填报至该客户所属行业的小类代码，如：所属行业为“稻谷种植”填报“A0111”。境外机构按“境外”填报。 | L87: =INDEX(数据元说明!A:F,MATCH(I87,数据元说明!C:C,0),6) -> C..90 | M87: 股东或关联方主营业务所属的行业 | N87: 新增
C88: GDJGLFXXB | D88: 股东及关联方信息表 | E88: 106 | F88: 股东或关联方注册地 | G88: 10610 | H88: ZCD | I88: 地址 | J88: =INDEX(数据元说明!A:F,MATCH(I88,数据元说明!C:C,0),2) -> 001008 | K88: =INDEX(数据元说明!A:F,MATCH(I88,数据元说明!C:C,0),5) -> 中文描述。个人填报个人住址。机构填报有关部门批准的有效证件上登记的地址。参照《企业法人营业执照》中的注册地填报，要写明省（区、市）、地（区、市、州、盟）、县（区、市、旗）。境内涉密机构不填报。客户为境外企业的，填报客户在境外的注册地址（英文）。 | L88: =INDEX(数据元说明!A:F,MATCH(I88,数据元说明!C:C,0),6) -> C..600 | M88: 主要股东不得为空。 | N88: 新增
C89: GDJGLFXXB | D89: 股东及关联方信息表 | E89: 106 | F89: 关系类型 | G89: 10611 | H89: GXLX | I89: 股东或关联方关系类型 | J89: =INDEX(数据元说明!A:F,MATCH(I89,数据元说明!C:C,0),2) -> 002019 | K89: =INDEX(数据元说明!A:F,MATCH(I89,数据元说明!C:C,0),5) -> 枚举类型（代码）： 1-股东； 2-银行机构的自然人控股股东、实际控制人，及其一致行动人、最终受益人； 3-持有或控制银行机构5%以上股权的，或持股不足5%但对银行机构经营管理有重大影响的自然人； 4-银行机构的董事、监事、总行和重要分行的高级管理人员，以及具有大额授信、资产转移等核心业务审批或决策权的人员； 5-第2至4项所列关联方的配偶、父母、成年子女及兄弟姐妹； 6-第7、8项所列关联方的董事、监事、高级管理人员； 7-银行机构的法人控股股东、实际控制人，及其一致行动人、最终受益人； 8-持有或控制银行机构5%以上股权的，或者持股不足5%但对银行机构经营管理有重大影响的法人或非法人组织，及其控股股东、实际控制人、一致行动人、最终受益人； 9-第7项所列关联方控制或施加重大影响的法人或非法人组织，第8项所列关联方控制的法人或非法人组织； 10-银行机构控制或施加重大影响的法人或非法人组织； 11-第2项所列关联方控制或施加重大影响的法人或非法人组织，第3至第5项所列关联方控制的法人或非法人组织； 12-银行机构认定的其他自然人、法人或非法人组织； 13-银保监会或其派出机构认定可能导致银行机构利益转移的自然人、法人或非法人组织。 如关系类型为“股东”，则填报“1”。无法以枚举类型填报的，以“其他-XX”填报，其中“XX”为银行自定义类型。 | L89: =INDEX(数据元说明!A:F,MATCH(I89,数据元说明!C:C,0),6) -> C..300 | M89: 股东：上市银行持有或控制1%以上、5%以下股份或表决权的股东；非上市银行为持有或控制5%以下股份的所有股东。 控制：包括直接控制、间接控制，是指有权决定一个企业的财务和经营决策，并能据以从该企业的经营活动中获取利益。 持有：包括直接持有与间接持有。 重大影响：是指对法人或组织的财务和经营政策有参与决策的权力，但不能够控制或者与其他方共同控制这些政策的制定。包括但不限于派驻董事、监事或高级管理人员、通过协议或其他方式影响法人或组织的财务和经营管理决策，以及银保监会或其派出机构认定的其他情形。 控股股东：是指持股比例达到50%以上的股东；或持股比例虽不足50%，但依享有的表决权已足以对股东（大）会的决议产生控制性影响的股东。 实际控制人：是指虽不是公司的股东，但通过投资关系、协议或者其他安排，能够实际支配公司行为的自然人或其他最终控制人。 一致行动人：是指通过协议、合作或其他途径，在行使表决权或参与其他经济活动时采取相同意思表示的自然人、法人或非法人组织。 最终受益人：是指实际享有银行保险机构股权收益、金融产品收益的人。 “以上”含本数，“以下”不含本数。未尽事宜参照《银行保险机构关联交易管理办法》（中国银行保险监督管理委员会令〔2022〕1号）填报。 | N89: 新增
C90: GDJGLFXXB | D90: 股东及关联方信息表 | E90: 106 | F90: 实际控制人 | G90: 10612 | H90: SJKZR | I90: 名称 | J90: =INDEX(数据元说明!A:F,MATCH(I90,数据元说明!C:C,0),2) -> 001001 | K90: =INDEX(数据元说明!A:F,MATCH(I90,数据元说明!C:C,0),5) -> 名称应与公章所使用的名称完全一致。银行机构以银保监会金融机构许可证登记名称为准。无独立金融机构许可证的机构，可在本名称中体现出机构特征。第三方支付平台填报第三方支付平台名称。 客户名称按照客户的不同类型按如下标准填报。 （1）集团客户，填报银行对该集团授信采用的集团客户名称。视同集团客户填报的供应链融资填报核心企业客户名称。 （2）单一法人客户，经有关部门批准正式使用的全称，与公章所使用的名称完全一致。视同单一法人客户填报的分公司，填报分公司全称，与分公司公章所使用的名称完全一致。客户是境内涉密机构的，客户名称填报为“*********”。 （3）同业客户，经有关部门批准正式使用的客户全称，与客户公章所使用的名称完全一致。 （4）自然人，与有效证件上的姓名一致。 （5）境外客户，客户名称填报英文名称。 | L90: =INDEX(数据元说明!A:F,MATCH(I90,数据元说明!C:C,0),6) -> C..450 | M90: 应按照穿透原则填报股东的最终实际控制人，公有制企业的应填报至最终出资人，如XX国资委；非公有制企业应填报至出资自然人名称；外资企业应填报境外出资人名称。实控人为多人以英文半角分号隔开。无实控人的，填报“无”。非隐私，不做变形。 | N90: 新增
C91: GDJGLFXXB | D91: 股东及关联方信息表 | E91: 106 | F91: 参股商业银行的数量 | G91: 10613 | H91: CGSYYHSL | I91: 数量 | J91: =INDEX(数据元说明!A:F,MATCH(I91,数据元说明!C:C,0),2) -> 001029 | K91: =INDEX(数据元说明!A:F,MATCH(I91,数据元说明!C:C,0),5) -> 数量。 | L91: =INDEX(数据元说明!A:F,MATCH(I91,数据元说明!C:C,0),6) -> D20 | M91: 同一股东及其关联方、一致行动人作为主要股东参股商业银行的数量 | N91: 新增
C92: GDJGLFXXB | D92: 股东及关联方信息表 | E92: 106 | F92: 控股商业银行的数量 | G92: 10614 | H92: KGSL | I92: 数量 | J92: =INDEX(数据元说明!A:F,MATCH(I92,数据元说明!C:C,0),2) -> 001029 | K92: =INDEX(数据元说明!A:F,MATCH(I92,数据元说明!C:C,0),5) -> 数量。 | L92: =INDEX(数据元说明!A:F,MATCH(I92,数据元说明!C:C,0),6) -> D20 | M92: 同一股东及其关联方、一致行动人作为主要股东控股商业银行的数量 | N92: 新增
C93: GDJGLFXXB | D93: 股东及关联方信息表 | E93: 106 | F93: 不良信息 | G93: 10615 | H93: BLXX | I93: 不良信息 | J93: =INDEX(数据元说明!A:F,MATCH(I93,数据元说明!C:C,0),2) -> 002020 | K93: =INDEX(数据元说明!A:F,MATCH(I93,数据元说明!C:C,0),5) -> 枚举类型（代码）： 1-被列为相关部门失信联合惩戒对象； 2-存在严重逃废银行债务行为； 3-提供虚假材料或者作不实声明； 4-对商业银行经营失败或重大违法违规行为负有重大责任； 5-拒绝或阻碍银监会或其派出机构依法实施监管； 6-因违法违规行为被金融监管部门或政府有关部门查处，造成恶劣影响； 7-其他可能对商业银行经营管理产生不利影响的情形。 如被列为相关部门失信联合惩戒对象，填报“1”。不存在上述情况不填报。 | L93: =INDEX(数据元说明!A:F,MATCH(I93,数据元说明!C:C,0),6) -> C..300 | N93: 新增
C94: GDJGLFXXB | D94: 股东及关联方信息表 | E94: 106 | F94: 是否限权 | G94: 10616 | H94: SFXQ | I94: 是否标志 | J94: =INDEX(数据元说明!A:F,MATCH(I94,数据元说明!C:C,0),2) -> 001002 | K94: =INDEX(数据元说明!A:F,MATCH(I94,数据元说明!C:C,0),5) -> 是，否。 | L94: =INDEX(数据元说明!A:F,MATCH(I94,数据元说明!C:C,0),6) -> C3 | M94: 是否存在限制股东参与经营管理的相关权利，包括股东大会召开请求权、表决权、提名权、提案权、处分权等 | N94: 新增
C95: GDJGLFXXB | D95: 股东及关联方信息表 | E95: 106 | F95: 入股资金来源 | G95: 10617 | H95: RGZJLY | I95: 入股资金来源 | J95: =INDEX(数据元说明!A:F,MATCH(I95,数据元说明!C:C,0),2) -> 002021 | K95: =INDEX(数据元说明!A:F,MATCH(I95,数据元说明!C:C,0),5) -> 自有资金、委托资金、债务资金、其他-银行自定义 | L95: =INDEX(数据元说明!A:F,MATCH(I95,数据元说明!C:C,0),6) -> C..60 | N95: 新增
C96: GDJGLFXXB | D96: 股东及关联方信息表 | E96: 106 | F96: 入股资金账号 | G96: 10618 | H96: RGZJZH | I96: 账号 | J96: =INDEX(数据元说明!A:F,MATCH(I96,数据元说明!C:C,0),2) -> 003001 | K96: =INDEX(数据元说明!A:F,MATCH(I96,数据元说明!C:C,0),5) -> 系统内最细一级的账号，无唯一性约束，不需要和序号、子序号等做拼接。 | L96: =INDEX(数据元说明!A:F,MATCH(I96,数据元说明!C:C,0),6) -> C..60 | M96: 需填写入股时在本行开立的验资户账户号。二级市场买入可为空。多个账号用英文半角分号隔开。 | N96: 新增
C97: GDJGLFXXB | D97: 股东及关联方信息表 | E97: 106 | F97: 持股数量 | G97: 10619 | H97: CGSL | I97: 数量 | J97: =INDEX(数据元说明!A:F,MATCH(I97,数据元说明!C:C,0),2) -> 001029 | K97: =INDEX(数据元说明!A:F,MATCH(I97,数据元说明!C:C,0),5) -> 数量。 | L97: =INDEX(数据元说明!A:F,MATCH(I97,数据元说明!C:C,0),6) -> D20 | M97: 股东持有银行股数，以股为单位。填报机构为非股份法人的可以为空。 | N97: 新增
C98: GDJGLFXXB | D98: 股东及关联方信息表 | E98: 106 | F98: 持股比例 | G98: 10620 | H98: CGBL | I98: 比例（精） | J98: =INDEX(数据元说明!A:F,MATCH(I98,数据元说明!C:C,0),2) -> 001004 | K98: =INDEX(数据元说明!A:F,MATCH(I98,数据元说明!C:C,0),5) -> 百分比为单位，即1/100，保留六位小数。4.123456%则填报为4.123456。 | L98: =INDEX(数据元说明!A:F,MATCH(I98,数据元说明!C:C,0),6) -> D20.6 | N98: 修改 | O98: 数据元
C99: GDJGLFXXB | D99: 股东及关联方信息表 | E99: 106 | F99: 入股日期 | G99: 10621 | H99: RGRQ | I99: 日期 | J99: =INDEX(数据元说明!A:F,MATCH(I99,数据元说明!C:C,0),2) -> 001005 | K99: =INDEX(数据元说明!A:F,MATCH(I99,数据元说明!C:C,0),5) -> YYYYMMDD，默认值99991231。 | L99: =INDEX(数据元说明!A:F,MATCH(I99,数据元说明!C:C,0),6) -> C8 | M99: 最近一次持股份额由0变为非0的日期。 | N99: 修改 | O99: 数据项名称、数据项代码
C100: GDJGLFXXB | D100: 股东及关联方信息表 | E100: 106 | F100: 质押比例 | G100: 10622 | H100: ZYBL | I100: 比例（精） | J100: =INDEX(数据元说明!A:F,MATCH(I100,数据元说明!C:C,0),2) -> 001004 | K100: =INDEX(数据元说明!A:F,MATCH(I100,数据元说明!C:C,0),5) -> 百分比为单位，即1/100，保留六位小数。4.123456%则填报为4.123456。 | L100: =INDEX(数据元说明!A:F,MATCH(I100,数据元说明!C:C,0),6) -> D20.6 | M100: 填报该股东截至报送日持有的本行股权用于质押的比例。未质押股权的填0，未采集质押比例的填报为空。 | N100: 新增
C101: GDJGLFXXB | D101: 股东及关联方信息表 | E101: 106 | F101: 是否驻派董监事 | G101: 10623 | H101: SFZPDJS | I101: 是否标志 | J101: =INDEX(数据元说明!A:F,MATCH(I101,数据元说明!C:C,0),2) -> 001002 | K101: =INDEX(数据元说明!A:F,MATCH(I101,数据元说明!C:C,0),5) -> 是，否。 | L101: =INDEX(数据元说明!A:F,MATCH(I101,数据元说明!C:C,0),6) -> C3 | M101: 该股东是否向本行派驻董事、监事。 | N101: 新增
C102: GDJGLFXXB | D102: 股东及关联方信息表 | E102: 106 | F102: 股东或关联方状态 | G102: 10624 | H102: GDHGLFZT | I102: 有效状态 | J102: =INDEX(数据元说明!A:F,MATCH(I102,数据元说明!C:C,0),2) -> 007008 | K102: =INDEX(数据元说明!A:F,MATCH(I102,数据元说明!C:C,0),5) -> 有效，无效。 | L102: =INDEX(数据元说明!A:F,MATCH(I102,数据元说明!C:C,0),6) -> C6 | M102: 表示一条记录是否已经无效。默认为有效，当需要删除一条股东信息时，更新为无效。 | N102: 修改 | O102: 数据元说明
C103: GDJGLFXXB | D103: 股东及关联方信息表 | E103: 106 | F103: 最近一次变动日期 | G103: 10625 | H103: ZJYCBDRQ | I103: 日期 | J103: =INDEX(数据元说明!A:F,MATCH(I103,数据元说明!C:C,0),2) -> 001005 | K103: =INDEX(数据元说明!A:F,MATCH(I103,数据元说明!C:C,0),5) -> YYYYMMDD，默认值99991231。 | L103: =INDEX(数据元说明!A:F,MATCH(I103,数据元说明!C:C,0),6) -> C8 | M103: 报送最近一次入股、增资扩股或股权转让等影响持股比例的日期。 | N103: 新增
...

Sheet 自营报送范围
A1: 自营资金业务报送范围
A3: 业务大类 | B3: 业务中类 | C3: 业务小类
A4: 同业往来 | B4: 买入返售 | C4: 买入返售证券
C5: 买入返售债权
C6: 买入返售信贷资产
C7: 其他-银行自定义
B8: 卖出回购 | C8: 卖出回购证券
C9: 卖出回购债权
C10: 卖出回购信贷资产
C11: 其他-银行自定义
B12: 拆入 | C12: 拆入银行金融机构
C13: 拆入非银行金融机构
B14: 拆出 | C14: 拆出银行金融机构
C15: 拆出非银行金融机构
B16: 同业借款 | C16: 境内同业借款
C17: 境外同业借款
B18: 同业代付 | C18: 代理境内同业付款
C19: 代理境外同业付款
B20: 存放同业 | C20: 非结算性存放同业
B21: 同业存单 | C21: 同业存单发行
C22: 同业存单投资
B23: 债券发行 | C23: 商业银行债
C24: 银行次级债
C25: 银行永续债
C26: 其他-银行自定义
B27: 其他 | C27: 债券借贷
C28: 银行自定义
A29: 债券投资与同业投资 | B29: 债券投资 | C29: 国债
C30: 地方政府债
C31: 央票
C32: 政府支持机构债
C33: 政策性金融债
C34: 商业性金融债
C35: 非金融企业债券
C36: 资产支持证券（信贷资产证券化）
C37: 资产支持证券（交易所资产支持证券）
C38: 资产支持证券（资产支持票据）
C39: 外国债券
C40: 其他-银行自定义
B41: 权益类投资 | C41: 长期股权投资
C42: 上市股票
C43: 非上市股权
C44: 其他-银行自定义
B45: 公募基金投资 | C45: 债券基金
C46: 货币市场基金
C47: 股票基金
C48: 基金中基金
C49: 混合基金
C50: 其他-银行自定义
B51: 私募基金投资 | C51: 私募证券投资基金
C52: 私募股权投资基金
C53: 私募创业投资基金
C54: 其他-银行自定义
B55: 资产管理产品投资 | C55: 非保本理财投资
C56: 信托产品（资金信托）
C57: 信托产品（财产权信托）
C58: 证券业资产管理产品（不含公募基金）
C59: 保险业资产管理产品
C60: 其他-银行自定义
B61: 其他投资 | C61: 其他债权融资（其他交易平台债权融资工具）
C62: 其他债权融资（非标转标资产）
C63: 其他-银行自定义

Sheet 即期及衍生品交易信息表填报示例
A1: 示例交易背景 | B1: 填报机构2021年6月1日以6.36元人民币/美元的价格向某交易对手卖出6360元人民币。 | C1: 填报机构2021年12月14日在中国外汇交易中心以1.128美元/欧元的价格向某匿名交易对手卖出500欧元。 | D1: 填报机构2021年12月20日在洲际交易所以1797.4美元/盎司的价格向某交易对手卖出100盎司黄金。 | E1: 某交易对手2021年12月1日以1800美元/盎司的价格向填报机构卖出100盎司账户黄金。 | F1: 填报机构2021年12月14日以365.7元/克的价格向某交易对手卖出4克黄金（积存金）。 | G1: 某交易对手2021年12月14日从其在填报机构开立的黄金（积存金）账户提取100克黄金。 | H1: 某交易对手2021年12月20日以0.5%的利率向填报机构租借5000克黄金，2022年9月15日到期。 | I1: 某交易对手2021年3月29日以15165印尼卢比/美元的价格向填报机构买入本金为4549500印尼卢比的远期合约，2022年3月31日到期。 | J1: 为对冲交易（201）汇率风险，填报机构以15147卢比/美元的价格向其他交易对手买入本金为4544100卢比的远期合约。 | K1: 填报机构2021年12月7日以1857.347美元/盎司的价格向某交易对手购买0.81盎司钯金远期合约，2022年3月9日到期，差额结算。 | L1: 填报机构2021年4月16日以99.43元/张的价格买入20手3年期国开债标准债券远期合约。 | M1: 某交易对手2021年12月7日以19847美元/吨的价格向填报机构买入6吨镍远期合约，2022年3月7日到期。 | N1: 某交易对手2021年11月30日以467.83元人民币/桶的价格向填报机构购买1.8桶账户原油。 | O1: 某交易对手2021年12月24日与填报机构达成名义本金为500万元人民币的远期利率协议，2022年3月24日到期，填报机构收固定利率4.4%、付浮动利率SHIBOR3M。 | Q1: 填报机构2020年4月10日以102.835元/张的价格买入平仓1手五年期国债期货合约 | R1: 填报机构与某交易对手2021年5月25日达成欧元美元掉期交易，填报机构2021年5月27日收1222美元付1000欧元，2021年12月27日收1000欧元付1233美元。 | T1: 某交易对手2021年12月7日与填报机构达成美元白银掉期交易，填报机构2021年12月9日收6729美元、付300盎司白银，2022年1月10日收6729.537美元、付300盎司白银。 | V1: 交易（402）2021年12月15日估值为2812.5美元。 | X1: 填报机构与某交易对手2020年12月15日达成利率互换交易，到期日为2021年12月15日，名义本金均为1000元人民币，每季度最后一个月的15日交换利息，填报机构收浮动利率FR007+50BP、付固定利率2.63%。 | Z1: 填报机构2020年5月21日与某交易对手达成交叉货币互换交易，2020年5月21日填报机构收1000美元本金、付6500元人民币本金，每年3月21日和9月21日互换利息，填报机构付美元固定利率6%、收人民币浮动利率SHIBOR3M+10BP，2022年3月21日完成最后一次利息交换以及本金交换。 | AB1: 某交易对手2019年10月23日以250BP的价格向填报机构买入名义本金为1亿元人民币的某信用风险缓释凭证。 | AC1: 填报机构2019年12月13日以1BP的价格向某交易对手卖出名义本金为1000万元人民币的某公司信用违约互换。 | AD1: 填报机构2021年11月5日向某交易对手买入美元对人民币欧式看涨期权，本金为1000美元，约定汇率为6.59人民币/美元，期权费为20元人民币，2021年11月26日到期。 | AE1: 某交易对手2021年10月15日向填报机构购买名义本金为8000欧元、挂钩EURIBOR3M的利率下限期权，期权费为0，2024年10月29日到期，2021年11月24日起每季度交割，某交易对手有权要求填报机构支付EURIBOR3M小于0的部分。 | AF1: 填报银行2021年3月29日以1BP的价格向某交易对手购买名义本金为1千万元、挂钩FDR001的利率上限期权，按季度交割，填报银行有权要求某交易对手支付FDR001超过1.5%的部分。 | AG1: 某交易对手2021年12月24日以10500元人民币的价格向填报机构买入挂钩LPR1Y、名义本金500万元、上限为4.05%的利率期权，同时以10000元人民币的价格向填报机构卖出挂钩LPR1Y、名义本金500万元、下限为3.8%的利率期权，按季度重置和支付，2022年12月24日到期。 | AI1: 某交易对手2019年4月5日向填报机构买入2200万磅棉花欧式看涨期权，期权费0.017美元/磅，行权日2019年6月21日，行权价格0.81美元/磅。 | AJ1: 交易（505）2019年5月31日估值为370000美元。 | AK1: 某交易对手2021年12月15日向填报机构购买10盎司黄金欧式看跌期权，2022年3月14日到期，期权费为350美元，约定单价为1650美元/盎司。 | AL1: 填报机构2021年12月15日向某交易对手购买名义本金为100美元的二元期权，行权日为2022年3月14日，期权费45美元，行权条件为欧元兑美元汇率大于等于1.135。 | AM1: 某交易对手2021年12月15日向填报机构购买名义本金为150美元的二元期权，期权费78美元，行权条件为2022年3月14日前欧元兑美元汇率小于等于1.15。 | AN1: 填报机构2021年12月15日向某交易对手购买名义本金为500元人民币的二元期权，期权费300元人民币，行权条件为2022年3月14日前欧元兑美元汇率在(1.105,1.16)区间内。 | AO1: 填报机构2021年11月30日在上海黄金交易所以368.66元/克的价格买入9000克AU(T+D)合约。 | AP1: 填报机构2012年6月12日向某交易对手买入利率掉期期权，期权费为200美元，填报机构在期权到期日（2012年9月12日）决定是否进行一笔名义本金为200000美元的利率互换：填报机构付浮动利率USD 3M LIBOR+2%、收固定利率3%。
A2: 金融许可证号 | B2: XXX | C2: XXX | D2: XXX | E2: XXX | F2: XXX | G2: XXX | H2: XXX | I2: XXX | J2: XXX | K2: XXX | L2: XXX | M2: XXX | N2: XXX | O2: XXX | P2: XXX | Q2: XXX | R2: XXX | S2: XXX | T2: XXX | U2: XXX | V2: XXX | W2: XXX | X2: XXX | Y2: XXX | Z2: XXX | AA2: XXX | AB2: XXX | AC2: XXX | AD2: XXX | AE2: XXX | AF2: XXX | AG2: XXX | AH2: XXX | AI2: XXX | AJ2: XXX | AK2: XXX | AL2: XXX | AM2: XXX | AN2: XXX | AO2: XXX | AP2: XXX | AQ2: XXX | AR2: XXX
A3: 内部机构号 | B3: XXX | C3: XXX | D3: XXX | E3: XXX | F3: XXX | G3: XXX | H3: XXX | I3: XXX | J3: XXX | K3: XXX | L3: XXX | M3: XXX | N3: XXX | O3: XXX | P3: XXX | Q3: XXX | R3: XXX | S3: XXX | T3: XXX | U3: XXX | V3: XXX | W3: XXX | X3: XXX | Y3: XXX | Z3: XXX | AA3: XXX | AB3: XXX | AC3: XXX | AD3: XXX | AE3: XXX | AF3: XXX | AG3: XXX | AH3: XXX | AI3: XXX | AJ3: XXX | AK3: XXX | AL3: XXX | AM3: XXX | AN3: XXX | AO3: XXX | AP3: XXX | AQ3: XXX | AR3: XXX
A4: 银行机构名称 | B4: XXX | C4: XXX | D4: XXX | E4: XXX | F4: XXX | G4: XXX | H4: XXX | I4: XXX | J4: XXX | K4: XXX | L4: XXX | M4: XXX | N4: XXX | O4: XXX | P4: XXX | Q4: XXX | R4: XXX | S4: XXX | T4: XXX | U4: XXX | V4: XXX | W4: XXX | X4: XXX | Y4: XXX | Z4: XXX | AA4: XXX | AB4: XXX | AC4: XXX | AD4: XXX | AE4: XXX | AF4: XXX | AG4: XXX | AH4: XXX | AI4: XXX | AJ4: XXX | AK4: XXX | AL4: XXX | AM4: XXX | AN4: XXX | AO4: XXX | AP4: XXX | AQ4: XXX | AR4: XXX
A5: 交易编号 | B5: 101 | C5: 102 | D5: 103 | E5: 104 | F5: 105 | G5: 106 | H5: 107 | I5: 201 | J5: 202 | K5: 203 | L5: 204 | M5: 205 | N5: 206 | O5: 207 | P5: 207 | Q5: 301 | R5: 401 | S5: 401 | T5: 402 | U5: 402 | V5: 402 | W5: 402 | X5: 403 | Y5: 403 | Z5: 404 | AA5: 404 | AB5: 405 | AC5: 406 | AD5: 501 | AE5: 502 | AF5: 503 | AG5: 504 | AH5: 504 | AI5: 505 | AJ5: 505 | AK5: 506 | AL5: 507 | AM5: 508 | AN5: 509 | AO5: 601 | AP5: 701 | AQ5: 701 | AR5: 701
A6: 业务品种 | B6: 即期结售汇 | C6: 即期外汇买卖 | D6: 即期贵金属 | E6: 双向账户贵金属 | F6: 贵金属积存金 | G6: 贵金属积存金提取 | H6: 贵金属租借 | I6: 远期外汇 | J6: 远期外汇 | K6: 远期贵金属 | L6: 标准债券远期 | M6: 商品远期 | N6: 远期账户商品 | O6: 远期利率协议 | Q6: 国债期货 | R6: 外汇掉期 | T6: 贵金属掉期 | V6: 贵金属掉期（估值） | X6: 利率互换 | Z6: 交叉货币互换 | AB6: 信用风险缓释凭证 | AC6: 信用违约互换 | AD6: 外汇期权 | AE6: 利率下限期权 | AF6: 利率上限期权 | AG6: 领式期权 | AI6: 商品期权 | AJ6: 商品期权（估值） | AK6: 贵金属期权 | AL6: 二元期权（digital） | AM6: 二元期权（one touch） | AN6: 二元期权(double no touch) | AO6: AU(T+D) | AP6: 利率掉期期权
A7: 基础资产类型 | B7: 汇率 | C7: 汇率 | D7: 贵金属 | E7: 贵金属 | F7: 贵金属 | G7: 贵金属 | H7: 贵金属 | I7: 汇率 | J7: 汇率 | K7: 贵金属 | L7: 利率 | M7: 商品 | N7: 商品 | O7: 利率 | P7: 利率 | Q7: 利率 | R7: 汇率 | S7: 汇率 | T7: 贵金属 | U7: 贵金属 | V7: 贵金属 | W7: 贵金属 | X7: 利率 | Y7: 利率 | Z7: 利率 | AA7: 利率 | AB7: 信用 | AC7: 信用 | AD7: 汇率 | AE7: 利率 | AF7: 利率 | AG7: 利率 | AH7: 利率 | AI7: 商品 | AJ7: 商品 | AK7: 贵金属 | AL7: 汇率 | AM7: 汇率 | AN7: 汇率 | AO7: 贵金属 | AP7: 利率 | AQ7: 利率 | AR7: 利率
A8: 基础资产名称 | B8: USDCNY | C8: EURUSD | D8: XAU | E8: XAU | F8: 黄金 | G8: 黄金 | H8: 黄金 | I8: USDIDR | J8: USDIDR | K8: XPD | L8: 3年期虚拟国开债 | M8: 镍 | N8: 原油 | O8: 固定利率 | P8: SHIBOR3M | Q8: 5年期虚拟国债 | R8: USD | S8: EUR | T8: USD | U8: XAG | V8: USD | W8: XAG | X8: 固定利率 | Y8: FR007 | Z8: 固定利率 | AA8: SHIBOR3M | AB8: 某信用风险缓释凭证 | AC8: 某公司信用事件 | AD8: USDCNY | AE8: EURIBOR3M | AF8: FDR001 | AG8: LPR1Y | AH8: LPR1Y | AI8: 棉花 | AJ8: 棉花 | AK8: XAUUSD | AL8: EURUSD | AM8: EURUSD | AN8: EURUSD | AO8: 黄金 | AP8: USD 3M LIBOR | AQ8: USD 3M LIBOR | AR8: 固定利率
A9: 交易类型 | B9: 代客 | C9: 做市 | D9: 自营 | E9: 代客 | F9: 自营 | G9: 自营 | H9: 自营 | I9: 代客 | J9: 代客平盘 | K9: 代客 | L9: 做市 | M9: 代客 | N9: 代客 | O9: 代客 | P9: 代客 | Q9: 做市 | R9: 自营 | S9: 自营 | T9: 代客 | U9: 代客 | V9: 代客 | W9: 代客 | X9: 自营 | Y9: 自营 | Z9: 自营 | AA9: 自营 | AB9: 自营 | AC9: 做市 | AD9: 自营 | AE9: 套期保值 | AF9: 做市 | AG9: 代客 | AH9: 代客 | AI9: 做市 | AJ9: 做市 | AK9: 代客 | AL9: 做市 | AM9: 做市 | AN9: 代客 | AO9: 自营 | AP9: 做市 | AQ9: 做市 | AR9: 做市
A10: 合约种类 | B10: 即期 | C10: 即期 | D10: 即期 | E10: 即期 | F10: 即期 | G10: 即期 | H10: 即期 | I10: 远期 | J10: 远期 | K10: 远期 | L10: 远期 | M10: 远期 | N10: 远期 | O10: 远期 | P10: 远期 | Q10: 期货 | R10: 掉期 | S10: 掉期 | T10: 掉期 | U10: 掉期 | V10: 掉期 | W10: 掉期 | X10: 互换 | Y10: 互换 | Z10: 互换 | AA10: 互换 | AB10: 互换 | AC10: 互换 | AD10: 期权 | AE10: 期权 | AF10: 期权 | AG10: 期权 | AH10: 期权 | AI10: 期权 | AJ10: 期权 | AK10: 期权 | AL10: 期权 | AM10: 期权 | AN10: 期权 | AO10: 延期交收 | AP10: 期权 | AQ10: 互换 | AR10: 互换
A11: 交易状态 | B11: 新增 | C11: 新增 | D11: 新增 | E11: 新增 | F11: 新增 | G11: 新增 | H11: 新增 | I11: 新增 | J11: 新增 | K11: 新增 | L11: 新增 | M11: 新增 | N11: 新增 | O11: 新增 | P11: 新增 | Q11: 新增 | R11: 新增 | S11: 新增 | T11: 新增 | U11: 新增 | V11: 估值 | W11: 估值 | X11: 新增 | Y11: 新增 | Z11: 新增 | AA11: 新增 | AB11: 新增 | AC11: 新增 | AD11: 新增 | AE11: 新增 | AF11: 新增 | AG11: 新增 | AH11: 新增 | AI11: 新增 | AJ11: 估值 | AK11: 新增 | AL11: 新增 | AM11: 新增 | AN11: 新增 | AO11: 新增 | AP11: 新增 | AQ11: 新增 | AR11: 新增
A12: 买方名称 | B12: 某交易对手 | D12: 某交易对手 | E12: 填报机构 | F12: 某交易对手 | G12: 某交易对手 | H12: 某交易对手 | I12: 某交易对手 | J12: 填报机构 | K12: 填报机构 | L12: 填报机构 | M12: 某交易对手 | N12: 某交易对手 | O12: 某交易对手 | P12: 填报机构 | Q12: 填报机构 | R12: 某交易对手 | S12: 某交易对手 | T12: 某交易对手 | U12: 某交易对手 | V12: 某交易对手 | W12: 某交易对手 | X12: 填报机构 | Y12: 某交易对手 | Z12: 填报机构 | AA12: 某交易对手 | AB12: 某交易对手 | AC12: 某交易对手 | AD12: 填报机构 | AE12: 某交易对手 | AF12: 填报银行 | AG12: 某交易对手 | AH12: 填报银行 | AI12: 某交易对手 | AJ12: 某交易对手 | AK12: 某交易对手 | AL12: 填报机构 | AM12: 填报机构 | AN12: 某交易对手 | AO12: 填报机构 | AP12: 填报机构 | AQ12: 填报机构 | AR12: 某交易对手
A13: 买方客户统一编号 | B13: XXX | D13: XXX | E13: XXX | F13: XXX | G13: XXX | H13: XXX | I13: XXX | J13: XXX | K13: XXX | L13: XXX | M13: XXX | N13: XXX | O13: XXX | P13: XXX | Q13: XXX | R13: XXX | S13: XXX | T13: XXX | U13: XXX | V13: XXX | W13: XXX | X13: XXX | Y13: XXX | Z13: XXX | AA13: XXX | AB13: XXX | AC13: XXX | AD13: XXX | AE13: XXX | AF13: XXX | AG13: XXX | AH13: XXX | AI13: XXX | AJ13: XXX | AK13: XXX | AL13: XXX | AM13: XXX | AN13: XXX | AO13: XXX | AP13: XXX | AQ13: XXX | AR13: XXX
A14: 卖方名称 | B14: 填报机构 | C14: 填报机构 | D14: 填报机构 | E14: 某交易对手 | F14: 填报机构 | G14: 填报机构 | H14: 填报机构 | I14: 填报机构 | J14: 某交易对手 | K14: 某交易对手 | M14: 填报机构 | N14: 填报机构 | O14: 填报机构 | P14: 某交易对手 | R14: 填报机构 | S14: 填报机构 | T14: 填报机构 | U14: 填报机构 | V14: 填报机构 | W14: 填报机构 | X14: 某交易对手 | Y14: 填报机构 | Z14: 某交易对手 | AA14: 填报机构 | AB14: 填报机构 | AC14: 填报机构 | AD14: 某交易对手 | AE14: 填报机构 | AF14: 某交易对手 | AG14: 填报机构 | AH14: 某交易对手 | AI14: 填报银行 | AJ14: 填报银行 | AK14: 填报机构 | AL14: 某交易对手 | AM14: 某交易对手 | AN14: 填报机构 | AP14: 某交易对手 | AQ14: 某交易对手 | AR14: 填报机构
A15: 卖方客户统一编号 | B15: XXX | C15: XXX | D15: XXX | E15: XXX | F15: XXX | G15: XXX | H15: XXX | I15: XXX | J15: XXX | K15: XXX | M15: XXX | N15: XXX | O15: XXX | P15: XXX | R15: XXX | S15: XXX | T15: XXX | U15: XXX | V15: XXX | W15: XXX | X15: XXX | Y15: XXX | Z15: XXX | AA15: XXX | AB15: XXX | AC15: XXX | AD15: XXX | AE15: XXX | AF15: XXX | AG15: XXX | AH15: XXX | AI15: XXX | AJ15: XXX | AK15: XXX | AL15: XXX | AM15: XXX | AN15: XXX | AP15: XXX | AQ15: XXX | AR15: XXX
A16: 交易日期 | B16: 20210601 | C16: 20211214 | D16: 20211220 | E16: 20211201 | F16: 20211214 | G16: 20211214 | H16: 20211220 | I16: 20210329 | J16: 20210329 | K16: 20211207 | L16: 20210416 | M16: 20211207 | N16: 20211130 | O16: 20211224 | P16: 20211224 | Q16: 20200410 | R16: 20210525 | S16: 20210525 | T16: 20211207 | U16: 20211207 | V16: 20211207 | W16: 20211207 | X16: 20201215 | Y16: 20201215 | Z16: 20200521 | AA16: 20200521 | AB16: 20191023 | AC16: 20191213 | AD16: 20211105 | AE16: 20211015 | AF16: 20210329 | AG16: 20211224 | AH16: 20211224 | AI16: 20190405 | AJ16: 20190405 | AK16: 20211215 | AL16: 20211215 | AM16: 20211215 | AN16: 20211215 | AO16: 20211130 | AP16: 20120612
A17: 交易时间 | B17: 000000 | C17: 000000 | D17: 000000 | E17: 000000 | F17: 000000 | G17: 000000 | H17: 000000 | I17: 000000 | J17: 000000 | K17: 000000 | M17: 000000 | N17: 000000 | O17: 000000 | P17: 000000 | R17: 000000 | S17: 000000 | T17: 000000 | U17: 000000 | V17: 000000 | W17: 000000 | X17: 000000 | Y17: 000000 | Z17: 000000 | AA17: 000000 | AB17: 000000 | AC17: 000000 | AD17: 000000 | AE17: 000000 | AF17: 000000 | AG17: 000000 | AH17: 000000 | AI17: 000000 | AJ17: 000000 | AK17: 000000 | AL17: 000000 | AM17: 000000 | AN17: 000000 | AO17: 000000 | AP17: 000000
A18: 起息日期 | B18: 20210603 | C18: 20211216 | D18: 20211222 | E18: 20211201 | F18: 20211214 | G18: 20211214 | H18: 20211220 | I18: 20220331 | J18: 20220331 | K18: 20220309 | M18: 20220307 | O18: 20220324 | P18: 20220324 | R18: 20210527 | S18: 20211227 | T18: 20211209 | U18: 20220110 | V18: 20211209 | W18: 20220110 | X18: 20201215 | Y18: 20201215 | Z18: 20200521 | AA18: 20200521 | AB18: 20191023 | AC18: 20191216 | AD18: 20211126 | AE18: 20211029 | AF18: 20210329 | AG18: 20220121 | AH18: 20220121 | AK18: 20211217 | AL18: 20211217 | AM18: 20211217 | AN18: 20211217 | AP18: 20120912 | AQ18: 20120612 | AR18: 20120612
A19: 到期日期 | B19: 20210603 | C19: 20211216 | D19: 20211222 | E19: 20211201 | F19: 20211214 | G19: 20211214 | H19: 20220915 | I19: 20220331 | J19: 20220331 | K19: 20220309 | L19: 202106 | M19: 20220307 | N19: 20211230 | O19: 20220324 | P19: 20220324 | Q19: 202009 | R19: 20210527 | S19: 20211227 | T19: 20211209 | U19: 20220110 | V19: 20211209 | W19: 20220110 | X19: 20201215 | Y19: 20201215 | Z19: 20200921 | AA19: 20200921 | AB19: 20221023 | AC19: 20191227 | AD19: 20211126 | AE19: 20211124 | AF19: 20210629 | AG19: 20220121 | AH19: 20220121 | AI19: 20190621 | AJ19: 20190621 | AK19: 20220314 | AL19: 20220314 | AM19: 20220314 | AN19: 20220314 | AP19: 20120912 | AQ19: 20121212 | AR19: 20121212
A20: 截止日期 | B20: 20210603 | C20: 20211216 | D20: 20211222 | E20: 20211201 | F20: 20211214 | G20: 20211214 | H20: 20220915 | I20: 20220331 | J20: 20220331 | K20: 20220309 | L20: 202106 | M20: 20220307 | N20: 20211230 | O20: 20220324 | P20: 20220324 | Q20: 202009 | R20: 20211227 | S20: 20211227 | T20: 20220110 | U20: 20220110 | V20: 20220110 | W20: 20220110 | X20: 20211215 | Y20: 20211215 | Z20: 20220321 | AA20: 20220321 | AB20: 20221023 | AC20: 20191227 | AD20: 20211126 | AE20: 20241029 | AF20: 20220629 | AG20: 20221224 | AH20: 20221224 | AI20: 20190621 | AJ20: 20190621 | AK20: 20220316 | AL20: 20220316 | AM20: 20220316 | AN20: 20220316 | AP20: 20120912 | AQ20: 20121212 | AR20: 20121212
A21: 交割频率 | X21: 3M | Y21: 3M | Z21: 6M | AA21: 6M | AE21: 3M | AF21: 3M | AG21: 3M | AH21: 3M
A22: 标的数量 | B22: 6360 | C22: 500 | D22: 100 | E22: 100 | F22: 4 | G22: 100 | H22: 5000 | I22: 300 | J22: 300 | K22: 0.81 | L22: 1000000 | M22: 6 | N22: 1.8 | O22: 5000000 | P22: 5000000 | Q22: 1000000 | R22: 1000 | S22: 1233 | T22: 300 | U22: 6729.537 | V22: 300 | W22: 6729.537 | X22: 1000 | Y22: 1000 | Z22: 1000 | AA22: 6500 | AB22: 100000000 | AC22: 10000000 | AD22: 6590 | AE22: 8000 | AF22: 10000000 | AG22: 5000000 | AH22: 5000000 | AI22: 22000000 | AJ22: 22000000 | AK22: 10 | AL22: 100 | AM22: 150 | AN22: 500 | AO22: 9000 | AP22: 200000 | AQ22: 200000 | AR22: 200000
A23: 标的数量单位 | B23: CNY | C23: EUR | D23: 盎司 | E23: 盎司 | F23: 克 | G23: 克 | H23: 克 | I23: USD | J23: USD | K23: 盎司 | L23: CNY | M23: 吨 | N23: 桶 | O23: CNY | P23: CNY | Q23: CNY | R23: EUR | S23: USD | T23: 盎司 | U23: USD | V23: 盎司 | W23: USD | X23: CNY | Y23: CNY | Z23: USD | AA23: CNY | AB23: CNY | AC23: CNY | AD23: CNY | AE23: EUR | AF23: CNY | AG23: CNY | AH23: CNY | AI23: 磅 | AJ23: 磅 | AK23: 盎司 | AL23: USD | AM23: USD | AN23: CNY | AO23: 克 | AP23: USD | AQ23: USD | AR23: USD
A24: 成交价格 | B24: 1000 | C24: 564 | D24: 179740 | E24: 180000 | F24: 1462.79 | G24: 100 | H24: 50 | I24: 4549500 | J24: 4544100 | K24: 1504.4511 | L24: 9943000 | M24: 119082 | N24: 842.094 | O24: 440 | P24: 0 | Q24: 1028350 | R24: 1222 | S24: 1000 | T24: 6729 | U24: 300 | V24: 6729 | W24: 300 | X24: 263 | Y24: 50 | Z24: 600 | AA24: 10 | AB24: 250 | AC24: 1 | AD24: 20 | AE24: 0 | AF24: 1000 | AG24: 10500 | AH24: 10000 | AI24: 374000 | AJ24: 374000 | AK24: 350 | AL24: 45 | AM24: 78 | AN24: 300 | AO24: 3317940 | AP24: 200 | AQ24: 200 | AR24: 300
A25: 成交价格单位 | B25: USD | C25: USD | D25: USD | E25: USD | F25: CNY | G25: 克 | H25: BP | I25: IDR | J25: IDR | K25: USD | L25: CNY | M25: USD | N25: CNY | O25: BP | P25: BP | Q25: CNY | R25: USD | S25: EUR | T25: USD | U25: 盎司 | V25: USD | W25: 盎司 | X25: BP | Y25: BP | Z25: BP | AA25: BP | AB25: BP | AC25: BP | AD25: CNY | AE25: EUR | AF25: CNY | AG25: CNY | AH25: CNY | AI25: USD | AJ25: USD | AK25: USD | AL25: USD | AM25: USD | AN25: CNY | AO25: CNY | AP25: USD | AQ25: BP | AR25: BP
A26: 交易场所 | B26: 场外 | C26: 中国外汇交易中心 | D26: Intercontinental Exchange | E26: 场外 | F26: 场外 | G26: 场外 | H26: 上海黄金交易所 | I26: 场外 | J26: 场外 | K26: 场外 | L26: 场外 | M26: 场外 | N26: 场外 | O26: 场外 | P26: 场外 | Q26: 中国金融期货交易所 | R26: 场外 | S26: 场外 | T26: 场外 | U26: 场外 | V26: 场外 | W26: 场外 | X26: 场外 | Y26: 场外 | Z26: 场外 | AA26: 场外 | AB26: 场外 | AC26: 场外 | AD26: 场外 | AE26: 场外 | AF26: 场外 | AG26: 场外 | AH26: 场外 | AI26: 场外 | AJ26: 场外 | AK26: 场外 | AL26: 场外 | AM26: 场外 | AN26: 场外 | AO26: 上海黄金交易所 | AP26: 场外 | AQ26: 场外 | AR26: 场外
A27: 交割方式 | B27: 全额 | C27: 净额 | D27: 全额 | E27: 全额 | F27: 全额 | G27: 全额 | H27: 全额 | I27: 差额 | J27: 差额 | K27: 差额 | L27: 差额 | M27: 全额 | N27: 全额 | O27: 差额 | P27: 差额 | Q27: 全额 | R27: 全额 | S27: 全额 | T27: 全额 | U27: 全额 | V27: 全额 | W27: 全额 | X27: 差额 | Y27: 差额 | Z27: 差额 | AA27: 差额 | AB27: 全额 | AC27: 全额 | AD27: 全额 | AE27: 差额 | AF27: 全额 | AG27: 差额 | AH27: 差额 | AI27: 差额 | AJ27: 差额 | AK27: 差额 | AL27: 差额 | AM27: 差额 | AN27: 差额 | AO27: 全额 | AP27: 差额 | AQ27: 差额 | AR27: 差额
A28: 期权类型 | AD28: 看涨 | AE28: 下限 | AF28: 上限 | AG28: 上限 | AH28: 下限 | AI28: 看涨 | AJ28: 看涨 | AK28: 看跌 | AL28: 看涨 | AM28: 看跌 | AN28: 其他-双边不触碰 | AP28: 看跌
A29: 行权方式 | AD29: 欧式 | AE29: 欧式 | AF29: 欧式 | AG29: 欧式 | AH29: 欧式 | AI29: 欧式 | AJ29: 欧式 | AK29: 欧式 | AL29: 欧式 | AM29: 美式 | AN29: 美式 | AP29: 欧式
A30: 行权价格 | AD30: 1000 | AE30: 0 | AF30: 150 | AG30: 405 | AH30: 380 | AI30: 17820000 | AJ30: 17820000 | AK30: 16500 | AL30: 1.135 | AM30: 1.15 | AP30: 200
A31: 行权价格单位 | AD31: USD | AE31: BP | AF31: BP | AG31: BP | AH31: BP | AI31: USD | AJ31: USD | AK31: USD | AL31: EURUSD | AM31: EURUSD | AP31: BP
A32: 保证金标志 | B32: 否 | C32: 否 | D32: 否 | E32: 是 | F32: 否 | G32: 否 | H32: 否 | I32: 否 | J32: 否 | K32: 是 | L32: 否 | M32: 是 | N32: 是 | O32: 否 | P32: 否 | Q32: 是 | R32: 否 | S32: 否 | T32: 是 | U32: 是 | V32: 是 | W32: 是 | X32: 否 | Y32: 否 | Z32: 否 | AA32: 否 | AB32: 否 | AC32: 否 | AD32: 否 | AE32: 否 | AF32: 否 | AG32: 否 | AH32: 否 | AI32: 否 | AJ32: 否 | AK32: 否 | AL32: 否 | AM32: 否 | AN32: 否 | AO32: 是 | AP32: 否 | AQ32: 否 | AR32: 否
A33: 主协议名称 | I33: ISDA;NAFMII | J33: ISDA;NAFMII | K33: NAFMII | M33: ISDA | R33: NAFMII | S33: NAFMII | T33: ISDA | U33: ISDA | V33: ISDA | W33: ISDA | X33: NAFMII | Y33: NAFMII | Z33: NAFMII | AA33: NAFMII | AB33: NAFMII | AC33: NAFMII | AD33: NAFMII | AF33: NAFMII | AI33: ISDA | AJ33: ISDA | AK33: NAFMII | AL33: ISDA | AM33: ISDA | AN33: NAFMII
A34: 中央交易对手 | C34: 上海清算所 | L34: 上海清算所 | Q34: 中国金融期货交易所
A35: 估值金额 | V35: 2812.5 | W35: 2812.5 | AJ35: 370000
A36: 估值币种 | V36: USD | W36: USD | AJ36: USD
A37: 估值日期 | V37: 20211215 | W37: 20211215 | AJ37: 20190531
A38: 交易员工号 | B38: XXX | C38: XXX | D38: XXX | E38: XXX | F38: XXX | G38: XXX | H38: XXX | I38: XXX | J38: XXX | K38: XXX | L38: XXX | M38: XXX | N38: XXX | O38: XXX | P38: XXX | Q38: XXX | R38: XXX | S38: XXX | T38: XXX | U38: XXX | V38: XXX | W38: XXX | X38: XXX | Y38: XXX | Z38: XXX | AA38: XXX | AB38: XXX | AC38: XXX | AD38: XXX | AE38: XXX | AF38: XXX | AG38: XXX | AH38: XXX | AI38: XXX | AJ38: XXX | AK38: XXX | AL38: XXX | AM38: XXX | AN38: XXX | AO38: XXX | AP38: XXX | AQ38: XXX | AR38: XXX
A39: 审批人工号 | B39: XXX | C39: XXX | D39: XXX | E39: XXX | F39: XXX | G39: XXX | H39: XXX | I39: XXX | J39: XXX | K39: XXX | L39: XXX | M39: XXX | N39: XXX | O39: XXX | P39: XXX | Q39: XXX | R39: XXX | S39: XXX | T39: XXX | U39: XXX | V39: XXX | W39: XXX | X39: XXX | Y39: XXX | Z39: XXX | AA39: XXX | AB39: XXX | AC39: XXX | AD39: XXX | AE39: XXX | AF39: XXX | AG39: XXX | AH39: XXX | AI39: XXX | AJ39: XXX | AK39: XXX | AL39: XXX | AM39: XXX | AN39: XXX | AO39: XXX | AP39: XXX | AQ39: XXX | AR39: XXX
A40: 备注 | B40: XXX | C40: XXX | D40: XXX | E40: XXX | F40: XXX | G40: XXX | H40: XXX | I40: XXX | J40: XXX | K40: XXX | L40: XXX | M40: XXX | N40: XXX | O40: XXX | P40: XXX | Q40: XXX | R40: XXX | S40: XXX | T40: XXX | U40: XXX | V40: XXX | W40: XXX | X40: XXX | Y40: XXX | Z40: XXX | AA40: XXX | AB40: XXX | AC40: XXX | AD40: XXX | AE40: XXX | AF40: XXX | AG40: XXX | AH40: XXX | AI40: XXX | AJ40: XXX | AK40: XXX | AL40: XXX | AM40: XXX | AN40: 1.105,1.16 | AO40: XXX | AP40: XXX | AQ40: XXX | AR40: XXX
A41: 采集日期 | B41: 20210630 | C41: 20211231 | D41: 20211231 | E41: 20211231 | F41: 20211231 | G41: 20211231 | H41: 20211231 | I41: 20211231 | J41: 20211231 | K41: 20211231 | L41: 20211231 | M41: 20211231 | N41: 20211231 | O41: 20211231 | P41: 20211231 | Q41: 20200430 | R41: 20210531 | S41: 20210531 | T41: 20211231 | U41: 20211231 | V41: 20211231 | W41: 20211231 | X41: 20201231 | Y41: 20201231 | Z41: 20200531 | AA41: 20200531 | AB41: 20211231 | AC41: 20191231 | AD41: 20211130 | AE41: 20211031 | AF41: 20210331 | AG41: 20210331 | AH41: 20210331 | AI41: 20190430 | AJ41: 20190531 | AK41: 20211231 | AL41: 20211231 | AM41: 20211231 | AN41: 20211231 | AO41: 20211231 | AP41: 20120630 | AQ41: 20120630 | AR41: 20120630
